Workbook
Name cMed: Config!$F$6
Name cMed2: Config!$F$7
Name cFecha: Config!$F$8
Name cCat1: Config!$F$9
Name cCat2: Config!$F$10
Name cEtapa: Config!$F$11
Name cDepto: Config!$F$12
Name cCosto: Config!$F$13
Name nFilas: Config!$C$16
Name fMin: Config!$C$17
Name fMax: Config!$C$18
Name gran: Config!$C$19
Name conHora: Config!$C$20
Name total: Config!$C$21
Name n1: Config!$C$22
Name n2: Config!$C$23
Name dona2: Config!$C$24
Name mIni: Config!$C$25
Name nomMed: Config!$C$26
Name tBase: Config!$C$27
Name fTexto: Config!$C$29
Name gIdx: Config!$C$28
Name rMed: INDEX(Datos!$A$2:$AN$1048576,1,MAX(1,cMed)):INDEX(Datos!$A$2:$AN$1048576,MAX(1,nFilas),MAX(1,cMed))
Name rMed2: INDEX(Datos!$A$2:$AN$1048576,1,MAX(1,cMed2)):INDEX(Datos!$A$2:$AN$1048576,MAX(1,nFilas),MAX(1,cMed2))
Name rFecha: INDEX(Datos!$A$2:$AN$1048576,1,MAX(1,cFecha)):INDEX(Datos!$A$2:$AN$1048576,MAX(1,nFilas),MAX(1,cFecha))
Name rCat1: INDEX(Datos!$A$2:$AN$1048576,1,MAX(1,cCat1)):INDEX(Datos!$A$2:$AN$1048576,MAX(1,nFilas),MAX(1,cCat1))
Name rCat2: INDEX(Datos!$A$2:$AN$1048576,1,MAX(1,cCat2)):INDEX(Datos!$A$2:$AN$1048576,MAX(1,nFilas),MAX(1,cCat2))
Name rEtapa: INDEX(Datos!$A$2:$AN$1048576,1,MAX(1,cEtapa)):INDEX(Datos!$A$2:$AN$1048576,MAX(1,nFilas),MAX(1,cEtapa))
Name rDepto: INDEX(Datos!$A$2:$AN$1048576,1,MAX(1,cDepto)):INDEX(Datos!$A$2:$AN$1048576,MAX(1,nFilas),MAX(1,cDepto))
Name rCosto: INDEX(Datos!$A$2:$AN$1048576,1,MAX(1,cCosto)):INDEX(Datos!$A$2:$AN$1048576,MAX(1,nFilas),MAX(1,cCosto))

Sheet Dashboard
B2: =IF(cMed>0,"Dashboard de "&nomMed,"Dashboard de análisis") -> Dashboard de Ventas
B3: =IF(fTexto<>"","⚠ La columna «"&fTexto&"» parece fecha pero está guardada como texto: selecciónala y usa Datos › Texto en columnas › Fecha (DMA). ","")&"Pega tus datos en la hoja Datos (encabezados en la fila 1) · "&FIXED(nFilas,0)&" registros · columnas elegidas en la hoja Config" -> Pega tus datos en la hoja Datos (encabezados en la fila 1) · 2,400 registros · columnas elegidas en la hoja Config
B5: =IF(cMed>0,UPPER(nomMed)&" TOTAL","REGISTROS") -> VENTAS TOTAL | F5: =IF(cMed>0,"REGISTROS",IF(cMed2>0,"PROMEDIO "&UPPER(Config!$E$7),IF(cCat2>0,UPPER(Config!$E$10)&" DISTINTOS","—"))) -> REGISTROS | J5: =IF(cMed>0,"PROMEDIO POR REGISTRO",IF(cEtapa>0,"% "&UPPER(Motor!$CB$14),"—")) -> PROMEDIO POR REGISTRO | N5: =IF(cCosto>0,"MARGEN",IF(AND(cMed>0,cEtapa>0),"% "&UPPER(Motor!$CB$14),IF(cCat1>0,UPPER(Config!$E$9)&" DISTINTOS","—"))) -> MARGEN
B6: =total -> 2006391920 | F6: =IF(cMed>0,IF(ABS(nFilas)>=1000000,FIXED(nFilas/1000000,1)&"M",IF(ABS(nFilas)>=1000,FIXED(nFilas/1000,1)&"K",FIXED(nFilas,IF(ABS(nFilas)<100,1,0)))),IF(cMed2>0,IF(ABS(Motor!$CB$11)>=1000000,FIXED(Motor!$CB$11/1000000,1)&"M",IF(ABS(Motor!$CB$11)>=1000,FIXED(Motor!$CB$11/1000,1)&"K",FIXED(Motor!$CB$11,IF(ABS(Motor!$CB$11)<100,1,0)))),IF(cCat2>0,IF(n2>=40,n2&"+",n2&""),""))) -> 2.4K | J6: =IF(cMed>0,IF(ABS(IFERROR(total/nFilas,0))>=1000000,FIXED(IFERROR(total/nFilas,0)/1000000,1)&"M",IF(ABS(IFERROR(total/nFilas,0))>=1000,FIXED(IFERROR(total/nFilas,0)/1000,1)&"K",FIXED(IFERROR(total/nFilas,0),IF(ABS(IFERROR(total/nFilas,0))<100,1,0)))),IF(cEtapa>0,ROUND(Motor!$CB$15*100,1)&"%","")) -> 836.0K | N6: =IF(cCosto>0,ROUND(Motor!$CB$10*100,1)&"%",IF(AND(cMed>0,cEtapa>0),ROUND(Motor!$CB$15*100,1)&"%",IF(cCat1>0,IF(n1>=40,n1&"+",n1&""),""))) -> 34.9%
B8: =IF(OR(cFecha=0,N(Motor!$CB$4)=0),"",IF(Motor!$CB$3>=Motor!$CB$4,"▲ ","▼ ")&ROUND(ABS(Motor!$CB$3/Motor!$CB$4-1)*100,1)&"% · "&Motor!$CB$9) -> ▲ 7.6% · Sep 25 vs Ago 25 | F8: =IF(cMed>0,IF(OR(cFecha=0,N(Motor!$CB$6)=0),"",IF(Motor!$CB$5>=Motor!$CB$6,"▲ ","▼ ")&ROUND(ABS(Motor!$CB$5/Motor!$CB$6-1)*100,1)&"% · "&Motor!$CB$9),IF(cMed2>0,IF(OR(cFecha=0,N(Motor!$CB$13)=0),"",IF(Motor!$CB$12>=Motor!$CB$13,"▲ ","▼ ")&ROUND(ABS(Motor!$CB$12/Motor!$CB$13-1)*100,1)&"% · "&Motor!$CB$9),"")) -> ▼ 18% · Sep 25 vs Ago 25 | J8: =IF(cMed>0,IF(OR(cFecha=0,N(IFERROR(Motor!$CB$4/Motor!$CB$6,0))=0),"",IF(IFERROR(Motor!$CB$3/Motor!$CB$5,0)>=IFERROR(Motor!$CB$4/Motor!$CB$6,0),"▲ ","▼ ")&ROUND(ABS(IFERROR(Motor!$CB$3/Motor!$CB$5,0)/IFERROR(Motor!$CB$4/Motor!$CB$6,0)-1)*100,1)&"% · "&Motor!$CB$9),IF(cEtapa>0,IF(cFecha=0,"",IF(Motor!$CB$16>=Motor!$CB$17,"▲ ","▼ ")&ROUND(ABS(Motor!$CB$16-Motor!$CB$17)*100,1)&" pp · "&Motor!$CB$9),"")) -> ▲ 31.3% · Sep 25 vs Ago 25 | N8: =IF(cCosto>0,IF(cFecha=0,"",IF(cFecha=0,"",IF(IFERROR((Motor!$CB$3-Motor!$CB$7)/Motor!$CB$3,0)>=IFERROR((Motor!$CB$4-Motor!$CB$8)/Motor!$CB$4,0),"▲ ","▼ ")&ROUND(ABS(IFERROR((Motor!$CB$3-Motor!$CB$7)/Motor!$CB$3,0)-IFERROR((Motor!$CB$4-Motor!$CB$8)/Motor!$CB$4,0))*100,1)&" pp · "&Motor!$CB$9)),IF(AND(cMed>0,cEtapa>0),IF(cFecha=0,"",IF(Motor!$CB$16>=Motor!$CB$17,"▲ ","▼ ")&ROUND(ABS(Motor!$CB$16-Motor!$CB$17)*100,1)&" pp · "&Motor!$CB$9),"")) -> ▲ 2.1 pp · Sep 25 vs Ago 25
B11: ="Tendencia de "&nomMed -> Tendencia de Ventas
B12: =IF(cFecha=0,"⚠ No hay columna de fecha: elígela en Config","Total por "&LOWER(gran)&" · se agrupa solo según el rango de fechas") -> Total por mes · se agrupa solo según el rango de fechas
B31: =IF(cCat1>0,"Ranking por "&Config!$E$9,"Ranking") -> Ranking por Ciudad | J31: ="Participación por "&IF(dona2,Config!$E$10,Config!$E$9) -> Participación por Categoría
B32: =IF(cCat1=0,"⚠ Elige una categoría en Config","Top 10 por "&nomMed&" · líder: "&Motor!$F$3) -> Top 10 por Ventas · líder: Bogotá | J32: =IF(cCat1=0,"⚠ Elige una categoría en Config","% de "&nomMed&" · top 5 + Otros") -> % de Ventas · top 5 + Otros
B51: ="Composición mensual por "&IF(cCat2>0,Config!$E$10,Config!$E$9) -> Composición mensual por Categoría | J51: ="Embudo"&IF(cEtapa>0," por "&Config!$E$11,"") -> Embudo por Etapa
B52: =IF(cFecha=0,"⚠ Necesita columna de fecha (Config)","Últimos 12 meses · barras apiladas") -> Últimos 12 meses · barras apiladas | J52: =IF(cEtapa=0,"⚠ Elige la columna de Etapa en Config (ej. Visita, Carrito, Compra)","Registros por etapa, de mayor a menor · la última es el "&ROUND(IFERROR(LOOKUP(2,1/(Motor!$BU$3:$BU$8<>""),Motor!$BU$3:$BU$8)/Motor!$BU$3,0)*100,1)&"% de la primera") -> Registros por etapa, de mayor a menor · la última es el 23.6% de la primera
B71: ="Matriz: "&IF(cCat1>0,Config!$E$9,"categoría")&" × mes" -> Matriz: Ciudad × mes
B72: =IF(OR(cFecha=0,cCat1=0),"⚠ Necesita fecha y categoría (Config)","Tabla dinámica de "&nomMed&" · últimos 6 meses · color según el valor") -> Tabla dinámica de Ventas · últimos 6 meses · color según el valor
B74: =Motor!AT$2 -> Ciudad | D74: =Motor!AU$2 -> Abr 25 | E74: =Motor!AV$2 -> May 25 | F74: =Motor!AW$2 -> Jun 25 | G74: =Motor!AX$2 -> Jul 25 | H74: =Motor!AY$2 -> Ago 25 | J74: =Motor!AZ$2 -> Sep 25 | K74: =Motor!BA$2 -> Total 6 meses
B75: =Motor!AT3 -> Bogotá | D75: =Motor!AU3 -> 30128910 | E75: =Motor!AV3 -> 32358815 | F75: =Motor!AW3 -> 30920975 | G75: =Motor!AX3 -> 19240210 | H75: =Motor!AY3 -> 31876865 | J75: =Motor!AZ3 -> 35966285 | K75: =Motor!BA3 -> 180492060
B76: =Motor!AT4 -> Medellín | D76: =Motor!AU4 -> 30561990 | E76: =Motor!AV4 -> 13583845 | F76: =Motor!AW4 -> 16902070 | G76: =Motor!AX4 -> 24227440 | H76: =Motor!AY4 -> 15921045 | J76: =Motor!AZ4 -> 12965950 | K76: =Motor!BA4 -> 114162340
B77: =Motor!AT5 -> Cali | D77: =Motor!AU5 -> 8882510 | E77: =Motor!AV5 -> 11355755 | F77: =Motor!AW5 -> 22180125 | G77: =Motor!AX5 -> 16910820 | H77: =Motor!AY5 -> 6750730 | J77: =Motor!AZ5 -> 7444840 | K77: =Motor!BA5 -> 73524780
B78: =Motor!AT6 -> Barranquilla | D78: =Motor!AU6 -> 10780135 | E78: =Motor!AV6 -> 3684460 | F78: =Motor!AW6 -> 20292940 | G78: =Motor!AX6 -> 12220070 | H78: =Motor!AY6 -> 4140075 | J78: =Motor!AZ6 -> 10155800 | K78: =Motor!BA6 -> 61273480
B79: =Motor!AT7 -> Bucaramanga | D79: =Motor!AU7 -> 2680175 | E79: =Motor!AV7 -> 6900755 | F79: =Motor!AW7 -> 6026550 | G79: =Motor!AX7 -> 10151115 | H79: =Motor!AY7 -> 7189000 | J79: =Motor!AZ7 -> 13641035 | K79: =Motor!BA7 -> 46588630
B80: =Motor!AT8 -> Pereira | D80: =Motor!AU8 -> 7650620 | E80: =Motor!AV8 -> 5065660 | F80: =Motor!AW8 -> 10577850 | G80: =Motor!AX8 -> 7159585 | H80: =Motor!AY8 -> 14545595 | J80: =Motor!AZ8 -> 2134000 | K80: =Motor!BA8 -> 47133310
B81: =Motor!AT9 -> Cartagena | D81: =Motor!AU9 -> 6017050 | E81: =Motor!AV9 -> 12168985 | F81: =Motor!AW9 -> 5831180 | G81: =Motor!AX9 -> 14656260 | H81: =Motor!AY9 -> 4863045 | J81: =Motor!AZ9 -> 1270100 | K81: =Motor!BA9 -> 44806620
B82: =Motor!AT10 -> Villavicencio | D82: =Motor!AU10 -> 0 | E82: =Motor!AV10 -> 3200380 | F82: =Motor!AW10 -> 2478015 | G82: =Motor!AX10 -> 7442895 | H82: =Motor!AY10 -> 2106405 | J82: =Motor!AZ10 -> 4088675 | K82: =Motor!BA10 -> 19316370
B83: =Motor!AT11 -> Pasto | D83: =Motor!AU11 -> 3468090 | E83: =Motor!AV11 -> 6147200 | F83: =Motor!AW11 -> 5519700 | G83: =Motor!AX11 -> 4104500 | H83: =Motor!AY11 -> 1007170 | J83: =Motor!AZ11 -> 6914160 | K83: =Motor!BA11 -> 27160820
B84: =Motor!AT12 -> Neiva | D84: =Motor!AU12 -> 432810 | E84: =Motor!AV12 -> 5456970 | F84: =Motor!AW12 -> 2449625 | G84: =Motor!AX12 -> 2408580 | H84: =Motor!AY12 -> 547495 | J84: =Motor!AZ12 -> 1162800 | K84: =Motor!BA12 -> 12458280
B87: ="Mapa de Colombia por "&IF(cDepto>0,Config!$E$12,"departamento") -> Mapa de Colombia por Departamento | J87: ="Top 5 departamentos" -> Top 5 departamentos
B88: =IF(cDepto=0,"⚠ Elige la columna de Departamento en Config","Mosaico por departamento · más oscuro = mayor "&nomMed) -> Mosaico por departamento · más oscuro = mayor Ventas | J88: ="Participación sobre el total de "&nomMed -> Participación sobre el total de Ventas
B89: =N(Motor!$BN$3) -> 0 | G89: =N(Motor!$BN$4) -> 0
B90: =IF(N(Motor!$BN$3)=0,"",Motor!$BN$3) | G90: =IF(N(Motor!$BN$4)=0,"",Motor!$BN$4) | J90: Departamento | M90: =nomMed -> Ventas | P90: %
E91: =N(Motor!$BN$5) -> 174627110 | F91: =N(Motor!$BN$6) -> 0 | G91: =N(Motor!$BN$7) -> 0 | J91: =Motor!$BP$3 -> Bogotá D.C. | M91: =Motor!$BQ$3 -> 554388700 | P91: =IF(Motor!$BQ$3="","",IFERROR(Motor!$BQ$3/total,"")) -> 0.27631127
E92: =IF(N(Motor!$BN$5)=0,"",Motor!$BN$5) -> 174627110 | F92: =IF(N(Motor!$BN$6)=0,"",Motor!$BN$6) | G92: =IF(N(Motor!$BN$7)=0,"",Motor!$BN$7)
D93: =N(Motor!$BN$8) -> 0 | E93: =N(Motor!$BN$9) -> 0 | F93: =N(Motor!$BN$10) -> 128977510 | G93: =N(Motor!$BN$11) -> 0 | J93: =Motor!$BP$4 -> Antioquia | M93: =Motor!$BQ$4 -> 410638375 | P93: =IF(Motor!$BQ$4="","",IFERROR(Motor!$BQ$4/total,"")) -> 0.20466509
D94: =IF(N(Motor!$BN$8)=0,"",Motor!$BN$8) | E94: =IF(N(Motor!$BN$9)=0,"",Motor!$BN$9) | F94: =IF(N(Motor!$BN$10)=0,"",Motor!$BN$10) -> 128977510 | G94: =IF(N(Motor!$BN$11)=0,"",Motor!$BN$11)
C95: =N(Motor!$BN$12) -> 0 | D95: =N(Motor!$BN$13) -> 410638375 | F95: =N(Motor!$BN$14) -> 140976355 | G95: =N(Motor!$BN$15) -> 0 | J95: =Motor!$BP$5 -> Valle del Cauca | M95: =Motor!$BQ$5 -> 260852225 | P95: =IF(Motor!$BQ$5="","",IFERROR(Motor!$BQ$5/total,"")) -> 0.1300106
C96: =IF(N(Motor!$BN$12)=0,"",Motor!$BN$12) | D96: =IF(N(Motor!$BN$13)=0,"",Motor!$BN$13) -> 410638375 | F96: =IF(N(Motor!$BN$14)=0,"",Motor!$BN$14) -> 140976355 | G96: =IF(N(Motor!$BN$15)=0,"",Motor!$BN$15)
C97: =N(Motor!$BN$16) -> 135285040 | D97: =N(Motor!$BN$17) -> 0 | E97: =N(Motor!$BN$18) -> 0 | F97: =N(Motor!$BN$19) -> 0 | G97: =N(Motor!$BN$20) -> 0 | H97: =N(Motor!$BN$21) -> 0 | J97: =Motor!$BP$6 -> Atlántico | M97: =Motor!$BQ$6 -> 174627110 | P97: =IF(Motor!$BQ$6="","",IFERROR(Motor!$BQ$6/total,"")) -> 0.087035393
C98: =IF(N(Motor!$BN$16)=0,"",Motor!$BN$16) -> 135285040 | D98: =IF(N(Motor!$BN$17)=0,"",Motor!$BN$17) | E98: =IF(N(Motor!$BN$18)=0,"",Motor!$BN$18) | F98: =IF(N(Motor!$BN$19)=0,"",Motor!$BN$19) | G98: =IF(N(Motor!$BN$20)=0,"",Motor!$BN$20) | H98: =IF(N(Motor!$BN$21)=0,"",Motor!$BN$21)
C99: =N(Motor!$BN$22) -> 260852225 | D99: =N(Motor!$BN$23) -> 0 | E99: =N(Motor!$BN$24) -> 0 | F99: =N(Motor!$BN$25) -> 554388700 | G99: =N(Motor!$BN$26) -> 83519275 | H99: =N(Motor!$BN$27) -> 0 | J99: =Motor!$BP$7 -> Santander | M99: =Motor!$BQ$7 -> 140976355 | P99: =IF(Motor!$BQ$7="","",IFERROR(Motor!$BQ$7/total,"")) -> 0.070263618
C100: =IF(N(Motor!$BN$22)=0,"",Motor!$BN$22) -> 260852225 | D100: =IF(N(Motor!$BN$23)=0,"",Motor!$BN$23) | E100: =IF(N(Motor!$BN$24)=0,"",Motor!$BN$24) | F100: =IF(N(Motor!$BN$25)=0,"",Motor!$BN$25) -> 554388700 | G100: =IF(N(Motor!$BN$26)=0,"",Motor!$BN$26) -> 83519275 | H100: =IF(N(Motor!$BN$27)=0,"",Motor!$BN$27)
C101: =N(Motor!$BN$28) -> 0 | D101: =N(Motor!$BN$29) -> 48591155 | E101: =N(Motor!$BN$30) -> 0 | F101: =N(Motor!$BN$31) -> 0 | G101: =N(Motor!$BN$32) -> 0
C102: =IF(N(Motor!$BN$28)=0,"",Motor!$BN$28) | D102: =IF(N(Motor!$BN$29)=0,"",Motor!$BN$29) -> 48591155 | E102: =IF(N(Motor!$BN$30)=0,"",Motor!$BN$30) | F102: =IF(N(Motor!$BN$31)=0,"",Motor!$BN$31) | G102: =IF(N(Motor!$BN$32)=0,"",Motor!$BN$32)
C103: =N(Motor!$BN$33) -> 68536175 | D103: =N(Motor!$BN$34) -> 0 | F103: =N(Motor!$BN$35) -> 0
C104: =IF(N(Motor!$BN$33)=0,"",Motor!$BN$33) -> 68536175 | D104: =IF(N(Motor!$BN$34)=0,"",Motor!$BN$34) | F104: =IF(N(Motor!$BN$35)=0,"",Motor!$BN$35)
B108: ="Relación "&nomMed&IF(cMed2>0," vs "&Config!$E$7,"") -> Relación Ventas vs Unidades | J108: =IF(cCat2>0,"Ranking por "&Config!$E$10,"Segunda categoría") -> Ranking por Categoría
B109: =IF(OR(cMed=0,cMed2=0),"⚠ Necesita dos columnas numéricas: elige Medida principal y secundaria en Config","Eje X: "&Config!$E$7&" · eje Y: "&nomMed&" · hasta 5,000 registros") -> Eje X: Unidades · eje Y: Ventas · hasta 5,000 registros | J109: =IF(cCat2=0,"⚠ No hay segunda categoría: elígela en Config","Top 10 por "&nomMed) -> Top 10 por Ventas
B128: ="Mapa de calor: "&IF(conHora,"hora","mes")&" × día de la semana" -> Mapa de calor: hora × día de la semana
B129: =IF(cFecha=0,"⚠ Necesita columna de fecha (Config)","Detecta patrones: más oscuro = mayor "&nomMed) -> Detecta patrones: más oscuro = mayor Ventas
B130: =Motor!BC2 -> Hora | D130: =Motor!BD2 -> Lun | E130: =Motor!BE2 -> Mar | F130: =Motor!BF2 -> Mié | G130: =Motor!BG2 -> Jue | H130: =Motor!BH2 -> Vie | J130: =Motor!BI2 -> Sáb | K130: =Motor!BJ2 -> Dom
B131: =Motor!BC3 -> 00:00 | D131: =Motor!BD3 -> 803400 | E131: =Motor!BE3 -> 0 | F131: =Motor!BF3 -> 10614400 | G131: =Motor!BG3 -> 1100500 | H131: =Motor!BH3 -> 8034065 | J131: =Motor!BI3 -> 2306205 | K131: =Motor!BJ3 -> 3878490
B132: =Motor!BC4 -> 01:00 | D132: =Motor!BD4 -> 347200 | E132: =Motor!BE4 -> 328440 | F132: =Motor!BF4 -> 919540 | G132: =Motor!BG4 -> 0 | H132: =Motor!BH4 -> 0 | J132: =Motor!BI4 -> 530380 | K132: =Motor!BJ4 -> 1190320
B133: =Motor!BC5 -> 02:00 | D133: =Motor!BD5 -> 2838400 | E133: =Motor!BE5 -> 393300 | F133: =Motor!BF5 -> 2818700 | G133: =Motor!BG5 -> 358400 | H133: =Motor!BH5 -> 0 | J133: =Motor!BI5 -> 0 | K133: =Motor!BJ5 -> 0
B134: =Motor!BC6 -> 03:00 | D134: =Motor!BD6 -> 600400 | E134: =Motor!BE6 -> 0 | F134: =Motor!BF6 -> 233900 | G134: =Motor!BG6 -> 0 | H134: =Motor!BH6 -> 3934265 | J134: =Motor!BI6 -> 0 | K134: =Motor!BJ6 -> 0
B135: =Motor!BC7 -> 04:00 | D135: =Motor!BD7 -> 0 | E135: =Motor!BE7 -> 0 | F135: =Motor!BF7 -> 5488200 | G135: =Motor!BG7 -> 4529700 | H135: =Motor!BH7 -> 810060 | J135: =Motor!BI7 -> 0 | K135: =Motor!BJ7 -> 0
B136: =Motor!BC8 -> 05:00 | D136: =Motor!BD8 -> 2708880 | E136: =Motor!BE8 -> 255500 | F136: =Motor!BF8 -> 0 | G136: =Motor!BG8 -> 5433500 | H136: =Motor!BH8 -> 4567800 | J136: =Motor!BI8 -> 267490 | K136: =Motor!BJ8 -> 376740
B137: =Motor!BC9 -> 06:00 | D137: =Motor!BD9 -> 5531900 | E137: =Motor!BE9 -> 2614700 | F137: =Motor!BF9 -> 1861400 | G137: =Motor!BG9 -> 712960 | H137: =Motor!BH9 -> 5106345 | J137: =Motor!BI9 -> 1114120 | K137: =Motor!BJ9 -> 1663820
B138: =Motor!BC10 -> 07:00 | D138: =Motor!BD10 -> 6615240 | E138: =Motor!BE10 -> 9530000 | F138: =Motor!BF10 -> 4455300 | G138: =Motor!BG10 -> 6244520 | H138: =Motor!BH10 -> 8408925 | J138: =Motor!BI10 -> 9118195 | K138: =Motor!BJ10 -> 3423305
B139: =Motor!BC11 -> 08:00 | D139: =Motor!BD11 -> 5837900 | E139: =Motor!BE11 -> 3926640 | F139: =Motor!BF11 -> 5628680 | G139: =Motor!BG11 -> 17055300 | H139: =Motor!BH11 -> 19051475 | J139: =Motor!BI11 -> 18744080 | K139: =Motor!BJ11 -> 11852665
B140: =Motor!BC12 -> 09:00 | D140: =Motor!BD12 -> 24648480 | E140: =Motor!BE12 -> 8029860 | F140: =Motor!BF12 -> 29334020 | G140: =Motor!BG12 -> 21157860 | H140: =Motor!BH12 -> 17739255 | J140: =Motor!BI12 -> 14905345 | K140: =Motor!BJ12 -> 26239235
B141: =Motor!BC13 -> 10:00 | D141: =Motor!BD13 -> 7754680 | E141: =Motor!BE13 -> 14570580 | F141: =Motor!BF13 -> 17103780 | G141: =Motor!BG13 -> 11598120 | H141: =Motor!BH13 -> 12956225 | J141: =Motor!BI13 -> 14086155 | K141: =Motor!BJ13 -> 15497715
... B154: =Motor!BC26 -> 23:00 | D154: =Motor!BD26 -> 6042800 | E154: =Motor!BE26 -> 617880 | F154: =Motor!BF26 -> 6211080 | G154: =Motor!BG26 -> 4108960 | H154: =Motor!BH26 -> 6298645 | J154: =Motor!BI26 -> 5190200 | K154: =Motor!BJ26 -> 11527090

Sheet Datos
A1: ID Pedido | B1: Fecha | C1: Departamento | D1: Ciudad | E1: Categoría | F1: Canal | G1: Etapa | H1: Unidades | I1: Precio unitario | J1: Ventas | K1: Costo
A2: 10619 | B2: 45383.456 | C2: Bogotá D.C. | D2: Bogotá | E2: Hogar | F2: Web | G2: 3. Pago | H2: 3 | I2: 258900 | J2: 776700 | K2: 485128
A3: 11465 | B3: 45383.538 | C3: Atlántico | D3: Barranquilla | E3: Juguetes | F3: Web | G3: 1. Visita | H3: 2 | I3: 75400 | J3: 150800 | K3: 91694
A4: 10495 | B4: 45383.563 | C4: Valle del Cauca | D4: Cali | E4: Deportes | F4: Web | G4: 1. Visita | H4: 2 | I4: 157000 | J4: 314000 | K4: 231304
A5: 10928 | B5: 45384.537 | C5: Valle del Cauca | D5: Cali | E5: Tecnología | F5: App | G5: 4. Compra | H5: 2 | I5: 719200 | J5: 1438400 | K5: 1052322
A6: 10700 | B6: 45384.54 | C6: Nariño | D6: Pasto | E6: Deportes | F6: Web | G6: 1. Visita | H6: 1 | I6: 136000 | J6: 136000 | K6: 94504
A7: 11314 | B7: 45384.617 | C7: Valle del Cauca | D7: Cali | E7: Hogar | F7: Web | G7: 2. Carrito | H7: 2 | I7: 238200 | J7: 476400 | K7: 340091
A8: 11434 | B8: 45384.759 | C8: Valle del Cauca | D8: Cali | E8: Belleza | F8: App | G8: 1. Visita | H8: 5 | I8: 61800 | J8: 309000 | K8: 175437
A9: 10419 | B9: 45385.831 | C9: Bolívar | D9: Cartagena | E9: Deportes | F9: Web | G9: 3. Pago | H9: 4 | I9: 206000 | J9: 824000 | K9: 568816
A10: 10016 | B10: 45386.376 | C10: Valle del Cauca | D10: Cali | E10: Hogar | F10: App | G10: 1. Visita | H10: 4 | I10: 187900 | J10: 751600 | K10: 433021
A11: 12082 | B11: 45386.466 | C11: Bogotá D.C. | D11: Bogotá | E11: Hogar | F11: App | G11: 1. Visita | H11: 4 | I11: 268600 | J11: 1074400 | K11: 752326
A12: 11210 | B12: 45386.478 | C12: Bogotá D.C. | D12: Bogotá | E12: Hogar | F12: Web | G12: 3. Pago | H12: 4 | I12: 147700 | J12: 590800 | K12: 355322
A13: 10299 | B13: 45386.628 | C13: Meta | D13: Villavicencio | E13: Hogar | F13: Tienda física | G13: 2. Carrito | H13: 5 | I13: 223100 | J13: 1115500 | K13: 665555
... A2401: 12282 | B2401: 45922.936 | C2401: Atlántico | D2401: Barranquilla | E2401: Juguetes | F2401: App | G2401: 2. Carrito | H2401: 4 | I2401: 103700 | J2401: 414800 | K2401: 278656

Sheet Config
B1: Configuración del tablero
B2: La plantilla elige sola las columnas (columna C). Si quieres otra, escógela en la columna amarilla D; para volver a la automática, borra la celda amarilla.
B5: Uso en el tablero | C5: Detección automática | D5: Tu elección (opcional) | E5: En uso | F5: Col.
B6: Medida principal (lo que se suma) | C6: =IF(MAX($I$40:$I$79)>10,INDEX($B$40:$B$79,MATCH(MAX($I$40:$I$79),$I$40:$I$79,0)),"") -> Ventas | E6: =IF(D6<>"",D6,C6) -> Ventas | F6: =IF(E6="",0,IFERROR(MATCH(E6,Datos!$A$1:$AN$1,0),0)) -> 10
B7: Medida secundaria (eje X dispersión) | C7: =IF(MAX($P$40:$P$79)>0,INDEX($B$40:$B$79,MATCH(MAX($P$40:$P$79),$P$40:$P$79,0)),"") -> Unidades | E7: =IF(D7<>"",D7,C7) -> Unidades | F7: =IF(E7="",0,IFERROR(MATCH(E7,Datos!$A$1:$AN$1,0),0)) -> 8
B8: Fecha | C8: =IF(MAX($L$40:$L$79)>0,INDEX($B$40:$B$79,MATCH(MAX($L$40:$L$79),$L$40:$L$79,0)),"") -> Fecha | E8: =IF(D8<>"",D8,C8) -> Fecha | F8: =IF(E8="",0,IFERROR(MATCH(E8,Datos!$A$1:$AN$1,0),0)) -> 2
B9: Categoría principal | C9: =IF(MAX($J$40:$J$79)>0,INDEX($B$40:$B$79,MATCH(MAX($J$40:$J$79),$J$40:$J$79,0)),"") -> Ciudad | E9: =IF(D9<>"",D9,C9) -> Ciudad | F9: =IF(E9="",0,IFERROR(MATCH(E9,Datos!$A$1:$AN$1,0),0)) -> 4
B10: Categoría secundaria | C10: =IF(MAX($Q$40:$Q$79)>0,INDEX($B$40:$B$79,MATCH(MAX($Q$40:$Q$79),$Q$40:$Q$79,0)),"") -> Categoría | E10: =IF(D10<>"",D10,C10) -> Categoría | F10: =IF(E10="",0,IFERROR(MATCH(E10,Datos!$A$1:$AN$1,0),0)) -> 5
B11: Etapa (embudo) | C11: =IF(MAX($M$40:$M$79)>0,INDEX($B$40:$B$79,MATCH(MAX($M$40:$M$79),$M$40:$M$79,0)),"") -> Etapa | E11: =IF(D11<>"",D11,C11) -> Etapa | F11: =IF(E11="",0,IFERROR(MATCH(E11,Datos!$A$1:$AN$1,0),0)) -> 7
B12: Departamento (mapa) | C12: =IF(MAX($N$40:$N$79)>0,INDEX($B$40:$B$79,MATCH(MAX($N$40:$N$79),$N$40:$N$79,0)),"") -> Departamento | E12: =IF(D12<>"",D12,C12) -> Departamento | F12: =IF(E12="",0,IFERROR(MATCH(E12,Datos!$A$1:$AN$1,0),0)) -> 3
B13: Costo (para el margen) | C13: =IF(MAX($R$40:$R$79)>0,INDEX($B$40:$B$79,MATCH(MAX($R$40:$R$79),$R$40:$R$79,0)),"") -> Costo | E13: =IF(D13<>"",D13,C13) -> Costo | F13: =IF(E13="",0,IFERROR(MATCH(E13,Datos!$A$1:$AN$1,0),0)) -> 11
B15: Valores calculados
B16: Filas de datos | C16: =MAX(C40:C79) -> 2400
B17: Fecha mínima | C17: =IF(cFecha>0,MIN(rFecha),"") -> 45383.456
B18: Fecha máxima | C18: =IF(cFecha>0,MAX(rFecha),"") -> 45922.936
B19: Agrupación de la tendencia | C19: =IF(cFecha=0,"",IF(INT(fMax)-INT(fMin)<24,"Día",IF(INT(fMax)-INT(fMin)<168,"Semana",IF(INT(fMax)-INT(fMin)<730,"Mes",IF(INT(fMax)-INT(fMin)<2190,"Trimestre","Año"))))) -> Mes
B20: La fecha incluye hora | C20: =IF(cFecha>0,IFERROR(SUMPRODUCT(--(MOD(rFecha,1)>0))>0,FALSE),FALSE) -> TRUE
B21: Total de la medida | C21: =IF(cMed>0,SUM(rMed),nFilas) -> 2006391920
B22: Valores distintos categoría principal | C22: =SUMPRODUCT(--(Motor!$B$3:$B$42<>"")) -> 10
B23: Valores distintos categoría secundaria | C23: =SUMPRODUCT(--(Motor!$K$3:$K$42<>"")) -> 6
B24: Dona usa la categoría secundaria | C24: =AND(cCat2>0,n2>=2,n2<n1) -> TRUE
B25: Inicio del último mes | C25: =IF(cFecha>0,DATE(YEAR(fMax),MONTH(fMax),1),"") -> 45901
B26: Nombre de la medida | C26: =IF(cMed>0,$E$6,"Registros") -> Ventas
B27: Inicio del primer período | C27: =IF(cFecha=0,"",CHOOSE(gIdx,INT(fMin),INT(fMin)-WEEKDAY(fMin,2)+1,DATE(YEAR(fMin),MONTH(fMin),1),DATE(YEAR(fMin),3*INT((MONTH(fMin)-1)/3)+1,1),DATE(YEAR(fMin),1,1))) -> 45383
B28: Índice de agrupación | C28: =IFERROR(MATCH(gran,{"Día","Semana","Mes","Trimestre","Año"},0),3) -> 3
B29: Columna de fecha guardada como texto | C29: =IF(cFecha>0,"",IFERROR(INDEX($B$40:$B$79,MATCH(TRUE,$S$40:$S$79,0)),""))
B38: Perfil automático de columnas (no editar)
A39: # | B39: Encabezado | C39: Celdas | D39: Numéricas | E39: ¿Fecha? | F39: ¿Número? | G39: Texto norm. | H39: ¿Texto? | I39: P. medida | J39: P. categoría | K39: Distintos (500) | L39: P. fecha | M39: P. etapa | N39: P. depto | O39: P. costo | P39: P. medida 2 | Q39: P. categoría 2 | R39: P. costo 2 | S39: ¿Fecha en texto?
A40: 1 | B40: =IF(INDEX(Datos!$A$1:$AN$1,1,1)="","",INDEX(Datos!$A$1:$AN$1,1,1)&"") -> ID Pedido | C40: =IF(B40="",0,COUNTA(INDEX(Datos!$A$2:$AN$1048576,0,1))) -> 2400 | D40: =IF(B40="",0,COUNT(INDEX(Datos!$A$2:$AN$1048576,0,1))) -> 2400 | E40: =AND(C40>0,D40>=0.9*C40,OR(LEFT(CELL("format",INDEX(Datos!$A$2:$AN$2,1,1)),1)="D",MIN(1,SUMPRODUCT(--ISNUMBER(SEARCH({"fecha","date","periodo","timestamp"},G40))))>0)) -> FALSE | F40: =AND(C40>0,D40>=0.9*C40,NOT(E40),MIN(1,SUMPRODUCT(--ISNUMBER(SEARCH({" id "," id"," cod"," nit "," cedula"," cédula"," telefono"," teléfono"," celular"," sku"," factura"," numero"," número"," nro"," año "," ano "," year"," zip"," postal"," documento"," guia"," guía"," orden"," cuenta"," pedido"," radicado"," consecutivo"," omr"," pob "," placa"," referencia"," ref "},G40))))=0,NOT(AND(K40>=20,K40>=0.95*MIN(500,C40),MIN(1,SUMPRODUCT(--ISNUMBER(SEARCH({"venta","ingreso","monto","importe","total","valor","factur","revenue","sales","amount","utilidad","ganancia","gasto"},G40))))+MIN(1,SUMPRODUCT(--ISNUMBER(SEARCH({"precio","price","unit","costo","cost","promedio","tasa","%","edad","calific","rating","puntaje","porcentaje","satisf","nps","score","nota"},G40))))+MIN(1,SUMPRODUCT(--ISNUMBER(SEARCH({"costo","cost"},G40))))+MIN(1,SUMPRODUCT(--ISNUMBER(SEARCH({" dias"," días","tiempo","demora","duraci","lead"," horas"},G40))))+MIN(1,SUMPRODUCT(--ISNUMBER(SEARCH({"cantidad","unidades","qty","peso","kilos"," kg","volumen","stock","existencia","inventario"},G40))))=0))) -> FALSE | G40: =" "&LOWER(SUBSTITUTE(SUBSTITUTE(SUBSTITUTE(B40,"_"," "),"-"," "),"."," "))&" " -> id pedido | H40: =AND(C40>0,D40<0.5*C40) -> FALSE | I40: =IF(F40,2+10*MIN(1,SUMPRODUCT(--ISNUMBER(SEARCH({"venta","ingreso","monto","importe","total","valor","factur","revenue","sales","amount","utilidad","ganancia","gasto"},G40))))+8*MIN(1,SUMPRODUCT(--ISNUMBER(SEARCH({"cantidad","unidades","qty","peso","kilos"," kg","volumen","stock","existencia","inventario"},G40))))*(1-MIN(1,SUMPRODUCT(--ISNUMBER(SEARCH({"venta","ingreso","monto","importe","total","valor","factur","revenue","sales","amount","utilidad","ganancia","gasto"},G40)))))-MIN(1,SUMPRODUCT(--ISNUMBER(SEARCH({"precio","price","unit","costo","cost","promedio","tasa","%","edad","calific","rating","puntaje","porcentaje","satisf","nps","score","nota"},G40))))+0.040,0) -> 0 | J40: =IF(AND(H40,K40>=2),IF(K40<=40,2+10*MIN(1,SUMPRODUCT(--ISNUMBER(SEARCH({"categor","region","región","producto","linea","línea","segmento","canal","ciudad","tienda","sucursal","vendedor","cliente","tipo","marca","zona","sede","courier","transportadora","oficina","trayecto","motivo","clasifica","proceso"},G40))))+3*AND(K40>=4,K40<=25),0.5+MIN(1,SUMPRODUCT(--ISNUMBER(SEARCH({"categor","region","región","producto","linea","línea","segmento","canal","ciudad","tienda","sucursal","vendedor","cliente","tipo","marca","zona","sede","courier","transportadora","oficina","trayecto","motivo","clasifica","proceso"},G40)))))+0.040,0) -> 0 | K40: =IF(C40>0,SUMPRODUCT((INDEX(Datos!$A$2:$AN$501,0,1)<>"")/COUNTIF(INDEX(Datos!$A$2:$AN$501,0,1),INDEX(Datos!$A$2:$AN$501,0,1)&"")),0) -> 500 | L40: =IF(E40,1+MIN(1,SUMPRODUCT(--ISNUMBER(SEARCH({"fecha","date","periodo","timestamp"},G40))))+0.040,0) -> 0 | M40: =IF(AND(H40,K40>=2,K40<=15),MIN(1,SUMPRODUCT(--ISNUMBER(SEARCH({"etapa","fase","estado","stage","embudo","funnel","paso","status"},G40))))*(1+0.040),0) -> 0 | N40: =IF(H40,MIN(1,SUMPRODUCT(--ISNUMBER(SEARCH({"departamento","depto","dpto","depart"},G40))))*(1+0.040),0) -> 0 | O40: =IF(F40,MIN(1,SUMPRODUCT(--ISNUMBER(SEARCH({"costo","cost"},G40))))*(1+0.040),0) -> 0 | P40: =IF(B40=$E$6,0,I40+5*MIN(1,SUMPRODUCT(--ISNUMBER(SEARCH({" dias"," días","tiempo","demora","duraci","lead"," horas"},G40))))*(I40>0)) -> 0 | Q40: =IF(B40=$E$9,0,J40) -> 0 | R40: =IF(OR(B40=$E$6,INDEX($I$40:$I$79,MAX(1,$F$6))<12),0,O40) -> 0 | S40: =AND(C40>0,D40<0.5*C40,MIN(1,SUMPRODUCT(--ISNUMBER(SEARCH({"fecha","date","periodo","timestamp"},G40))))>0) -> FALSE
A41: 2 | B41: =IF(INDEX(Datos!$A$1:$AN$1,1,2)="","",INDEX(Datos!$A$1:$AN$1,1,2)&"") -> Fecha | C41: =IF(B41="",0,COUNTA(INDEX(Datos!$A$2:$AN$1048576,0,2))) -> 2400 | D41: =IF(B41="",0,COUNT(INDEX(Datos!$A$2:$AN$1048576,0,2))) -> 2400 | E41: =AND(C41>0,D41>=0.9*C41,OR(LEFT(CELL("format",INDEX(Datos!$A$2:$AN$2,1,2)),1)="D",MIN(1,SUMPRODUCT(--ISNUMBER(SEARCH({"fecha","date","periodo","timestamp"},G41))))>0)) -> TRUE | F41: =AND(C41>0,D41>=0.9*C41,NOT(E41),MIN(1,SUMPRODUCT(--ISNUMBER(SEARCH({" id "," id"," cod"," nit "," cedula"," cédula"," telefono"," teléfono"," celular"," sku"," factura"," numero"," número"," nro"," año "," ano "," year"," zip"," postal"," documento"," guia"," guía"," orden"," cuenta"," pedido"," radicado"," consecutivo"," omr"," pob "," placa"," referencia"," ref "},G41))))=0,NOT(AND(K41>=20,K41>=0.95*MIN(500,C41),MIN(1,SUMPRODUCT(--ISNUMBER(SEARCH({"venta","ingreso","monto","importe","total","valor","factur","revenue","sales","amount","utilidad","ganancia","gasto"},G41))))+MIN(1,SUMPRODUCT(--ISNUMBER(SEARCH({"precio","price","unit","costo","cost","promedio","tasa","%","edad","calific","rating","puntaje","porcentaje","satisf","nps","score","nota"},G41))))+MIN(1,SUMPRODUCT(--ISNUMBER(SEARCH({"costo","cost"},G41))))+MIN(1,SUMPRODUCT(--ISNUMBER(SEARCH({" dias"," días","tiempo","demora","duraci","lead"," horas"},G41))))+MIN(1,SUMPRODUCT(--ISNUMBER(SEARCH({"cantidad","unidades","qty","peso","kilos"," kg","volumen","stock","existencia","inventario"},G41))))=0))) -> FALSE | G41: =" "&LOWER(SUBSTITUTE(SUBSTITUTE(SUBSTITUTE(B41,"_"," "),"-"," "),"."," "))&" " -> fecha | H41: =AND(C41>0,D41<0.5*C41) -> FALSE | I41: =IF(F41,2+10*MIN(1,SUMPRODUCT(--ISNUMBER(SEARCH({"venta","ingreso","monto","importe","total","valor","factur","revenue","sales","amount","utilidad","ganancia","gasto"},G41))))+8*MIN(1,SUMPRODUCT(--ISNUMBER(SEARCH({"cantidad","unidades","qty","peso","kilos"," kg","volumen","stock","existencia","inventario"},G41))))*(1-MIN(1,SUMPRODUCT(--ISNUMBER(SEARCH({"venta","ingreso","monto","importe","total","valor","factur","revenue","sales","amount","utilidad","ganancia","gasto"},G41)))))-MIN(1,SUMPRODUCT(--ISNUMBER(SEARCH({"precio","price","unit","costo","cost","promedio","tasa","%","edad","calific","rating","puntaje","porcentaje","satisf","nps","score","nota"},G41))))+0.039,0) -> 0 | J41: =IF(AND(H41,K41>=2),IF(K41<=40,2+10*MIN(1,SUMPRODUCT(--ISNUMBER(SEARCH({"categor","region","región","producto","linea","línea","segmento","canal","ciudad","tienda","sucursal","vendedor","cliente","tipo","marca","zona","sede","courier","transportadora","oficina","trayecto","motivo","clasifica","proceso"},G41))))+3*AND(K41>=4,K41<=25),0.5+MIN(1,SUMPRODUCT(--ISNUMBER(SEARCH({"categor","region","región","producto","linea","línea","segmento","canal","ciudad","tienda","sucursal","vendedor","cliente","tipo","marca","zona","sede","courier","transportadora","oficina","trayecto","motivo","clasifica","proceso"},G41)))))+0.039,0) -> 0 | K41: =IF(C41>0,SUMPRODUCT((INDEX(Datos!$A$2:$AN$501,0,2)<>"")/COUNTIF(INDEX(Datos!$A$2:$AN$501,0,2),INDEX(Datos!$A$2:$AN$501,0,2)&"")),0) -> 500 | L41: =IF(E41,1+MIN(1,SUMPRODUCT(--ISNUMBER(SEARCH({"fecha","date","periodo","timestamp"},G41))))+0.039,0) -> 2.039 | M41: =IF(AND(H41,K41>=2,K41<=15),MIN(1,SUMPRODUCT(--ISNUMBER(SEARCH({"etapa","fase","estado","stage","embudo","funnel","paso","status"},G41))))*(1+0.039),0) -> 0 | N41: =IF(H41,MIN(1,SUMPRODUCT(--ISNUMBER(SEARCH({"departamento","depto","dpto","depart"},G41))))*(1+0.039),0) -> 0 | O41: =IF(F41,MIN(1,SUMPRODUCT(--ISNUMBER(SEARCH({"costo","cost"},G41))))*(1+0.039),0) -> 0 | P41: =IF(B41=$E$6,0,I41+5*MIN(1,SUMPRODUCT(--ISNUMBER(SEARCH({" dias"," días","tiempo","demora","duraci","lead"," horas"},G41))))*(I41>0)) -> 0 | Q41: =IF(B41=$E$9,0,J41) -> 0 | R41: =IF(OR(B41=$E$6,INDEX($I$40:$I$79,MAX(1,$F$6))<12),0,O41) -> 0 | S41: =AND(C41>0,D41<0.5*C41,MIN(1,SUMPRODUCT(--ISNUMBER(SEARCH({"fecha","date","periodo","timestamp"},G41))))>0) -> FALSE
A42: 3 | B42: =IF(INDEX(Datos!$A$1:$AN$1,1,3)="","",INDEX(Datos!$A$1:$AN$1,1,3)&"") -> Departamento | C42: =IF(B42="",0,COUNTA(INDEX(Datos!$A$2:$AN$1048576,0,3))) -> 2400 | D42: =IF(B42="",0,COUNT(INDEX(Datos!$A$2:$AN$1048576,0,3))) -> 0 | E42: =AND(C42>0,D42>=0.9*C42,OR(LEFT(CELL("format",INDEX(Datos!$A$2:$AN$2,1,3)),1)="D",MIN(1,SUMPRODUCT(--ISNUMBER(SEARCH({"fecha","date","periodo","timestamp"},G42))))>0)) -> FALSE | F42: =AND(C42>0,D42>=0.9*C42,NOT(E42),MIN(1,SUMPRODUCT(--ISNUMBER(SEARCH({" id "," id"," cod"," nit "," cedula"," cédula"," telefono"," teléfono"," celular"," sku"," factura"," numero"," número"," nro"," año "," ano "," year"," zip"," postal"," documento"," guia"," guía"," orden"," cuenta"," pedido"," radicado"," consecutivo"," omr"," pob "," placa"," referencia"," ref "},G42))))=0,NOT(AND(K42>=20,K42>=0.95*MIN(500,C42),MIN(1,SUMPRODUCT(--ISNUMBER(SEARCH({"venta","ingreso","monto","importe","total","valor","factur","revenue","sales","amount","utilidad","ganancia","gasto"},G42))))+MIN(1,SUMPRODUCT(--ISNUMBER(SEARCH({"precio","price","unit","costo","cost","promedio","tasa","%","edad","calific","rating","puntaje","porcentaje","satisf","nps","score","nota"},G42))))+MIN(1,SUMPRODUCT(--ISNUMBER(SEARCH({"costo","cost"},G42))))+MIN(1,SUMPRODUCT(--ISNUMBER(SEARCH({" dias"," días","tiempo","demora","duraci","lead"," horas"},G42))))+MIN(1,SUMPRODUCT(--ISNUMBER(SEARCH({"cantidad","unidades","qty","peso","kilos"," kg","volumen","stock","existencia","inventario"},G42))))=0))) -> FALSE | G42: =" "&LOWER(SUBSTITUTE(SUBSTITUTE(SUBSTITUTE(B42,"_"," "),"-"," "),"."," "))&" " -> departamento | H42: =AND(C42>0,D42<0.5*C42) -> TRUE | I42: =IF(F42,2+10*MIN(1,SUMPRODUCT(--ISNUMBER(SEARCH({"venta","ingreso","monto","importe","total","valor","factur","revenue","sales","amount","utilidad","ganancia","gasto"},G42))))+8*MIN(1,SUMPRODUCT(--ISNUMBER(SEARCH({"cantidad","unidades","qty","peso","kilos"," kg","volumen","stock","existencia","inventario"},G42))))*(1-MIN(1,SUMPRODUCT(--ISNUMBER(SEARCH({"venta","ingreso","monto","importe","total","valor","factur","revenue","sales","amount","utilidad","ganancia","gasto"},G42)))))-MIN(1,SUMPRODUCT(--ISNUMBER(SEARCH({"precio","price","unit","costo","cost","promedio","tasa","%","edad","calific","rating","puntaje","porcentaje","satisf","nps","score","nota"},G42))))+0.038,0) -> 0 | J42: =IF(AND(H42,K42>=2),IF(K42<=40,2+10*MIN(1,SUMPRODUCT(--ISNUMBER(SEARCH({"categor","region","región","producto","linea","línea","segmento","canal","ciudad","tienda","sucursal","vendedor","cliente","tipo","marca","zona","sede","courier","transportadora","oficina","trayecto","motivo","clasifica","proceso"},G42))))+3*AND(K42>=4,K42<=25),0.5+MIN(1,SUMPRODUCT(--ISNUMBER(SEARCH({"categor","region","región","producto","linea","línea","segmento","canal","ciudad","tienda","sucursal","vendedor","cliente","tipo","marca","zona","sede","courier","transportadora","oficina","trayecto","motivo","clasifica","proceso"},G42)))))+0.038,0) -> 5.038 | K42: =IF(C42>0,SUMPRODUCT((INDEX(Datos!$A$2:$AN$501,0,3)<>"")/COUNTIF(INDEX(Datos!$A$2:$AN$501,0,3),INDEX(Datos!$A$2:$AN$501,0,3)&"")),0) -> 10 | L42: =IF(E42,1+MIN(1,SUMPRODUCT(--ISNUMBER(SEARCH({"fecha","date","periodo","timestamp"},G42))))+0.038,0) -> 0 | M42: =IF(AND(H42,K42>=2,K42<=15),MIN(1,SUMPRODUCT(--ISNUMBER(SEARCH({"etapa","fase","estado","stage","embudo","funnel","paso","status"},G42))))*(1+0.038),0) -> 0 | N42: =IF(H42,MIN(1,SUMPRODUCT(--ISNUMBER(SEARCH({"departamento","depto","dpto","depart"},G42))))*(1+0.038),0) -> 1.038 | O42: =IF(F42,MIN(1,SUMPRODUCT(--ISNUMBER(SEARCH({"costo","cost"},G42))))*(1+0.038),0) -> 0 | P42: =IF(B42=$E$6,0,I42+5*MIN(1,SUMPRODUCT(--ISNUMBER(SEARCH({" dias"," días","tiempo","demora","duraci","lead"," horas"},G42))))*(I42>0)) -> 0 | Q42: =IF(B42=$E$9,0,J42) -> 5.038 | R42: =IF(OR(B42=$E$6,INDEX($I$40:$I$79,MAX(1,$F$6))<12),0,O42) -> 0 | S42: =AND(C42>0,D42<0.5*C42,MIN(1,SUMPRODUCT(--ISNUMBER(SEARCH({"fecha","date","periodo","timestamp"},G42))))>0) -> FALSE
A43: 4 | B43: =IF(INDEX(Datos!$A$1:$AN$1,1,4)="","",INDEX(Datos!$A$1:$AN$1,1,4)&"") -> Ciudad | C43: =IF(B43="",0,COUNTA(INDEX(Datos!$A$2:$AN$1048576,0,4))) -> 2400 | D43: =IF(B43="",0,COUNT(INDEX(Datos!$A$2:$AN$1048576,0,4))) -> 0 | E43: =AND(C43>0,D43>=0.9*C43,OR(LEFT(CELL("format",INDEX(Datos!$A$2:$AN$2,1,4)),1)="D",MIN(1,SUMPRODUCT(--ISNUMBER(SEARCH({"fecha","date","periodo","timestamp"},G43))))>0)) -> FALSE | F43: =AND(C43>0,D43>=0.9*C43,NOT(E43),MIN(1,SUMPRODUCT(--ISNUMBER(SEARCH({" id "," id"," cod"," nit "," cedula"," cédula"," telefono"," teléfono"," celular"," sku"," factura"," numero"," número"," nro"," año "," ano "," year"," zip"," postal"," documento"," guia"," guía"," orden"," cuenta"," pedido"," radicado"," consecutivo"," omr"," pob "," placa"," referencia"," ref "},G43))))=0,NOT(AND(K43>=20,K43>=0.95*MIN(500,C43),MIN(1,SUMPRODUCT(--ISNUMBER(SEARCH({"venta","ingreso","monto","importe","total","valor","factur","revenue","sales","amount","utilidad","ganancia","gasto"},G43))))+MIN(1,SUMPRODUCT(--ISNUMBER(SEARCH({"precio","price","unit","costo","cost","promedio","tasa","%","edad","calific","rating","puntaje","porcentaje","satisf","nps","score","nota"},G43))))+MIN(1,SUMPRODUCT(--ISNUMBER(SEARCH({"costo","cost"},G43))))+MIN(1,SUMPRODUCT(--ISNUMBER(SEARCH({" dias"," días","tiempo","demora","duraci","lead"," horas"},G43))))+MIN(1,SUMPRODUCT(--ISNUMBER(SEARCH({"cantidad","unidades","qty","peso","kilos"," kg","volumen","stock","existencia","inventario"},G43))))=0))) -> FALSE | G43: =" "&LOWER(SUBSTITUTE(SUBSTITUTE(SUBSTITUTE(B43,"_"," "),"-"," "),"."," "))&" " -> ciudad | H43: =AND(C43>0,D43<0.5*C43) -> TRUE | I43: =IF(F43,2+10*MIN(1,SUMPRODUCT(--ISNUMBER(SEARCH({"venta","ingreso","monto","importe","total","valor","factur","revenue","sales","amount","utilidad","ganancia","gasto"},G43))))+8*MIN(1,SUMPRODUCT(--ISNUMBER(SEARCH({"cantidad","unidades","qty","peso","kilos"," kg","volumen","stock","existencia","inventario"},G43))))*(1-MIN(1,SUMPRODUCT(--ISNUMBER(SEARCH({"venta","ingreso","monto","importe","total","valor","factur","revenue","sales","amount","utilidad","ganancia","gasto"},G43)))))-MIN(1,SUMPRODUCT(--ISNUMBER(SEARCH({"precio","price","unit","costo","cost","promedio","tasa","%","edad","calific","rating","puntaje","porcentaje","satisf","nps","score","nota"},G43))))+0.037,0) -> 0 | J43: =IF(AND(H43,K43>=2),IF(K43<=40,2+10*MIN(1,SUMPRODUCT(--ISNUMBER(SEARCH({"categor","region","región","producto","linea","línea","segmento","canal","ciudad","tienda","sucursal","vendedor","cliente","tipo","marca","zona","sede","courier","transportadora","oficina","trayecto","motivo","clasifica","proceso"},G43))))+3*AND(K43>=4,K43<=25),0.5+MIN(1,SUMPRODUCT(--ISNUMBER(SEARCH({"categor","region","región","producto","linea","línea","segmento","canal","ciudad","tienda","sucursal","vendedor","cliente","tipo","marca","zona","sede","courier","transportadora","oficina","trayecto","motivo","clasifica","proceso"},G43)))))+0.037,0) -> 15.037 | K43: =IF(C43>0,SUMPRODUCT((INDEX(Datos!$A$2:$AN$501,0,4)<>"")/COUNTIF(INDEX(Datos!$A$2:$AN$501,0,4),INDEX(Datos!$A$2:$AN$501,0,4)&"")),0) -> 10 | L43: =IF(E43,1+MIN(1,SUMPRODUCT(--ISNUMBER(SEARCH({"fecha","date","periodo","timestamp"},G43))))+0.037,0) -> 0 | M43: =IF(AND(H43,K43>=2,K43<=15),MIN(1,SUMPRODUCT(--ISNUMBER(SEARCH({"etapa","fase","estado","stage","embudo","funnel","paso","status"},G43))))*(1+0.037),0) -> 0 | N43: =IF(H43,MIN(1,SUMPRODUCT(--ISNUMBER(SEARCH({"departamento","depto","dpto","depart"},G43))))*(1+0.037),0) -> 0 | O43: =IF(F43,MIN(1,SUMPRODUCT(--ISNUMBER(SEARCH({"costo","cost"},G43))))*(1+0.037),0) -> 0 | P43: =IF(B43=$E$6,0,I43+5*MIN(1,SUMPRODUCT(--ISNUMBER(SEARCH({" dias"," días","tiempo","demora","duraci","lead"," horas"},G43))))*(I43>0)) -> 0 | Q43: =IF(B43=$E$9,0,J43) -> 0 | R43: =IF(OR(B43=$E$6,INDEX($I$40:$I$79,MAX(1,$F$6))<12),0,O43) -> 0 | S43: =AND(C43>0,D43<0.5*C43,MIN(1,SUMPRODUCT(--ISNUMBER(SEARCH({"fecha","date","periodo","timestamp"},G43))))>0) -> FALSE
A44: 5 | B44: =IF(INDEX(Datos!$A$1:$AN$1,1,5)="","",INDEX(Datos!$A$1:$AN$1,1,5)&"") -> Categoría | C44: =IF(B44="",0,COUNTA(INDEX(Datos!$A$2:$AN$1048576,0,5))) -> 2400 | D44: =IF(B44="",0,COUNT(INDEX(Datos!$A$2:$AN$1048576,0,5))) -> 0 | E44: =AND(C44>0,D44>=0.9*C44,OR(LEFT(CELL("format",INDEX(Datos!$A$2:$AN$2,1,5)),1)="D",MIN(1,SUMPRODUCT(--ISNUMBER(SEARCH({"fecha","date","periodo","timestamp"},G44))))>0)) -> FALSE | F44: =AND(C44>0,D44>=0.9*C44,NOT(E44),MIN(1,SUMPRODUCT(--ISNUMBER(SEARCH({" id "," id"," cod"," nit "," cedula"," cédula"," telefono"," teléfono"," celular"," sku"," factura"," numero"," número"," nro"," año "," ano "," year"," zip"," postal"," documento"," guia"," guía"," orden"," cuenta"," pedido"," radicado"," consecutivo"," omr"," pob "," placa"," referencia"," ref "},G44))))=0,NOT(AND(K44>=20,K44>=0.95*MIN(500,C44),MIN(1,SUMPRODUCT(--ISNUMBER(SEARCH({"venta","ingreso","monto","importe","total","valor","factur","revenue","sales","amount","utilidad","ganancia","gasto"},G44))))+MIN(1,SUMPRODUCT(--ISNUMBER(SEARCH({"precio","price","unit","costo","cost","promedio","tasa","%","edad","calific","rating","puntaje","porcentaje","satisf","nps","score","nota"},G44))))+MIN(1,SUMPRODUCT(--ISNUMBER(SEARCH({"costo","cost"},G44))))+MIN(1,SUMPRODUCT(--ISNUMBER(SEARCH({" dias"," días","tiempo","demora","duraci","lead"," horas"},G44))))+MIN(1,SUMPRODUCT(--ISNUMBER(SEARCH({"cantidad","unidades","qty","peso","kilos"," kg","volumen","stock","existencia","inventario"},G44))))=0))) -> FALSE | G44: =" "&LOWER(SUBSTITUTE(SUBSTITUTE(SUBSTITUTE(B44,"_"," "),"-"," "),"."," "))&" " -> categoría | H44: =AND(C44>0,D44<0.5*C44) -> TRUE | I44: =IF(F44,2+10*MIN(1,SUMPRODUCT(--ISNUMBER(SEARCH({"venta","ingreso","monto","importe","total","valor","factur","revenue","sales","amount","utilidad","ganancia","gasto"},G44))))+8*MIN(1,SUMPRODUCT(--ISNUMBER(SEARCH({"cantidad","unidades","qty","peso","kilos"," kg","volumen","stock","existencia","inventario"},G44))))*(1-MIN(1,SUMPRODUCT(--ISNUMBER(SEARCH({"venta","ingreso","monto","importe","total","valor","factur","revenue","sales","amount","utilidad","ganancia","gasto"},G44)))))-MIN(1,SUMPRODUCT(--ISNUMBER(SEARCH({"precio","price","unit","costo","cost","promedio","tasa","%","edad","calific","rating","puntaje","porcentaje","satisf","nps","score","nota"},G44))))+0.036,0) -> 0 | J44: =IF(AND(H44,K44>=2),IF(K44<=40,2+10*MIN(1,SUMPRODUCT(--ISNUMBER(SEARCH({"categor","region","región","producto","linea","línea","segmento","canal","ciudad","tienda","sucursal","vendedor","cliente","tipo","marca","zona","sede","courier","transportadora","oficina","trayecto","motivo","clasifica","proceso"},G44))))+3*AND(K44>=4,K44<=25),0.5+MIN(1,SUMPRODUCT(--ISNUMBER(SEARCH({"categor","region","región","producto","linea","línea","segmento","canal","ciudad","tienda","sucursal","vendedor","cliente","tipo","marca","zona","sede","courier","transportadora","oficina","trayecto","motivo","clasifica","proceso"},G44)))))+0.036,0) -> 15.036 | K44: =IF(C44>0,SUMPRODUCT((INDEX(Datos!$A$2:$AN$501,0,5)<>"")/COUNTIF(INDEX(Datos!$A$2:$AN$501,0,5),INDEX(Datos!$A$2:$AN$501,0,5)&"")),0) -> 6 | L44: =IF(E44,1+MIN(1,SUMPRODUCT(--ISNUMBER(SEARCH({"fecha","date","periodo","timestamp"},G44))))+0.036,0) -> 0 | M44: =IF(AND(H44,K44>=2,K44<=15),MIN(1,SUMPRODUCT(--ISNUMBER(SEARCH({"etapa","fase","estado","stage","embudo","funnel","paso","status"},G44))))*(1+0.036),0) -> 0 | N44: =IF(H44,MIN(1,SUMPRODUCT(--ISNUMBER(SEARCH({"departamento","depto","dpto","depart"},G44))))*(1+0.036),0) -> 0 | O44: =IF(F44,MIN(1,SUMPRODUCT(--ISNUMBER(SEARCH({"costo","cost"},G44))))*(1+0.036),0) -> 0 | P44: =IF(B44=$E$6,0,I44+5*MIN(1,SUMPRODUCT(--ISNUMBER(SEARCH({" dias"," días","tiempo","demora","duraci","lead"," horas"},G44))))*(I44>0)) -> 0 | Q44: =IF(B44=$E$9,0,J44) -> 15.036 | R44: =IF(OR(B44=$E$6,INDEX($I$40:$I$79,MAX(1,$F$6))<12),0,O44) -> 0 | S44: =AND(C44>0,D44<0.5*C44,MIN(1,SUMPRODUCT(--ISNUMBER(SEARCH({"fecha","date","periodo","timestamp"},G44))))>0) -> FALSE
A45: 6 | B45: =IF(INDEX(Datos!$A$1:$AN$1,1,6)="","",INDEX(Datos!$A$1:$AN$1,1,6)&"") -> Canal | C45: =IF(B45="",0,COUNTA(INDEX(Datos!$A$2:$AN$1048576,0,6))) -> 2400 | D45: =IF(B45="",0,COUNT(INDEX(Datos!$A$2:$AN$1048576,0,6))) -> 0 | E45: =AND(C45>0,D45>=0.9*C45,OR(LEFT(CELL("format",INDEX(Datos!$A$2:$AN$2,1,6)),1)="D",MIN(1,SUMPRODUCT(--ISNUMBER(SEARCH({"fecha","date","periodo","timestamp"},G45))))>0)) -> FALSE | F45: =AND(C45>0,D45>=0.9*C45,NOT(E45),MIN(1,SUMPRODUCT(--ISNUMBER(SEARCH({" id "," id"," cod"," nit "," cedula"," cédula"," telefono"," teléfono"," celular"," sku"," factura"," numero"," número"," nro"," año "," ano "," year"," zip"," postal"," documento"," guia"," guía"," orden"," cuenta"," pedido"," radicado"," consecutivo"," omr"," pob "," placa"," referencia"," ref "},G45))))=0,NOT(AND(K45>=20,K45>=0.95*MIN(500,C45),MIN(1,SUMPRODUCT(--ISNUMBER(SEARCH({"venta","ingreso","monto","importe","total","valor","factur","revenue","sales","amount","utilidad","ganancia","gasto"},G45))))+MIN(1,SUMPRODUCT(--ISNUMBER(SEARCH({"precio","price","unit","costo","cost","promedio","tasa","%","edad","calific","rating","puntaje","porcentaje","satisf","nps","score","nota"},G45))))+MIN(1,SUMPRODUCT(--ISNUMBER(SEARCH({"costo","cost"},G45))))+MIN(1,SUMPRODUCT(--ISNUMBER(SEARCH({" dias"," días","tiempo","demora","duraci","lead"," horas"},G45))))+MIN(1,SUMPRODUCT(--ISNUMBER(SEARCH({"cantidad","unidades","qty","peso","kilos"," kg","volumen","stock","existencia","inventario"},G45))))=0))) -> FALSE | G45: =" "&LOWER(SUBSTITUTE(SUBSTITUTE(SUBSTITUTE(B45,"_"," "),"-"," "),"."," "))&" " -> canal | H45: =AND(C45>0,D45<0.5*C45) -> TRUE | I45: =IF(F45,2+10*MIN(1,SUMPRODUCT(--ISNUMBER(SEARCH({"venta","ingreso","monto","importe","total","valor","factur","revenue","sales","amount","utilidad","ganancia","gasto"},G45))))+8*MIN(1,SUMPRODUCT(--ISNUMBER(SEARCH({"cantidad","unidades","qty","peso","kilos"," kg","volumen","stock","existencia","inventario"},G45))))*(1-MIN(1,SUMPRODUCT(--ISNUMBER(SEARCH({"venta","ingreso","monto","importe","total","valor","factur","revenue","sales","amount","utilidad","ganancia","gasto"},G45)))))-MIN(1,SUMPRODUCT(--ISNUMBER(SEARCH({"precio","price","unit","costo","cost","promedio","tasa","%","edad","calific","rating","puntaje","porcentaje","satisf","nps","score","nota"},G45))))+0.035,0) -> 0 | J45: =IF(AND(H45,K45>=2),IF(K45<=40,2+10*MIN(1,SUMPRODUCT(--ISNUMBER(SEARCH({"categor","region","región","producto","linea","línea","segmento","canal","ciudad","tienda","sucursal","vendedor","cliente","tipo","marca","zona","sede","courier","transportadora","oficina","trayecto","motivo","clasifica","proceso"},G45))))+3*AND(K45>=4,K45<=25),0.5+MIN(1,SUMPRODUCT(--ISNUMBER(SEARCH({"categor","region","región","producto","linea","línea","segmento","canal","ciudad","tienda","sucursal","vendedor","cliente","tipo","marca","zona","sede","courier","transportadora","oficina","trayecto","motivo","clasifica","proceso"},G45)))))+0.035,0) -> 15.035 | K45: =IF(C45>0,SUMPRODUCT((INDEX(Datos!$A$2:$AN$501,0,6)<>"")/COUNTIF(INDEX(Datos!$A$2:$AN$501,0,6),INDEX(Datos!$A$2:$AN$501,0,6)&"")),0) -> 4 | L45: =IF(E45,1+MIN(1,SUMPRODUCT(--ISNUMBER(SEARCH({"fecha","date","periodo","timestamp"},G45))))+0.035,0) -> 0 | M45: =IF(AND(H45,K45>=2,K45<=15),MIN(1,SUMPRODUCT(--ISNUMBER(SEARCH({"etapa","fase","estado","stage","embudo","funnel","paso","status"},G45))))*(1+0.035),0) -> 0 | N45: =IF(H45,MIN(1,SUMPRODUCT(--ISNUMBER(SEARCH({"departamento","depto","dpto","depart"},G45))))*(1+0.035),0) -> 0 | O45: =IF(F45,MIN(1,SUMPRODUCT(--ISNUMBER(SEARCH({"costo","cost"},G45))))*(1+0.035),0) -> 0 | P45: =IF(B45=$E$6,0,I45+5*MIN(1,SUMPRODUCT(--ISNUMBER(SEARCH({" dias"," días","tiempo","demora","duraci","lead"," horas"},G45))))*(I45>0)) -> 0 | Q45: =IF(B45=$E$9,0,J45) -> 15.035 | R45: =IF(OR(B45=$E$6,INDEX($I$40:$I$79,MAX(1,$F$6))<12),0,O45) -> 0 | S45: =AND(C45>0,D45<0.5*C45,MIN(1,SUMPRODUCT(--ISNUMBER(SEARCH({"fecha","date","periodo","timestamp"},G45))))>0) -> FALSE
A46: 7 | B46: =IF(INDEX(Datos!$A$1:$AN$1,1,7)="","",INDEX(Datos!$A$1:$AN$1,1,7)&"") -> Etapa | C46: =IF(B46="",0,COUNTA(INDEX(Datos!$A$2:$AN$1048576,0,7))) -> 2400 | D46: =IF(B46="",0,COUNT(INDEX(Datos!$A$2:$AN$1048576,0,7))) -> 0 | E46: =AND(C46>0,D46>=0.9*C46,OR(LEFT(CELL("format",INDEX(Datos!$A$2:$AN$2,1,7)),1)="D",MIN(1,SUMPRODUCT(--ISNUMBER(SEARCH({"fecha","date","periodo","timestamp"},G46))))>0)) -> FALSE | F46: =AND(C46>0,D46>=0.9*C46,NOT(E46),MIN(1,SUMPRODUCT(--ISNUMBER(SEARCH({" id "," id"," cod"," nit "," cedula"," cédula"," telefono"," teléfono"," celular"," sku"," factura"," numero"," número"," nro"," año "," ano "," year"," zip"," postal"," documento"," guia"," guía"," orden"," cuenta"," pedido"," radicado"," consecutivo"," omr"," pob "," placa"," referencia"," ref "},G46))))=0,NOT(AND(K46>=20,K46>=0.95*MIN(500,C46),MIN(1,SUMPRODUCT(--ISNUMBER(SEARCH({"venta","ingreso","monto","importe","total","valor","factur","revenue","sales","amount","utilidad","ganancia","gasto"},G46))))+MIN(1,SUMPRODUCT(--ISNUMBER(SEARCH({"precio","price","unit","costo","cost","promedio","tasa","%","edad","calific","rating","puntaje","porcentaje","satisf","nps","score","nota"},G46))))+MIN(1,SUMPRODUCT(--ISNUMBER(SEARCH({"costo","cost"},G46))))+MIN(1,SUMPRODUCT(--ISNUMBER(SEARCH({" dias"," días","tiempo","demora","duraci","lead"," horas"},G46))))+MIN(1,SUMPRODUCT(--ISNUMBER(SEARCH({"cantidad","unidades","qty","peso","kilos"," kg","volumen","stock","existencia","inventario"},G46))))=0))) -> FALSE | G46: =" "&LOWER(SUBSTITUTE(SUBSTITUTE(SUBSTITUTE(B46,"_"," "),"-"," "),"."," "))&" " -> etapa | H46: =AND(C46>0,D46<0.5*C46) -> TRUE | I46: =IF(F46,2+10*MIN(1,SUMPRODUCT(--ISNUMBER(SEARCH({"venta","ingreso","monto","importe","total","valor","factur","revenue","sales","amount","utilidad","ganancia","gasto"},G46))))+8*MIN(1,SUMPRODUCT(--ISNUMBER(SEARCH({"cantidad","unidades","qty","peso","kilos"," kg","volumen","stock","existencia","inventario"},G46))))*(1-MIN(1,SUMPRODUCT(--ISNUMBER(SEARCH({"venta","ingreso","monto","importe","total","valor","factur","revenue","sales","amount","utilidad","ganancia","gasto"},G46)))))-MIN(1,SUMPRODUCT(--ISNUMBER(SEARCH({"precio","price","unit","costo","cost","promedio","tasa","%","edad","calific","rating","puntaje","porcentaje","satisf","nps","score","nota"},G46))))+0.034,0) -> 0 | J46: =IF(AND(H46,K46>=2),IF(K46<=40,2+10*MIN(1,SUMPRODUCT(--ISNUMBER(SEARCH({"categor","region","región","producto","linea","línea","segmento","canal","ciudad","tienda","sucursal","vendedor","cliente","tipo","marca","zona","sede","courier","transportadora","oficina","trayecto","motivo","clasifica","proceso"},G46))))+3*AND(K46>=4,K46<=25),0.5+MIN(1,SUMPRODUCT(--ISNUMBER(SEARCH({"categor","region","región","producto","linea","línea","segmento","canal","ciudad","tienda","sucursal","vendedor","cliente","tipo","marca","zona","sede","courier","transportadora","oficina","trayecto","motivo","clasifica","proceso"},G46)))))+0.034,0) -> 5.034 | K46: =IF(C46>0,SUMPRODUCT((INDEX(Datos!$A$2:$AN$501,0,7)<>"")/COUNTIF(INDEX(Datos!$A$2:$AN$501,0,7),INDEX(Datos!$A$2:$AN$501,0,7)&"")),0) -> 4 | L46: =IF(E46,1+MIN(1,SUMPRODUCT(--ISNUMBER(SEARCH({"fecha","date","periodo","timestamp"},G46))))+0.034,0) -> 0 | M46: =IF(AND(H46,K46>=2,K46<=15),MIN(1,SUMPRODUCT(--ISNUMBER(SEARCH({"etapa","fase","estado","stage","embudo","funnel","paso","status"},G46))))*(1+0.034),0) -> 1.034 | N46: =IF(H46,MIN(1,SUMPRODUCT(--ISNUMBER(SEARCH({"departamento","depto","dpto","depart"},G46))))*(1+0.034),0) -> 0 | O46: =IF(F46,MIN(1,SUMPRODUCT(--ISNUMBER(SEARCH({"costo","cost"},G46))))*(1+0.034),0) -> 0 | P46: =IF(B46=$E$6,0,I46+5*MIN(1,SUMPRODUCT(--ISNUMBER(SEARCH({" dias"," días","tiempo","demora","duraci","lead"," horas"},G46))))*(I46>0)) -> 0 | Q46: =IF(B46=$E$9,0,J46) -> 5.034 | R46: =IF(OR(B46=$E$6,INDEX($I$40:$I$79,MAX(1,$F$6))<12),0,O46) -> 0 | S46: =AND(C46>0,D46<0.5*C46,MIN(1,SUMPRODUCT(--ISNUMBER(SEARCH({"fecha","date","periodo","timestamp"},G46))))>0) -> FALSE
A47: 8 | B47: =IF(INDEX(Datos!$A$1:$AN$1,1,8)="","",INDEX(Datos!$A$1:$AN$1,1,8)&"") -> Unidades | C47: =IF(B47="",0,COUNTA(INDEX(Datos!$A$2:$AN$1048576,0,8))) -> 2400 | D47: =IF(B47="",0,COUNT(INDEX(Datos!$A$2:$AN$1048576,0,8))) -> 2400 | E47: =AND(C47>0,D47>=0.9*C47,OR(LEFT(CELL("format",INDEX(Datos!$A$2:$AN$2,1,8)),1)="D",MIN(1,SUMPRODUCT(--ISNUMBER(SEARCH({"fecha","date","periodo","timestamp"},G47))))>0)) -> FALSE | F47: =AND(C47>0,D47>=0.9*C47,NOT(E47),MIN(1,SUMPRODUCT(--ISNUMBER(SEARCH({" id "," id"," cod"," nit "," cedula"," cédula"," telefono"," teléfono"," celular"," sku"," factura"," numero"," número"," nro"," año "," ano "," year"," zip"," postal"," documento"," guia"," guía"," orden"," cuenta"," pedido"," radicado"," consecutivo"," omr"," pob "," placa"," referencia"," ref "},G47))))=0,NOT(AND(K47>=20,K47>=0.95*MIN(500,C47),MIN(1,SUMPRODUCT(--ISNUMBER(SEARCH({"venta","ingreso","monto","importe","total","valor","factur","revenue","sales","amount","utilidad","ganancia","gasto"},G47))))+MIN(1,SUMPRODUCT(--ISNUMBER(SEARCH({"precio","price","unit","costo","cost","promedio","tasa","%","edad","calific","rating","puntaje","porcentaje","satisf","nps","score","nota"},G47))))+MIN(1,SUMPRODUCT(--ISNUMBER(SEARCH({"costo","cost"},G47))))+MIN(1,SUMPRODUCT(--ISNUMBER(SEARCH({" dias"," días","tiempo","demora","duraci","lead"," horas"},G47))))+MIN(1,SUMPRODUCT(--ISNUMBER(SEARCH({"cantidad","unidades","qty","peso","kilos"," kg","volumen","stock","existencia","inventario"},G47))))=0))) -> TRUE | G47: =" "&LOWER(SUBSTITUTE(SUBSTITUTE(SUBSTITUTE(B47,"_"," "),"-"," "),"."," "))&" " -> unidades | H47: =AND(C47>0,D47<0.5*C47) -> FALSE | I47: =IF(F47,2+10*MIN(1,SUMPRODUCT(--ISNUMBER(SEARCH({"venta","ingreso","monto","importe","total","valor","factur","revenue","sales","amount","utilidad","ganancia","gasto"},G47))))+8*MIN(1,SUMPRODUCT(--ISNUMBER(SEARCH({"cantidad","unidades","qty","peso","kilos"," kg","volumen","stock","existencia","inventario"},G47))))*(1-MIN(1,SUMPRODUCT(--ISNUMBER(SEARCH({"venta","ingreso","monto","importe","total","valor","factur","revenue","sales","amount","utilidad","ganancia","gasto"},G47)))))-MIN(1,SUMPRODUCT(--ISNUMBER(SEARCH({"precio","price","unit","costo","cost","promedio","tasa","%","edad","calific","rating","puntaje","porcentaje","satisf","nps","score","nota"},G47))))+0.033,0) -> 10.033 | J47: =IF(AND(H47,K47>=2),IF(K47<=40,2+10*MIN(1,SUMPRODUCT(--ISNUMBER(SEARCH({"categor","region","región","producto","linea","línea","segmento","canal","ciudad","tienda","sucursal","vendedor","cliente","tipo","marca","zona","sede","courier","transportadora","oficina","trayecto","motivo","clasifica","proceso"},G47))))+3*AND(K47>=4,K47<=25),0.5+MIN(1,SUMPRODUCT(--ISNUMBER(SEARCH({"categor","region","región","producto","linea","línea","segmento","canal","ciudad","tienda","sucursal","vendedor","cliente","tipo","marca","zona","sede","courier","transportadora","oficina","trayecto","motivo","clasifica","proceso"},G47)))))+0.033,0) -> 0 | K47: =IF(C47>0,SUMPRODUCT((INDEX(Datos!$A$2:$AN$501,0,8)<>"")/COUNTIF(INDEX(Datos!$A$2:$AN$501,0,8),INDEX(Datos!$A$2:$AN$501,0,8)&"")),0) -> 5 | L47: =IF(E47,1+MIN(1,SUMPRODUCT(--ISNUMBER(SEARCH({"fecha","date","periodo","timestamp"},G47))))+0.033,0) -> 0 | M47: =IF(AND(H47,K47>=2,K47<=15),MIN(1,SUMPRODUCT(--ISNUMBER(SEARCH({"etapa","fase","estado","stage","embudo","funnel","paso","status"},G47))))*(1+0.033),0) -> 0 | N47: =IF(H47,MIN(1,SUMPRODUCT(--ISNUMBER(SEARCH({"departamento","depto","dpto","depart"},G47))))*(1+0.033),0) -> 0 | O47: =IF(F47,MIN(1,SUMPRODUCT(--ISNUMBER(SEARCH({"costo","cost"},G47))))*(1+0.033),0) -> 0 | P47: =IF(B47=$E$6,0,I47+5*MIN(1,SUMPRODUCT(--ISNUMBER(SEARCH({" dias"," días","tiempo","demora","duraci","lead"," horas"},G47))))*(I47>0)) -> 10.033 | Q47: =IF(B47=$E$9,0,J47) -> 0 | R47: =IF(OR(B47=$E$6,INDEX($I$40:$I$79,MAX(1,$F$6))<12),0,O47) -> 0 | S47: =AND(C47>0,D47<0.5*C47,MIN(1,SUMPRODUCT(--ISNUMBER(SEARCH({"fecha","date","periodo","timestamp"},G47))))>0) -> FALSE
A48: 9 | B48: =IF(INDEX(Datos!$A$1:$AN$1,1,9)="","",INDEX(Datos!$A$1:$AN$1,1,9)&"") -> Precio unitario | C48: =IF(B48="",0,COUNTA(INDEX(Datos!$A$2:$AN$1048576,0,9))) -> 2400 | D48: =IF(B48="",0,COUNT(INDEX(Datos!$A$2:$AN$1048576,0,9))) -> 2400 | E48: =AND(C48>0,D48>=0.9*C48,OR(LEFT(CELL("format",INDEX(Datos!$A$2:$AN$2,1,9)),1)="D",MIN(1,SUMPRODUCT(--ISNUMBER(SEARCH({"fecha","date","periodo","timestamp"},G48))))>0)) -> FALSE | F48: =AND(C48>0,D48>=0.9*C48,NOT(E48),MIN(1,SUMPRODUCT(--ISNUMBER(SEARCH({" id "," id"," cod"," nit "," cedula"," cédula"," telefono"," teléfono"," celular"," sku"," factura"," numero"," número"," nro"," año "," ano "," year"," zip"," postal"," documento"," guia"," guía"," orden"," cuenta"," pedido"," radicado"," consecutivo"," omr"," pob "," placa"," referencia"," ref "},G48))))=0,NOT(AND(K48>=20,K48>=0.95*MIN(500,C48),MIN(1,SUMPRODUCT(--ISNUMBER(SEARCH({"venta","ingreso","monto","importe","total","valor","factur","revenue","sales","amount","utilidad","ganancia","gasto"},G48))))+MIN(1,SUMPRODUCT(--ISNUMBER(SEARCH({"precio","price","unit","costo","cost","promedio","tasa","%","edad","calific","rating","puntaje","porcentaje","satisf","nps","score","nota"},G48))))+MIN(1,SUMPRODUCT(--ISNUMBER(SEARCH({"costo","cost"},G48))))+MIN(1,SUMPRODUCT(--ISNUMBER(SEARCH({" dias"," días","tiempo","demora","duraci","lead"," horas"},G48))))+MIN(1,SUMPRODUCT(--ISNUMBER(SEARCH({"cantidad","unidades","qty","peso","kilos"," kg","volumen","stock","existencia","inventario"},G48))))=0))) -> TRUE | G48: =" "&LOWER(SUBSTITUTE(SUBSTITUTE(SUBSTITUTE(B48,"_"," "),"-"," "),"."," "))&" " -> precio unitario | H48: =AND(C48>0,D48<0.5*C48) -> FALSE | I48: =IF(F48,2+10*MIN(1,SUMPRODUCT(--ISNUMBER(SEARCH({"venta","ingreso","monto","importe","total","valor","factur","revenue","sales","amount","utilidad","ganancia","gasto"},G48))))+8*MIN(1,SUMPRODUCT(--ISNUMBER(SEARCH({"cantidad","unidades","qty","peso","kilos"," kg","volumen","stock","existencia","inventario"},G48))))*(1-MIN(1,SUMPRODUCT(--ISNUMBER(SEARCH({"venta","ingreso","monto","importe","total","valor","factur","revenue","sales","amount","utilidad","ganancia","gasto"},G48)))))-MIN(1,SUMPRODUCT(--ISNUMBER(SEARCH({"precio","price","unit","costo","cost","promedio","tasa","%","edad","calific","rating","puntaje","porcentaje","satisf","nps","score","nota"},G48))))+0.032,0) -> 1.032 | J48: =IF(AND(H48,K48>=2),IF(K48<=40,2+10*MIN(1,SUMPRODUCT(--ISNUMBER(SEARCH({"categor","region","región","producto","linea","línea","segmento","canal","ciudad","tienda","sucursal","vendedor","cliente","tipo","marca","zona","sede","courier","transportadora","oficina","trayecto","motivo","clasifica","proceso"},G48))))+3*AND(K48>=4,K48<=25),0.5+MIN(1,SUMPRODUCT(--ISNUMBER(SEARCH({"categor","region","región","producto","linea","línea","segmento","canal","ciudad","tienda","sucursal","vendedor","cliente","tipo","marca","zona","sede","courier","transportadora","oficina","trayecto","motivo","clasifica","proceso"},G48)))))+0.032,0) -> 0 | K48: =IF(C48>0,SUMPRODUCT((INDEX(Datos!$A$2:$AN$501,0,9)<>"")/COUNTIF(INDEX(Datos!$A$2:$AN$501,0,9),INDEX(Datos!$A$2:$AN$501,0,9)&"")),0) -> 466 | L48: =IF(E48,1+MIN(1,SUMPRODUCT(--ISNUMBER(SEARCH({"fecha","date","periodo","timestamp"},G48))))+0.032,0) -> 0 | M48: =IF(AND(H48,K48>=2,K48<=15),MIN(1,SUMPRODUCT(--ISNUMBER(SEARCH({"etapa","fase","estado","stage","embudo","funnel","paso","status"},G48))))*(1+0.032),0) -> 0 | N48: =IF(H48,MIN(1,SUMPRODUCT(--ISNUMBER(SEARCH({"departamento","depto","dpto","depart"},G48))))*(1+0.032),0) -> 0 | O48: =IF(F48,MIN(1,SUMPRODUCT(--ISNUMBER(SEARCH({"costo","cost"},G48))))*(1+0.032),0) -> 0 | P48: =IF(B48=$E$6,0,I48+5*MIN(1,SUMPRODUCT(--ISNUMBER(SEARCH({" dias"," días","tiempo","demora","duraci","lead"," horas"},G48))))*(I48>0)) -> 1.032 | Q48: =IF(B48=$E$9,0,J48) -> 0 | R48: =IF(OR(B48=$E$6,INDEX($I$40:$I$79,MAX(1,$F$6))<12),0,O48) -> 0 | S48: =AND(C48>0,D48<0.5*C48,MIN(1,SUMPRODUCT(--ISNUMBER(SEARCH({"fecha","date","periodo","timestamp"},G48))))>0) -> FALSE
A49: 10 | B49: =IF(INDEX(Datos!$A$1:$AN$1,1,10)="","",INDEX(Datos!$A$1:$AN$1,1,10)&"") -> Ventas | C49: =IF(B49="",0,COUNTA(INDEX(Datos!$A$2:$AN$1048576,0,10))) -> 2400 | D49: =IF(B49="",0,COUNT(INDEX(Datos!$A$2:$AN$1048576,0,10))) -> 2400 | E49: =AND(C49>0,D49>=0.9*C49,OR(LEFT(CELL("format",INDEX(Datos!$A$2:$AN$2,1,10)),1)="D",MIN(1,SUMPRODUCT(--ISNUMBER(SEARCH({"fecha","date","periodo","timestamp"},G49))))>0)) -> FALSE | F49: =AND(C49>0,D49>=0.9*C49,NOT(E49),MIN(1,SUMPRODUCT(--ISNUMBER(SEARCH({" id "," id"," cod"," nit "," cedula"," cédula"," telefono"," teléfono"," celular"," sku"," factura"," numero"," número"," nro"," año "," ano "," year"," zip"," postal"," documento"," guia"," guía"," orden"," cuenta"," pedido"," radicado"," consecutivo"," omr"," pob "," placa"," referencia"," ref "},G49))))=0,NOT(AND(K49>=20,K49>=0.95*MIN(500,C49),MIN(1,SUMPRODUCT(--ISNUMBER(SEARCH({"venta","ingreso","monto","importe","total","valor","factur","revenue","sales","amount","utilidad","ganancia","gasto"},G49))))+MIN(1,SUMPRODUCT(--ISNUMBER(SEARCH({"precio","price","unit","costo","cost","promedio","tasa","%","edad","calific","rating","puntaje","porcentaje","satisf","nps","score","nota"},G49))))+MIN(1,SUMPRODUCT(--ISNUMBER(SEARCH({"costo","cost"},G49))))+MIN(1,SUMPRODUCT(--ISNUMBER(SEARCH({" dias"," días","tiempo","demora","duraci","lead"," horas"},G49))))+MIN(1,SUMPRODUCT(--ISNUMBER(SEARCH({"cantidad","unidades","qty","peso","kilos"," kg","volumen","stock","existencia","inventario"},G49))))=0))) -> TRUE | G49: =" "&LOWER(SUBSTITUTE(SUBSTITUTE(SUBSTITUTE(B49,"_"," "),"-"," "),"."," "))&" " -> ventas | H49: =AND(C49>0,D49<0.5*C49) -> FALSE | I49: =IF(F49,2+10*MIN(1,SUMPRODUCT(--ISNUMBER(SEARCH({"venta","ingreso","monto","importe","total","valor","factur","revenue","sales","amount","utilidad","ganancia","gasto"},G49))))+8*MIN(1,SUMPRODUCT(--ISNUMBER(SEARCH({"cantidad","unidades","qty","peso","kilos"," kg","volumen","stock","existencia","inventario"},G49))))*(1-MIN(1,SUMPRODUCT(--ISNUMBER(SEARCH({"venta","ingreso","monto","importe","total","valor","factur","revenue","sales","amount","utilidad","ganancia","gasto"},G49)))))-MIN(1,SUMPRODUCT(--ISNUMBER(SEARCH({"precio","price","unit","costo","cost","promedio","tasa","%","edad","calific","rating","puntaje","porcentaje","satisf","nps","score","nota"},G49))))+0.031,0) -> 12.031 | J49: =IF(AND(H49,K49>=2),IF(K49<=40,2+10*MIN(1,SUMPRODUCT(--ISNUMBER(SEARCH({"categor","region","región","producto","linea","línea","segmento","canal","ciudad","tienda","sucursal","vendedor","cliente","tipo","marca","zona","sede","courier","transportadora","oficina","trayecto","motivo","clasifica","proceso"},G49))))+3*AND(K49>=4,K49<=25),0.5+MIN(1,SUMPRODUCT(--ISNUMBER(SEARCH({"categor","region","región","producto","linea","línea","segmento","canal","ciudad","tienda","sucursal","vendedor","cliente","tipo","marca","zona","sede","courier","transportadora","oficina","trayecto","motivo","clasifica","proceso"},G49)))))+0.031,0) -> 0 | K49: =IF(C49>0,SUMPRODUCT((INDEX(Datos!$A$2:$AN$501,0,10)<>"")/COUNTIF(INDEX(Datos!$A$2:$AN$501,0,10),INDEX(Datos!$A$2:$AN$501,0,10)&"")),0) -> 491 | L49: =IF(E49,1+MIN(1,SUMPRODUCT(--ISNUMBER(SEARCH({"fecha","date","periodo","timestamp"},G49))))+0.031,0) -> 0 | M49: =IF(AND(H49,K49>=2,K49<=15),MIN(1,SUMPRODUCT(--ISNUMBER(SEARCH({"etapa","fase","estado","stage","embudo","funnel","paso","status"},G49))))*(1+0.031),0) -> 0 | N49: =IF(H49,MIN(1,SUMPRODUCT(--ISNUMBER(SEARCH({"departamento","depto","dpto","depart"},G49))))*(1+0.031),0) -> 0 | O49: =IF(F49,MIN(1,SUMPRODUCT(--ISNUMBER(SEARCH({"costo","cost"},G49))))*(1+0.031),0) -> 0 | P49: =IF(B49=$E$6,0,I49+5*MIN(1,SUMPRODUCT(--ISNUMBER(SEARCH({" dias"," días","tiempo","demora","duraci","lead"," horas"},G49))))*(I49>0)) -> 0 | Q49: =IF(B49=$E$9,0,J49) -> 0 | R49: =IF(OR(B49=$E$6,INDEX($I$40:$I$79,MAX(1,$F$6))<12),0,O49) -> 0 | S49: =AND(C49>0,D49<0.5*C49,MIN(1,SUMPRODUCT(--ISNUMBER(SEARCH({"fecha","date","periodo","timestamp"},G49))))>0) -> FALSE
A50: 11 | B50: =IF(INDEX(Datos!$A$1:$AN$1,1,11)="","",INDEX(Datos!$A$1:$AN$1,1,11)&"") -> Costo | C50: =IF(B50="",0,COUNTA(INDEX(Datos!$A$2:$AN$1048576,0,11))) -> 2400 | D50: =IF(B50="",0,COUNT(INDEX(Datos!$A$2:$AN$1048576,0,11))) -> 2400 | E50: =AND(C50>0,D50>=0.9*C50,OR(LEFT(CELL("format",INDEX(Datos!$A$2:$AN$2,1,11)),1)="D",MIN(1,SUMPRODUCT(--ISNUMBER(SEARCH({"fecha","date","periodo","timestamp"},G50))))>0)) -> FALSE | F50: =AND(C50>0,D50>=0.9*C50,NOT(E50),MIN(1,SUMPRODUCT(--ISNUMBER(SEARCH({" id "," id"," cod"," nit "," cedula"," cédula"," telefono"," teléfono"," celular"," sku"," factura"," numero"," número"," nro"," año "," ano "," year"," zip"," postal"," documento"," guia"," guía"," orden"," cuenta"," pedido"," radicado"," consecutivo"," omr"," pob "," placa"," referencia"," ref "},G50))))=0,NOT(AND(K50>=20,K50>=0.95*MIN(500,C50),MIN(1,SUMPRODUCT(--ISNUMBER(SEARCH({"venta","ingreso","monto","importe","total","valor","factur","revenue","sales","amount","utilidad","ganancia","gasto"},G50))))+MIN(1,SUMPRODUCT(--ISNUMBER(SEARCH({"precio","price","unit","costo","cost","promedio","tasa","%","edad","calific","rating","puntaje","porcentaje","satisf","nps","score","nota"},G50))))+MIN(1,SUMPRODUCT(--ISNUMBER(SEARCH({"costo","cost"},G50))))+MIN(1,SUMPRODUCT(--ISNUMBER(SEARCH({" dias"," días","tiempo","demora","duraci","lead"," horas"},G50))))+MIN(1,SUMPRODUCT(--ISNUMBER(SEARCH({"cantidad","unidades","qty","peso","kilos"," kg","volumen","stock","existencia","inventario"},G50))))=0))) -> TRUE | G50: =" "&LOWER(SUBSTITUTE(SUBSTITUTE(SUBSTITUTE(B50,"_"," "),"-"," "),"."," "))&" " -> costo | H50: =AND(C50>0,D50<0.5*C50) -> FALSE | I50: =IF(F50,2+10*MIN(1,SUMPRODUCT(--ISNUMBER(SEARCH({"venta","ingreso","monto","importe","total","valor","factur","revenue","sales","amount","utilidad","ganancia","gasto"},G50))))+8*MIN(1,SUMPRODUCT(--ISNUMBER(SEARCH({"cantidad","unidades","qty","peso","kilos"," kg","volumen","stock","existencia","inventario"},G50))))*(1-MIN(1,SUMPRODUCT(--ISNUMBER(SEARCH({"venta","ingreso","monto","importe","total","valor","factur","revenue","sales","amount","utilidad","ganancia","gasto"},G50)))))-MIN(1,SUMPRODUCT(--ISNUMBER(SEARCH({"precio","price","unit","costo","cost","promedio","tasa","%","edad","calific","rating","puntaje","porcentaje","satisf","nps","score","nota"},G50))))+0.030,0) -> 1.03 | J50: =IF(AND(H50,K50>=2),IF(K50<=40,2+10*MIN(1,SUMPRODUCT(--ISNUMBER(SEARCH({"categor","region","región","producto","linea","línea","segmento","canal","ciudad","tienda","sucursal","vendedor","cliente","tipo","marca","zona","sede","courier","transportadora","oficina","trayecto","motivo","clasifica","proceso"},G50))))+3*AND(K50>=4,K50<=25),0.5+MIN(1,SUMPRODUCT(--ISNUMBER(SEARCH({"categor","region","región","producto","linea","línea","segmento","canal","ciudad","tienda","sucursal","vendedor","cliente","tipo","marca","zona","sede","courier","transportadora","oficina","trayecto","motivo","clasifica","proceso"},G50)))))+0.030,0) -> 0 | K50: =IF(C50>0,SUMPRODUCT((INDEX(Datos!$A$2:$AN$501,0,11)<>"")/COUNTIF(INDEX(Datos!$A$2:$AN$501,0,11),INDEX(Datos!$A$2:$AN$501,0,11)&"")),0) -> 500 | L50: =IF(E50,1+MIN(1,SUMPRODUCT(--ISNUMBER(SEARCH({"fecha","date","periodo","timestamp"},G50))))+0.030,0) -> 0 | M50: =IF(AND(H50,K50>=2,K50<=15),MIN(1,SUMPRODUCT(--ISNUMBER(SEARCH({"etapa","fase","estado","stage","embudo","funnel","paso","status"},G50))))*(1+0.030),0) -> 0 | N50: =IF(H50,MIN(1,SUMPRODUCT(--ISNUMBER(SEARCH({"departamento","depto","dpto","depart"},G50))))*(1+0.030),0) -> 0 | O50: =IF(F50,MIN(1,SUMPRODUCT(--ISNUMBER(SEARCH({"costo","cost"},G50))))*(1+0.030),0) -> 1.03 | P50: =IF(B50=$E$6,0,I50+5*MIN(1,SUMPRODUCT(--ISNUMBER(SEARCH({" dias"," días","tiempo","demora","duraci","lead"," horas"},G50))))*(I50>0)) -> 1.03 | Q50: =IF(B50=$E$9,0,J50) -> 0 | R50: =IF(OR(B50=$E$6,INDEX($I$40:$I$79,MAX(1,$F$6))<12),0,O50) -> 1.03 | S50: =AND(C50>0,D50<0.5*C50,MIN(1,SUMPRODUCT(--ISNUMBER(SEARCH({"fecha","date","periodo","timestamp"},G50))))>0) -> FALSE
A51: 12 | B51: =IF(INDEX(Datos!$A$1:$AN$1,1,12)="","",INDEX(Datos!$A$1:$AN$1,1,12)&"") | C51: =IF(B51="",0,COUNTA(INDEX(Datos!$A$2:$AN$1048576,0,12))) -> 0 | D51: =IF(B51="",0,COUNT(INDEX(Datos!$A$2:$AN$1048576,0,12))) -> 0 | E51: =AND(C51>0,D51>=0.9*C51,OR(LEFT(CELL("format",INDEX(Datos!$A$2:$AN$2,1,12)),1)="D",MIN(1,SUMPRODUCT(--ISNUMBER(SEARCH({"fecha","date","periodo","timestamp"},G51))))>0)) -> FALSE | F51: =AND(C51>0,D51>=0.9*C51,NOT(E51),MIN(1,SUMPRODUCT(--ISNUMBER(SEARCH({" id "," id"," cod"," nit "," cedula"," cédula"," telefono"," teléfono"," celular"," sku"," factura"," numero"," número"," nro"," año "," ano "," year"," zip"," postal"," documento"," guia"," guía"," orden"," cuenta"," pedido"," radicado"," consecutivo"," omr"," pob "," placa"," referencia"," ref "},G51))))=0,NOT(AND(K51>=20,K51>=0.95*MIN(500,C51),MIN(1,SUMPRODUCT(--ISNUMBER(SEARCH({"venta","ingreso","monto","importe","total","valor","factur","revenue","sales","amount","utilidad","ganancia","gasto"},G51))))+MIN(1,SUMPRODUCT(--ISNUMBER(SEARCH({"precio","price","unit","costo","cost","promedio","tasa","%","edad","calific","rating","puntaje","porcentaje","satisf","nps","score","nota"},G51))))+MIN(1,SUMPRODUCT(--ISNUMBER(SEARCH({"costo","cost"},G51))))+MIN(1,SUMPRODUCT(--ISNUMBER(SEARCH({" dias"," días","tiempo","demora","duraci","lead"," horas"},G51))))+MIN(1,SUMPRODUCT(--ISNUMBER(SEARCH({"cantidad","unidades","qty","peso","kilos"," kg","volumen","stock","existencia","inventario"},G51))))=0))) -> FALSE | G51: =" "&LOWER(SUBSTITUTE(SUBSTITUTE(SUBSTITUTE(B51,"_"," "),"-"," "),"."," "))&" " | H51: =AND(C51>0,D51<0.5*C51) -> FALSE | I51: =IF(F51,2+10*MIN(1,SUMPRODUCT(--ISNUMBER(SEARCH({"venta","ingreso","monto","importe","total","valor","factur","revenue","sales","amount","utilidad","ganancia","gasto"},G51))))+8*MIN(1,SUMPRODUCT(--ISNUMBER(SEARCH({"cantidad","unidades","qty","peso","kilos"," kg","volumen","stock","existencia","inventario"},G51))))*(1-MIN(1,SUMPRODUCT(--ISNUMBER(SEARCH({"venta","ingreso","monto","importe","total","valor","factur","revenue","sales","amount","utilidad","ganancia","gasto"},G51)))))-MIN(1,SUMPRODUCT(--ISNUMBER(SEARCH({"precio","price","unit","costo","cost","promedio","tasa","%","edad","calific","rating","puntaje","porcentaje","satisf","nps","score","nota"},G51))))+0.029,0) -> 0 | J51: =IF(AND(H51,K51>=2),IF(K51<=40,2+10*MIN(1,SUMPRODUCT(--ISNUMBER(SEARCH({"categor","region","región","producto","linea","línea","segmento","canal","ciudad","tienda","sucursal","vendedor","cliente","tipo","marca","zona","sede","courier","transportadora","oficina","trayecto","motivo","clasifica","proceso"},G51))))+3*AND(K51>=4,K51<=25),0.5+MIN(1,SUMPRODUCT(--ISNUMBER(SEARCH({"categor","region","región","producto","linea","línea","segmento","canal","ciudad","tienda","sucursal","vendedor","cliente","tipo","marca","zona","sede","courier","transportadora","oficina","trayecto","motivo","clasifica","proceso"},G51)))))+0.029,0) -> 0 | K51: =IF(C51>0,SUMPRODUCT((INDEX(Datos!$A$2:$AN$501,0,12)<>"")/COUNTIF(INDEX(Datos!$A$2:$AN$501,0,12),INDEX(Datos!$A$2:$AN$501,0,12)&"")),0) -> 0 | L51: =IF(E51,1+MIN(1,SUMPRODUCT(--ISNUMBER(SEARCH({"fecha","date","periodo","timestamp"},G51))))+0.029,0) -> 0 | M51: =IF(AND(H51,K51>=2,K51<=15),MIN(1,SUMPRODUCT(--ISNUMBER(SEARCH({"etapa","fase","estado","stage","embudo","funnel","paso","status"},G51))))*(1+0.029),0) -> 0 | N51: =IF(H51,MIN(1,SUMPRODUCT(--ISNUMBER(SEARCH({"departamento","depto","dpto","depart"},G51))))*(1+0.029),0) -> 0 | O51: =IF(F51,MIN(1,SUMPRODUCT(--ISNUMBER(SEARCH({"costo","cost"},G51))))*(1+0.029),0) -> 0 | P51: =IF(B51=$E$6,0,I51+5*MIN(1,SUMPRODUCT(--ISNUMBER(SEARCH({" dias"," días","tiempo","demora","duraci","lead"," horas"},G51))))*(I51>0)) -> 0 | Q51: =IF(B51=$E$9,0,J51) -> 0 | R51: =IF(OR(B51=$E$6,INDEX($I$40:$I$79,MAX(1,$F$6))<12),0,O51) -> 0 | S51: =AND(C51>0,D51<0.5*C51,MIN(1,SUMPRODUCT(--ISNUMBER(SEARCH({"fecha","date","periodo","timestamp"},G51))))>0) -> FALSE
A52: 13 | B52: =IF(INDEX(Datos!$A$1:$AN$1,1,13)="","",INDEX(Datos!$A$1:$AN$1,1,13)&"") | C52: =IF(B52="",0,COUNTA(INDEX(Datos!$A$2:$AN$1048576,0,13))) -> 0 | D52: =IF(B52="",0,COUNT(INDEX(Datos!$A$2:$AN$1048576,0,13))) -> 0 | E52: =AND(C52>0,D52>=0.9*C52,OR(LEFT(CELL("format",INDEX(Datos!$A$2:$AN$2,1,13)),1)="D",MIN(1,SUMPRODUCT(--ISNUMBER(SEARCH({"fecha","date","periodo","timestamp"},G52))))>0)) -> FALSE | F52: =AND(C52>0,D52>=0.9*C52,NOT(E52),MIN(1,SUMPRODUCT(--ISNUMBER(SEARCH({" id "," id"," cod"," nit "," cedula"," cédula"," telefono"," teléfono"," celular"," sku"," factura"," numero"," número"," nro"," año "," ano "," year"," zip"," postal"," documento"," guia"," guía"," orden"," cuenta"," pedido"," radicado"," consecutivo"," omr"," pob "," placa"," referencia"," ref "},G52))))=0,NOT(AND(K52>=20,K52>=0.95*MIN(500,C52),MIN(1,SUMPRODUCT(--ISNUMBER(SEARCH({"venta","ingreso","monto","importe","total","valor","factur","revenue","sales","amount","utilidad","ganancia","gasto"},G52))))+MIN(1,SUMPRODUCT(--ISNUMBER(SEARCH({"precio","price","unit","costo","cost","promedio","tasa","%","edad","calific","rating","puntaje","porcentaje","satisf","nps","score","nota"},G52))))+MIN(1,SUMPRODUCT(--ISNUMBER(SEARCH({"costo","cost"},G52))))+MIN(1,SUMPRODUCT(--ISNUMBER(SEARCH({" dias"," días","tiempo","demora","duraci","lead"," horas"},G52))))+MIN(1,SUMPRODUCT(--ISNUMBER(SEARCH({"cantidad","unidades","qty","peso","kilos"," kg","volumen","stock","existencia","inventario"},G52))))=0))) -> FALSE | G52: =" "&LOWER(SUBSTITUTE(SUBSTITUTE(SUBSTITUTE(B52,"_"," "),"-"," "),"."," "))&" " | H52: =AND(C52>0,D52<0.5*C52) -> FALSE | I52: =IF(F52,2+10*MIN(1,SUMPRODUCT(--ISNUMBER(SEARCH({"venta","ingreso","monto","importe","total","valor","factur","revenue","sales","amount","utilidad","ganancia","gasto"},G52))))+8*MIN(1,SUMPRODUCT(--ISNUMBER(SEARCH({"cantidad","unidades","qty","peso","kilos"," kg","volumen","stock","existencia","inventario"},G52))))*(1-MIN(1,SUMPRODUCT(--ISNUMBER(SEARCH({"venta","ingreso","monto","importe","total","valor","factur","revenue","sales","amount","utilidad","ganancia","gasto"},G52)))))-MIN(1,SUMPRODUCT(--ISNUMBER(SEARCH({"precio","price","unit","costo","cost","promedio","tasa","%","edad","calific","rating","puntaje","porcentaje","satisf","nps","score","nota"},G52))))+0.028,0) -> 0 | J52: =IF(AND(H52,K52>=2),IF(K52<=40,2+10*MIN(1,SUMPRODUCT(--ISNUMBER(SEARCH({"categor","region","región","producto","linea","línea","segmento","canal","ciudad","tienda","sucursal","vendedor","cliente","tipo","marca","zona","sede","courier","transportadora","oficina","trayecto","motivo","clasifica","proceso"},G52))))+3*AND(K52>=4,K52<=25),0.5+MIN(1,SUMPRODUCT(--ISNUMBER(SEARCH({"categor","region","región","producto","linea","línea","segmento","canal","ciudad","tienda","sucursal","vendedor","cliente","tipo","marca","zona","sede","courier","transportadora","oficina","trayecto","motivo","clasifica","proceso"},G52)))))+0.028,0) -> 0 | K52: =IF(C52>0,SUMPRODUCT((INDEX(Datos!$A$2:$AN$501,0,13)<>"")/COUNTIF(INDEX(Datos!$A$2:$AN$501,0,13),INDEX(Datos!$A$2:$AN$501,0,13)&"")),0) -> 0 | L52: =IF(E52,1+MIN(1,SUMPRODUCT(--ISNUMBER(SEARCH({"fecha","date","periodo","timestamp"},G52))))+0.028,0) -> 0 | M52: =IF(AND(H52,K52>=2,K52<=15),MIN(1,SUMPRODUCT(--ISNUMBER(SEARCH({"etapa","fase","estado","stage","embudo","funnel","paso","status"},G52))))*(1+0.028),0) -> 0 | N52: =IF(H52,MIN(1,SUMPRODUCT(--ISNUMBER(SEARCH({"departamento","depto","dpto","depart"},G52))))*(1+0.028),0) -> 0 | O52: =IF(F52,MIN(1,SUMPRODUCT(--ISNUMBER(SEARCH({"costo","cost"},G52))))*(1+0.028),0) -> 0 | P52: =IF(B52=$E$6,0,I52+5*MIN(1,SUMPRODUCT(--ISNUMBER(SEARCH({" dias"," días","tiempo","demora","duraci","lead"," horas"},G52))))*(I52>0)) -> 0 | Q52: =IF(B52=$E$9,0,J52) -> 0 | R52: =IF(OR(B52=$E$6,INDEX($I$40:$I$79,MAX(1,$F$6))<12),0,O52) -> 0 | S52: =AND(C52>0,D52<0.5*C52,MIN(1,SUMPRODUCT(--ISNUMBER(SEARCH({"fecha","date","periodo","timestamp"},G52))))>0) -> FALSE
A53: 14 | B53: =IF(INDEX(Datos!$A$1:$AN$1,1,14)="","",INDEX(Datos!$A$1:$AN$1,1,14)&"") | C53: =IF(B53="",0,COUNTA(INDEX(Datos!$A$2:$AN$1048576,0,14))) -> 0 | D53: =IF(B53="",0,COUNT(INDEX(Datos!$A$2:$AN$1048576,0,14))) -> 0 | E53: =AND(C53>0,D53>=0.9*C53,OR(LEFT(CELL("format",INDEX(Datos!$A$2:$AN$2,1,14)),1)="D",MIN(1,SUMPRODUCT(--ISNUMBER(SEARCH({"fecha","date","periodo","timestamp"},G53))))>0)) -> FALSE | F53: =AND(C53>0,D53>=0.9*C53,NOT(E53),MIN(1,SUMPRODUCT(--ISNUMBER(SEARCH({" id "," id"," cod"," nit "," cedula"," cédula"," telefono"," teléfono"," celular"," sku"," factura"," numero"," número"," nro"," año "," ano "," year"," zip"," postal"," documento"," guia"," guía"," orden"," cuenta"," pedido"," radicado"," consecutivo"," omr"," pob "," placa"," referencia"," ref "},G53))))=0,NOT(AND(K53>=20,K53>=0.95*MIN(500,C53),MIN(1,SUMPRODUCT(--ISNUMBER(SEARCH({"venta","ingreso","monto","importe","total","valor","factur","revenue","sales","amount","utilidad","ganancia","gasto"},G53))))+MIN(1,SUMPRODUCT(--ISNUMBER(SEARCH({"precio","price","unit","costo","cost","promedio","tasa","%","edad","calific","rating","puntaje","porcentaje","satisf","nps","score","nota"},G53))))+MIN(1,SUMPRODUCT(--ISNUMBER(SEARCH({"costo","cost"},G53))))+MIN(1,SUMPRODUCT(--ISNUMBER(SEARCH({" dias"," días","tiempo","demora","duraci","lead"," horas"},G53))))+MIN(1,SUMPRODUCT(--ISNUMBER(SEARCH({"cantidad","unidades","qty","peso","kilos"," kg","volumen","stock","existencia","inventario"},G53))))=0))) -> FALSE | G53: =" "&LOWER(SUBSTITUTE(SUBSTITUTE(SUBSTITUTE(B53,"_"," "),"-"," "),"."," "))&" " | H53: =AND(C53>0,D53<0.5*C53) -> FALSE | I53: =IF(F53,2+10*MIN(1,SUMPRODUCT(--ISNUMBER(SEARCH({"venta","ingreso","monto","importe","total","valor","factur","revenue","sales","amount","utilidad","ganancia","gasto"},G53))))+8*MIN(1,SUMPRODUCT(--ISNUMBER(SEARCH({"cantidad","unidades","qty","peso","kilos"," kg","volumen","stock","existencia","inventario"},G53))))*(1-MIN(1,SUMPRODUCT(--ISNUMBER(SEARCH({"venta","ingreso","monto","importe","total","valor","factur","revenue","sales","amount","utilidad","ganancia","gasto"},G53)))))-MIN(1,SUMPRODUCT(--ISNUMBER(SEARCH({"precio","price","unit","costo","cost","promedio","tasa","%","edad","calific","rating","puntaje","porcentaje","satisf","nps","score","nota"},G53))))+0.027,0) -> 0 | J53: =IF(AND(H53,K53>=2),IF(K53<=40,2+10*MIN(1,SUMPRODUCT(--ISNUMBER(SEARCH({"categor","region","región","producto","linea","línea","segmento","canal","ciudad","tienda","sucursal","vendedor","cliente","tipo","marca","zona","sede","courier","transportadora","oficina","trayecto","motivo","clasifica","proceso"},G53))))+3*AND(K53>=4,K53<=25),0.5+MIN(1,SUMPRODUCT(--ISNUMBER(SEARCH({"categor","region","región","producto","linea","línea","segmento","canal","ciudad","tienda","sucursal","vendedor","cliente","tipo","marca","zona","sede","courier","transportadora","oficina","trayecto","motivo","clasifica","proceso"},G53)))))+0.027,0) -> 0 | K53: =IF(C53>0,SUMPRODUCT((INDEX(Datos!$A$2:$AN$501,0,14)<>"")/COUNTIF(INDEX(Datos!$A$2:$AN$501,0,14),INDEX(Datos!$A$2:$AN$501,0,14)&"")),0) -> 0 | L53: =IF(E53,1+MIN(1,SUMPRODUCT(--ISNUMBER(SEARCH({"fecha","date","periodo","timestamp"},G53))))+0.027,0) -> 0 | M53: =IF(AND(H53,K53>=2,K53<=15),MIN(1,SUMPRODUCT(--ISNUMBER(SEARCH({"etapa","fase","estado","stage","embudo","funnel","paso","status"},G53))))*(1+0.027),0) -> 0 | N53: =IF(H53,MIN(1,SUMPRODUCT(--ISNUMBER(SEARCH({"departamento","depto","dpto","depart"},G53))))*(1+0.027),0) -> 0 | O53: =IF(F53,MIN(1,SUMPRODUCT(--ISNUMBER(SEARCH({"costo","cost"},G53))))*(1+0.027),0) -> 0 | P53: =IF(B53=$E$6,0,I53+5*MIN(1,SUMPRODUCT(--ISNUMBER(SEARCH({" dias"," días","tiempo","demora","duraci","lead"," horas"},G53))))*(I53>0)) -> 0 | Q53: =IF(B53=$E$9,0,J53) -> 0 | R53: =IF(OR(B53=$E$6,INDEX($I$40:$I$79,MAX(1,$F$6))<12),0,O53) -> 0 | S53: =AND(C53>0,D53<0.5*C53,MIN(1,SUMPRODUCT(--ISNUMBER(SEARCH({"fecha","date","periodo","timestamp"},G53))))>0) -> FALSE
A54: 15 | B54: =IF(INDEX(Datos!$A$1:$AN$1,1,15)="","",INDEX(Datos!$A$1:$AN$1,1,15)&"") | C54: =IF(B54="",0,COUNTA(INDEX(Datos!$A$2:$AN$1048576,0,15))) -> 0 | D54: =IF(B54="",0,COUNT(INDEX(Datos!$A$2:$AN$1048576,0,15))) -> 0 | E54: =AND(C54>0,D54>=0.9*C54,OR(LEFT(CELL("format",INDEX(Datos!$A$2:$AN$2,1,15)),1)="D",MIN(1,SUMPRODUCT(--ISNUMBER(SEARCH({"fecha","date","periodo","timestamp"},G54))))>0)) -> FALSE | F54: =AND(C54>0,D54>=0.9*C54,NOT(E54),MIN(1,SUMPRODUCT(--ISNUMBER(SEARCH({" id "," id"," cod"," nit "," cedula"," cédula"," telefono"," teléfono"," celular"," sku"," factura"," numero"," número"," nro"," año "," ano "," year"," zip"," postal"," documento"," guia"," guía"," orden"," cuenta"," pedido"," radicado"," consecutivo"," omr"," pob "," placa"," referencia"," ref "},G54))))=0,NOT(AND(K54>=20,K54>=0.95*MIN(500,C54),MIN(1,SUMPRODUCT(--ISNUMBER(SEARCH({"venta","ingreso","monto","importe","total","valor","factur","revenue","sales","amount","utilidad","ganancia","gasto"},G54))))+MIN(1,SUMPRODUCT(--ISNUMBER(SEARCH({"precio","price","unit","costo","cost","promedio","tasa","%","edad","calific","rating","puntaje","porcentaje","satisf","nps","score","nota"},G54))))+MIN(1,SUMPRODUCT(--ISNUMBER(SEARCH({"costo","cost"},G54))))+MIN(1,SUMPRODUCT(--ISNUMBER(SEARCH({" dias"," días","tiempo","demora","duraci","lead"," horas"},G54))))+MIN(1,SUMPRODUCT(--ISNUMBER(SEARCH({"cantidad","unidades","qty","peso","kilos"," kg","volumen","stock","existencia","inventario"},G54))))=0))) -> FALSE | G54: =" "&LOWER(SUBSTITUTE(SUBSTITUTE(SUBSTITUTE(B54,"_"," "),"-"," "),"."," "))&" " | H54: =AND(C54>0,D54<0.5*C54) -> FALSE | I54: =IF(F54,2+10*MIN(1,SUMPRODUCT(--ISNUMBER(SEARCH({"venta","ingreso","monto","importe","total","valor","factur","revenue","sales","amount","utilidad","ganancia","gasto"},G54))))+8*MIN(1,SUMPRODUCT(--ISNUMBER(SEARCH({"cantidad","unidades","qty","peso","kilos"," kg","volumen","stock","existencia","inventario"},G54))))*(1-MIN(1,SUMPRODUCT(--ISNUMBER(SEARCH({"venta","ingreso","monto","importe","total","valor","factur","revenue","sales","amount","utilidad","ganancia","gasto"},G54)))))-MIN(1,SUMPRODUCT(--ISNUMBER(SEARCH({"precio","price","unit","costo","cost","promedio","tasa","%","edad","calific","rating","puntaje","porcentaje","satisf","nps","score","nota"},G54))))+0.026,0) -> 0 | J54: =IF(AND(H54,K54>=2),IF(K54<=40,2+10*MIN(1,SUMPRODUCT(--ISNUMBER(SEARCH({"categor","region","región","producto","linea","línea","segmento","canal","ciudad","tienda","sucursal","vendedor","cliente","tipo","marca","zona","sede","courier","transportadora","oficina","trayecto","motivo","clasifica","proceso"},G54))))+3*AND(K54>=4,K54<=25),0.5+MIN(1,SUMPRODUCT(--ISNUMBER(SEARCH({"categor","region","región","producto","linea","línea","segmento","canal","ciudad","tienda","sucursal","vendedor","cliente","tipo","marca","zona","sede","courier","transportadora","oficina","trayecto","motivo","clasifica","proceso"},G54)))))+0.026,0) -> 0 | K54: =IF(C54>0,SUMPRODUCT((INDEX(Datos!$A$2:$AN$501,0,15)<>"")/COUNTIF(INDEX(Datos!$A$2:$AN$501,0,15),INDEX(Datos!$A$2:$AN$501,0,15)&"")),0) -> 0 | L54: =IF(E54,1+MIN(1,SUMPRODUCT(--ISNUMBER(SEARCH({"fecha","date","periodo","timestamp"},G54))))+0.026,0) -> 0 | M54: =IF(AND(H54,K54>=2,K54<=15),MIN(1,SUMPRODUCT(--ISNUMBER(SEARCH({"etapa","fase","estado","stage","embudo","funnel","paso","status"},G54))))*(1+0.026),0) -> 0 | N54: =IF(H54,MIN(1,SUMPRODUCT(--ISNUMBER(SEARCH({"departamento","depto","dpto","depart"},G54))))*(1+0.026),0) -> 0 | O54: =IF(F54,MIN(1,SUMPRODUCT(--ISNUMBER(SEARCH({"costo","cost"},G54))))*(1+0.026),0) -> 0 | P54: =IF(B54=$E$6,0,I54+5*MIN(1,SUMPRODUCT(--ISNUMBER(SEARCH({" dias"," días","tiempo","demora","duraci","lead"," horas"},G54))))*(I54>0)) -> 0 | Q54: =IF(B54=$E$9,0,J54) -> 0 | R54: =IF(OR(B54=$E$6,INDEX($I$40:$I$79,MAX(1,$F$6))<12),0,O54) -> 0 | S54: =AND(C54>0,D54<0.5*C54,MIN(1,SUMPRODUCT(--ISNUMBER(SEARCH({"fecha","date","periodo","timestamp"},G54))))>0) -> FALSE
A55: 16 | B55: =IF(INDEX(Datos!$A$1:$AN$1,1,16)="","",INDEX(Datos!$A$1:$AN$1,1,16)&"") | C55: =IF(B55="",0,COUNTA(INDEX(Datos!$A$2:$AN$1048576,0,16))) -> 0 | D55: =IF(B55="",0,COUNT(INDEX(Datos!$A$2:$AN$1048576,0,16))) -> 0 | E55: =AND(C55>0,D55>=0.9*C55,OR(LEFT(CELL("format",INDEX(Datos!$A$2:$AN$2,1,16)),1)="D",MIN(1,SUMPRODUCT(--ISNUMBER(SEARCH({"fecha","date","periodo","timestamp"},G55))))>0)) -> FALSE | F55: =AND(C55>0,D55>=0.9*C55,NOT(E55),MIN(1,SUMPRODUCT(--ISNUMBER(SEARCH({" id "," id"," cod"," nit "," cedula"," cédula"," telefono"," teléfono"," celular"," sku"," factura"," numero"," número"," nro"," año "," ano "," year"," zip"," postal"," documento"," guia"," guía"," orden"," cuenta"," pedido"," radicado"," consecutivo"," omr"," pob "," placa"," referencia"," ref "},G55))))=0,NOT(AND(K55>=20,K55>=0.95*MIN(500,C55),MIN(1,SUMPRODUCT(--ISNUMBER(SEARCH({"venta","ingreso","monto","importe","total","valor","factur","revenue","sales","amount","utilidad","ganancia","gasto"},G55))))+MIN(1,SUMPRODUCT(--ISNUMBER(SEARCH({"precio","price","unit","costo","cost","promedio","tasa","%","edad","calific","rating","puntaje","porcentaje","satisf","nps","score","nota"},G55))))+MIN(1,SUMPRODUCT(--ISNUMBER(SEARCH({"costo","cost"},G55))))+MIN(1,SUMPRODUCT(--ISNUMBER(SEARCH({" dias"," días","tiempo","demora","duraci","lead"," horas"},G55))))+MIN(1,SUMPRODUCT(--ISNUMBER(SEARCH({"cantidad","unidades","qty","peso","kilos"," kg","volumen","stock","existencia","inventario"},G55))))=0))) -> FALSE | G55: =" "&LOWER(SUBSTITUTE(SUBSTITUTE(SUBSTITUTE(B55,"_"," "),"-"," "),"."," "))&" " | H55: =AND(C55>0,D55<0.5*C55) -> FALSE | I55: =IF(F55,2+10*MIN(1,SUMPRODUCT(--ISNUMBER(SEARCH({"venta","ingreso","monto","importe","total","valor","factur","revenue","sales","amount","utilidad","ganancia","gasto"},G55))))+8*MIN(1,SUMPRODUCT(--ISNUMBER(SEARCH({"cantidad","unidades","qty","peso","kilos"," kg","volumen","stock","existencia","inventario"},G55))))*(1-MIN(1,SUMPRODUCT(--ISNUMBER(SEARCH({"venta","ingreso","monto","importe","total","valor","factur","revenue","sales","amount","utilidad","ganancia","gasto"},G55)))))-MIN(1,SUMPRODUCT(--ISNUMBER(SEARCH({"precio","price","unit","costo","cost","promedio","tasa","%","edad","calific","rating","puntaje","porcentaje","satisf","nps","score","nota"},G55))))+0.025,0) -> 0 | J55: =IF(AND(H55,K55>=2),IF(K55<=40,2+10*MIN(1,SUMPRODUCT(--ISNUMBER(SEARCH({"categor","region","región","producto","linea","línea","segmento","canal","ciudad","tienda","sucursal","vendedor","cliente","tipo","marca","zona","sede","courier","transportadora","oficina","trayecto","motivo","clasifica","proceso"},G55))))+3*AND(K55>=4,K55<=25),0.5+MIN(1,SUMPRODUCT(--ISNUMBER(SEARCH({"categor","region","región","producto","linea","línea","segmento","canal","ciudad","tienda","sucursal","vendedor","cliente","tipo","marca","zona","sede","courier","transportadora","oficina","trayecto","motivo","clasifica","proceso"},G55)))))+0.025,0) -> 0 | K55: =IF(C55>0,SUMPRODUCT((INDEX(Datos!$A$2:$AN$501,0,16)<>"")/COUNTIF(INDEX(Datos!$A$2:$AN$501,0,16),INDEX(Datos!$A$2:$AN$501,0,16)&"")),0) -> 0 | L55: =IF(E55,1+MIN(1,SUMPRODUCT(--ISNUMBER(SEARCH({"fecha","date","periodo","timestamp"},G55))))+0.025,0) -> 0 | M55: =IF(AND(H55,K55>=2,K55<=15),MIN(1,SUMPRODUCT(--ISNUMBER(SEARCH({"etapa","fase","estado","stage","embudo","funnel","paso","status"},G55))))*(1+0.025),0) -> 0 | N55: =IF(H55,MIN(1,SUMPRODUCT(--ISNUMBER(SEARCH({"departamento","depto","dpto","depart"},G55))))*(1+0.025),0) -> 0 | O55: =IF(F55,MIN(1,SUMPRODUCT(--ISNUMBER(SEARCH({"costo","cost"},G55))))*(1+0.025),0) -> 0 | P55: =IF(B55=$E$6,0,I55+5*MIN(1,SUMPRODUCT(--ISNUMBER(SEARCH({" dias"," días","tiempo","demora","duraci","lead"," horas"},G55))))*(I55>0)) -> 0 | Q55: =IF(B55=$E$9,0,J55) -> 0 | R55: =IF(OR(B55=$E$6,INDEX($I$40:$I$79,MAX(1,$F$6))<12),0,O55) -> 0 | S55: =AND(C55>0,D55<0.5*C55,MIN(1,SUMPRODUCT(--ISNUMBER(SEARCH({"fecha","date","periodo","timestamp"},G55))))>0) -> FALSE
A56: 17 | B56: =IF(INDEX(Datos!$A$1:$AN$1,1,17)="","",INDEX(Datos!$A$1:$AN$1,1,17)&"") | C56: =IF(B56="",0,COUNTA(INDEX(Datos!$A$2:$AN$1048576,0,17))) -> 0 | D56: =IF(B56="",0,COUNT(INDEX(Datos!$A$2:$AN$1048576,0,17))) -> 0 | E56: =AND(C56>0,D56>=0.9*C56,OR(LEFT(CELL("format",INDEX(Datos!$A$2:$AN$2,1,17)),1)="D",MIN(1,SUMPRODUCT(--ISNUMBER(SEARCH({"fecha","date","periodo","timestamp"},G56))))>0)) -> FALSE | F56: =AND(C56>0,D56>=0.9*C56,NOT(E56),MIN(1,SUMPRODUCT(--ISNUMBER(SEARCH({" id "," id"," cod"," nit "," cedula"," cédula"," telefono"," teléfono"," celular"," sku"," factura"," numero"," número"," nro"," año "," ano "," year"," zip"," postal"," documento"," guia"," guía"," orden"," cuenta"," pedido"," radicado"," consecutivo"," omr"," pob "," placa"," referencia"," ref "},G56))))=0,NOT(AND(K56>=20,K56>=0.95*MIN(500,C56),MIN(1,SUMPRODUCT(--ISNUMBER(SEARCH({"venta","ingreso","monto","importe","total","valor","factur","revenue","sales","amount","utilidad","ganancia","gasto"},G56))))+MIN(1,SUMPRODUCT(--ISNUMBER(SEARCH({"precio","price","unit","costo","cost","promedio","tasa","%","edad","calific","rating","puntaje","porcentaje","satisf","nps","score","nota"},G56))))+MIN(1,SUMPRODUCT(--ISNUMBER(SEARCH({"costo","cost"},G56))))+MIN(1,SUMPRODUCT(--ISNUMBER(SEARCH({" dias"," días","tiempo","demora","duraci","lead"," horas"},G56))))+MIN(1,SUMPRODUCT(--ISNUMBER(SEARCH({"cantidad","unidades","qty","peso","kilos"," kg","volumen","stock","existencia","inventario"},G56))))=0))) -> FALSE | G56: =" "&LOWER(SUBSTITUTE(SUBSTITUTE(SUBSTITUTE(B56,"_"," "),"-"," "),"."," "))&" " | H56: =AND(C56>0,D56<0.5*C56) -> FALSE | I56: =IF(F56,2+10*MIN(1,SUMPRODUCT(--ISNUMBER(SEARCH({"venta","ingreso","monto","importe","total","valor","factur","revenue","sales","amount","utilidad","ganancia","gasto"},G56))))+8*MIN(1,SUMPRODUCT(--ISNUMBER(SEARCH({"cantidad","unidades","qty","peso","kilos"," kg","volumen","stock","existencia","inventario"},G56))))*(1-MIN(1,SUMPRODUCT(--ISNUMBER(SEARCH({"venta","ingreso","monto","importe","total","valor","factur","revenue","sales","amount","utilidad","ganancia","gasto"},G56)))))-MIN(1,SUMPRODUCT(--ISNUMBER(SEARCH({"precio","price","unit","costo","cost","promedio","tasa","%","edad","calific","rating","puntaje","porcentaje","satisf","nps","score","nota"},G56))))+0.024,0) -> 0 | J56: =IF(AND(H56,K56>=2),IF(K56<=40,2+10*MIN(1,SUMPRODUCT(--ISNUMBER(SEARCH({"categor","region","región","producto","linea","línea","segmento","canal","ciudad","tienda","sucursal","vendedor","cliente","tipo","marca","zona","sede","courier","transportadora","oficina","trayecto","motivo","clasifica","proceso"},G56))))+3*AND(K56>=4,K56<=25),0.5+MIN(1,SUMPRODUCT(--ISNUMBER(SEARCH({"categor","region","región","producto","linea","línea","segmento","canal","ciudad","tienda","sucursal","vendedor","cliente","tipo","marca","zona","sede","courier","transportadora","oficina","trayecto","motivo","clasifica","proceso"},G56)))))+0.024,0) -> 0 | K56: =IF(C56>0,SUMPRODUCT((INDEX(Datos!$A$2:$AN$501,0,17)<>"")/COUNTIF(INDEX(Datos!$A$2:$AN$501,0,17),INDEX(Datos!$A$2:$AN$501,0,17)&"")),0) -> 0 | L56: =IF(E56,1+MIN(1,SUMPRODUCT(--ISNUMBER(SEARCH({"fecha","date","periodo","timestamp"},G56))))+0.024,0) -> 0 | M56: =IF(AND(H56,K56>=2,K56<=15),MIN(1,SUMPRODUCT(--ISNUMBER(SEARCH({"etapa","fase","estado","stage","embudo","funnel","paso","status"},G56))))*(1+0.024),0) -> 0 | N56: =IF(H56,MIN(1,SUMPRODUCT(--ISNUMBER(SEARCH({"departamento","depto","dpto","depart"},G56))))*(1+0.024),0) -> 0 | O56: =IF(F56,MIN(1,SUMPRODUCT(--ISNUMBER(SEARCH({"costo","cost"},G56))))*(1+0.024),0) -> 0 | P56: =IF(B56=$E$6,0,I56+5*MIN(1,SUMPRODUCT(--ISNUMBER(SEARCH({" dias"," días","tiempo","demora","duraci","lead"," horas"},G56))))*(I56>0)) -> 0 | Q56: =IF(B56=$E$9,0,J56) -> 0 | R56: =IF(OR(B56=$E$6,INDEX($I$40:$I$79,MAX(1,$F$6))<12),0,O56) -> 0 | S56: =AND(C56>0,D56<0.5*C56,MIN(1,SUMPRODUCT(--ISNUMBER(SEARCH({"fecha","date","periodo","timestamp"},G56))))>0) -> FALSE
A57: 18 | B57: =IF(INDEX(Datos!$A$1:$AN$1,1,18)="","",INDEX(Datos!$A$1:$AN$1,1,18)&"") | C57: =IF(B57="",0,COUNTA(INDEX(Datos!$A$2:$AN$1048576,0,18))) -> 0 | D57: =IF(B57="",0,COUNT(INDEX(Datos!$A$2:$AN$1048576,0,18))) -> 0 | E57: =AND(C57>0,D57>=0.9*C57,OR(LEFT(CELL("format",INDEX(Datos!$A$2:$AN$2,1,18)),1)="D",MIN(1,SUMPRODUCT(--ISNUMBER(SEARCH({"fecha","date","periodo","timestamp"},G57))))>0)) -> FALSE | F57: =AND(C57>0,D57>=0.9*C57,NOT(E57),MIN(1,SUMPRODUCT(--ISNUMBER(SEARCH({" id "," id"," cod"," nit "," cedula"," cédula"," telefono"," teléfono"," celular"," sku"," factura"," numero"," número"," nro"," año "," ano "," year"," zip"," postal"," documento"," guia"," guía"," orden"," cuenta"," pedido"," radicado"," consecutivo"," omr"," pob "," placa"," referencia"," ref "},G57))))=0,NOT(AND(K57>=20,K57>=0.95*MIN(500,C57),MIN(1,SUMPRODUCT(--ISNUMBER(SEARCH({"venta","ingreso","monto","importe","total","valor","factur","revenue","sales","amount","utilidad","ganancia","gasto"},G57))))+MIN(1,SUMPRODUCT(--ISNUMBER(SEARCH({"precio","price","unit","costo","cost","promedio","tasa","%","edad","calific","rating","puntaje","porcentaje","satisf","nps","score","nota"},G57))))+MIN(1,SUMPRODUCT(--ISNUMBER(SEARCH({"costo","cost"},G57))))+MIN(1,SUMPRODUCT(--ISNUMBER(SEARCH({" dias"," días","tiempo","demora","duraci","lead"," horas"},G57))))+MIN(1,SUMPRODUCT(--ISNUMBER(SEARCH({"cantidad","unidades","qty","peso","kilos"," kg","volumen","stock","existencia","inventario"},G57))))=0))) -> FALSE | G57: =" "&LOWER(SUBSTITUTE(SUBSTITUTE(SUBSTITUTE(B57,"_"," "),"-"," "),"."," "))&" " | H57: =AND(C57>0,D57<0.5*C57) -> FALSE | I57: =IF(F57,2+10*MIN(1,SUMPRODUCT(--ISNUMBER(SEARCH({"venta","ingreso","monto","importe","total","valor","factur","revenue","sales","amount","utilidad","ganancia","gasto"},G57))))+8*MIN(1,SUMPRODUCT(--ISNUMBER(SEARCH({"cantidad","unidades","qty","peso","kilos"," kg","volumen","stock","existencia","inventario"},G57))))*(1-MIN(1,SUMPRODUCT(--ISNUMBER(SEARCH({"venta","ingreso","monto","importe","total","valor","factur","revenue","sales","amount","utilidad","ganancia","gasto"},G57)))))-MIN(1,SUMPRODUCT(--ISNUMBER(SEARCH({"precio","price","unit","costo","cost","promedio","tasa","%","edad","calific","rating","puntaje","porcentaje","satisf","nps","score","nota"},G57))))+0.023,0) -> 0 | J57: =IF(AND(H57,K57>=2),IF(K57<=40,2+10*MIN(1,SUMPRODUCT(--ISNUMBER(SEARCH({"categor","region","región","producto","linea","línea","segmento","canal","ciudad","tienda","sucursal","vendedor","cliente","tipo","marca","zona","sede","courier","transportadora","oficina","trayecto","motivo","clasifica","proceso"},G57))))+3*AND(K57>=4,K57<=25),0.5+MIN(1,SUMPRODUCT(--ISNUMBER(SEARCH({"categor","region","región","producto","linea","línea","segmento","canal","ciudad","tienda","sucursal","vendedor","cliente","tipo","marca","zona","sede","courier","transportadora","oficina","trayecto","motivo","clasifica","proceso"},G57)))))+0.023,0) -> 0 | K57: =IF(C57>0,SUMPRODUCT((INDEX(Datos!$A$2:$AN$501,0,18)<>"")/COUNTIF(INDEX(Datos!$A$2:$AN$501,0,18),INDEX(Datos!$A$2:$AN$501,0,18)&"")),0) -> 0 | L57: =IF(E57,1+MIN(1,SUMPRODUCT(--ISNUMBER(SEARCH({"fecha","date","periodo","timestamp"},G57))))+0.023,0) -> 0 | M57: =IF(AND(H57,K57>=2,K57<=15),MIN(1,SUMPRODUCT(--ISNUMBER(SEARCH({"etapa","fase","estado","stage","embudo","funnel","paso","status"},G57))))*(1+0.023),0) -> 0 | N57: =IF(H57,MIN(1,SUMPRODUCT(--ISNUMBER(SEARCH({"departamento","depto","dpto","depart"},G57))))*(1+0.023),0) -> 0 | O57: =IF(F57,MIN(1,SUMPRODUCT(--ISNUMBER(SEARCH({"costo","cost"},G57))))*(1+0.023),0) -> 0 | P57: =IF(B57=$E$6,0,I57+5*MIN(1,SUMPRODUCT(--ISNUMBER(SEARCH({" dias"," días","tiempo","demora","duraci","lead"," horas"},G57))))*(I57>0)) -> 0 | Q57: =IF(B57=$E$9,0,J57) -> 0 | R57: =IF(OR(B57=$E$6,INDEX($I$40:$I$79,MAX(1,$F$6))<12),0,O57) -> 0 | S57: =AND(C57>0,D57<0.5*C57,MIN(1,SUMPRODUCT(--ISNUMBER(SEARCH({"fecha","date","periodo","timestamp"},G57))))>0) -> FALSE
A58: 19 | B58: =IF(INDEX(Datos!$A$1:$AN$1,1,19)="","",INDEX(Datos!$A$1:$AN$1,1,19)&"") | C58: =IF(B58="",0,COUNTA(INDEX(Datos!$A$2:$AN$1048576,0,19))) -> 0 | D58: =IF(B58="",0,COUNT(INDEX(Datos!$A$2:$AN$1048576,0,19))) -> 0 | E58: =AND(C58>0,D58>=0.9*C58,OR(LEFT(CELL("format",INDEX(Datos!$A$2:$AN$2,1,19)),1)="D",MIN(1,SUMPRODUCT(--ISNUMBER(SEARCH({"fecha","date","periodo","timestamp"},G58))))>0)) -> FALSE | F58: =AND(C58>0,D58>=0.9*C58,NOT(E58),MIN(1,SUMPRODUCT(--ISNUMBER(SEARCH({" id "," id"," cod"," nit "," cedula"," cédula"," telefono"," teléfono"," celular"," sku"," factura"," numero"," número"," nro"," año "," ano "," year"," zip"," postal"," documento"," guia"," guía"," orden"," cuenta"," pedido"," radicado"," consecutivo"," omr"," pob "," placa"," referencia"," ref "},G58))))=0,NOT(AND(K58>=20,K58>=0.95*MIN(500,C58),MIN(1,SUMPRODUCT(--ISNUMBER(SEARCH({"venta","ingreso","monto","importe","total","valor","factur","revenue","sales","amount","utilidad","ganancia","gasto"},G58))))+MIN(1,SUMPRODUCT(--ISNUMBER(SEARCH({"precio","price","unit","costo","cost","promedio","tasa","%","edad","calific","rating","puntaje","porcentaje","satisf","nps","score","nota"},G58))))+MIN(1,SUMPRODUCT(--ISNUMBER(SEARCH({"costo","cost"},G58))))+MIN(1,SUMPRODUCT(--ISNUMBER(SEARCH({" dias"," días","tiempo","demora","duraci","lead"," horas"},G58))))+MIN(1,SUMPRODUCT(--ISNUMBER(SEARCH({"cantidad","unidades","qty","peso","kilos"," kg","volumen","stock","existencia","inventario"},G58))))=0))) -> FALSE | G58: =" "&LOWER(SUBSTITUTE(SUBSTITUTE(SUBSTITUTE(B58,"_"," "),"-"," "),"."," "))&" " | H58: =AND(C58>0,D58<0.5*C58) -> FALSE | I58: =IF(F58,2+10*MIN(1,SUMPRODUCT(--ISNUMBER(SEARCH({"venta","ingreso","monto","importe","total","valor","factur","revenue","sales","amount","utilidad","ganancia","gasto"},G58))))+8*MIN(1,SUMPRODUCT(--ISNUMBER(SEARCH({"cantidad","unidades","qty","peso","kilos"," kg","volumen","stock","existencia","inventario"},G58))))*(1-MIN(1,SUMPRODUCT(--ISNUMBER(SEARCH({"venta","ingreso","monto","importe","total","valor","factur","revenue","sales","amount","utilidad","ganancia","gasto"},G58)))))-MIN(1,SUMPRODUCT(--ISNUMBER(SEARCH({"precio","price","unit","costo","cost","promedio","tasa","%","edad","calific","rating","puntaje","porcentaje","satisf","nps","score","nota"},G58))))+0.022,0) -> 0 | J58: =IF(AND(H58,K58>=2),IF(K58<=40,2+10*MIN(1,SUMPRODUCT(--ISNUMBER(SEARCH({"categor","region","región","producto","linea","línea","segmento","canal","ciudad","tienda","sucursal","vendedor","cliente","tipo","marca","zona","sede","courier","transportadora","oficina","trayecto","motivo","clasifica","proceso"},G58))))+3*AND(K58>=4,K58<=25),0.5+MIN(1,SUMPRODUCT(--ISNUMBER(SEARCH({"categor","region","región","producto","linea","línea","segmento","canal","ciudad","tienda","sucursal","vendedor","cliente","tipo","marca","zona","sede","courier","transportadora","oficina","trayecto","motivo","clasifica","proceso"},G58)))))+0.022,0) -> 0 | K58: =IF(C58>0,SUMPRODUCT((INDEX(Datos!$A$2:$AN$501,0,19)<>"")/COUNTIF(INDEX(Datos!$A$2:$AN$501,0,19),INDEX(Datos!$A$2:$AN$501,0,19)&"")),0) -> 0 | L58: =IF(E58,1+MIN(1,SUMPRODUCT(--ISNUMBER(SEARCH({"fecha","date","periodo","timestamp"},G58))))+0.022,0) -> 0 | M58: =IF(AND(H58,K58>=2,K58<=15),MIN(1,SUMPRODUCT(--ISNUMBER(SEARCH({"etapa","fase","estado","stage","embudo","funnel","paso","status"},G58))))*(1+0.022),0) -> 0 | N58: =IF(H58,MIN(1,SUMPRODUCT(--ISNUMBER(SEARCH({"departamento","depto","dpto","depart"},G58))))*(1+0.022),0) -> 0 | O58: =IF(F58,MIN(1,SUMPRODUCT(--ISNUMBER(SEARCH({"costo","cost"},G58))))*(1+0.022),0) -> 0 | P58: =IF(B58=$E$6,0,I58+5*MIN(1,SUMPRODUCT(--ISNUMBER(SEARCH({" dias"," días","tiempo","demora","duraci","lead"," horas"},G58))))*(I58>0)) -> 0 | Q58: =IF(B58=$E$9,0,J58) -> 0 | R58: =IF(OR(B58=$E$6,INDEX($I$40:$I$79,MAX(1,$F$6))<12),0,O58) -> 0 | S58: =AND(C58>0,D58<0.5*C58,MIN(1,SUMPRODUCT(--ISNUMBER(SEARCH({"fecha","date","periodo","timestamp"},G58))))>0) -> FALSE
A59: 20 | B59: =IF(INDEX(Datos!$A$1:$AN$1,1,20)="","",INDEX(Datos!$A$1:$AN$1,1,20)&"") | C59: =IF(B59="",0,COUNTA(INDEX(Datos!$A$2:$AN$1048576,0,20))) -> 0 | D59: =IF(B59="",0,COUNT(INDEX(Datos!$A$2:$AN$1048576,0,20))) -> 0 | E59: =AND(C59>0,D59>=0.9*C59,OR(LEFT(CELL("format",INDEX(Datos!$A$2:$AN$2,1,20)),1)="D",MIN(1,SUMPRODUCT(--ISNUMBER(SEARCH({"fecha","date","periodo","timestamp"},G59))))>0)) -> FALSE | F59: =AND(C59>0,D59>=0.9*C59,NOT(E59),MIN(1,SUMPRODUCT(--ISNUMBER(SEARCH({" id "," id"," cod"," nit "," cedula"," cédula"," telefono"," teléfono"," celular"," sku"," factura"," numero"," número"," nro"," año "," ano "," year"," zip"," postal"," documento"," guia"," guía"," orden"," cuenta"," pedido"," radicado"," consecutivo"," omr"," pob "," placa"," referencia"," ref "},G59))))=0,NOT(AND(K59>=20,K59>=0.95*MIN(500,C59),MIN(1,SUMPRODUCT(--ISNUMBER(SEARCH({"venta","ingreso","monto","importe","total","valor","factur","revenue","sales","amount","utilidad","ganancia","gasto"},G59))))+MIN(1,SUMPRODUCT(--ISNUMBER(SEARCH({"precio","price","unit","costo","cost","promedio","tasa","%","edad","calific","rating","puntaje","porcentaje","satisf","nps","score","nota"},G59))))+MIN(1,SUMPRODUCT(--ISNUMBER(SEARCH({"costo","cost"},G59))))+MIN(1,SUMPRODUCT(--ISNUMBER(SEARCH({" dias"," días","tiempo","demora","duraci","lead"," horas"},G59))))+MIN(1,SUMPRODUCT(--ISNUMBER(SEARCH({"cantidad","unidades","qty","peso","kilos"," kg","volumen","stock","existencia","inventario"},G59))))=0))) -> FALSE | G59: =" "&LOWER(SUBSTITUTE(SUBSTITUTE(SUBSTITUTE(B59,"_"," "),"-"," "),"."," "))&" " | H59: =AND(C59>0,D59<0.5*C59) -> FALSE | I59: =IF(F59,2+10*MIN(1,SUMPRODUCT(--ISNUMBER(SEARCH({"venta","ingreso","monto","importe","total","valor","factur","revenue","sales","amount","utilidad","ganancia","gasto"},G59))))+8*MIN(1,SUMPRODUCT(--ISNUMBER(SEARCH({"cantidad","unidades","qty","peso","kilos"," kg","volumen","stock","existencia","inventario"},G59))))*(1-MIN(1,SUMPRODUCT(--ISNUMBER(SEARCH({"venta","ingreso","monto","importe","total","valor","factur","revenue","sales","amount","utilidad","ganancia","gasto"},G59)))))-MIN(1,SUMPRODUCT(--ISNUMBER(SEARCH({"precio","price","unit","costo","cost","promedio","tasa","%","edad","calific","rating","puntaje","porcentaje","satisf","nps","score","nota"},G59))))+0.021,0) -> 0 | J59: =IF(AND(H59,K59>=2),IF(K59<=40,2+10*MIN(1,SUMPRODUCT(--ISNUMBER(SEARCH({"categor","region","región","producto","linea","línea","segmento","canal","ciudad","tienda","sucursal","vendedor","cliente","tipo","marca","zona","sede","courier","transportadora","oficina","trayecto","motivo","clasifica","proceso"},G59))))+3*AND(K59>=4,K59<=25),0.5+MIN(1,SUMPRODUCT(--ISNUMBER(SEARCH({"categor","region","región","producto","linea","línea","segmento","canal","ciudad","tienda","sucursal","vendedor","cliente","tipo","marca","zona","sede","courier","transportadora","oficina","trayecto","motivo","clasifica","proceso"},G59)))))+0.021,0) -> 0 | K59: =IF(C59>0,SUMPRODUCT((INDEX(Datos!$A$2:$AN$501,0,20)<>"")/COUNTIF(INDEX(Datos!$A$2:$AN$501,0,20),INDEX(Datos!$A$2:$AN$501,0,20)&"")),0) -> 0 | L59: =IF(E59,1+MIN(1,SUMPRODUCT(--ISNUMBER(SEARCH({"fecha","date","periodo","timestamp"},G59))))+0.021,0) -> 0 | M59: =IF(AND(H59,K59>=2,K59<=15),MIN(1,SUMPRODUCT(--ISNUMBER(SEARCH({"etapa","fase","estado","stage","embudo","funnel","paso","status"},G59))))*(1+0.021),0) -> 0 | N59: =IF(H59,MIN(1,SUMPRODUCT(--ISNUMBER(SEARCH({"departamento","depto","dpto","depart"},G59))))*(1+0.021),0) -> 0 | O59: =IF(F59,MIN(1,SUMPRODUCT(--ISNUMBER(SEARCH({"costo","cost"},G59))))*(1+0.021),0) -> 0 | P59: =IF(B59=$E$6,0,I59+5*MIN(1,SUMPRODUCT(--ISNUMBER(SEARCH({" dias"," días","tiempo","demora","duraci","lead"," horas"},G59))))*(I59>0)) -> 0 | Q59: =IF(B59=$E$9,0,J59) -> 0 | R59: =IF(OR(B59=$E$6,INDEX($I$40:$I$79,MAX(1,$F$6))<12),0,O59) -> 0 | S59: =AND(C59>0,D59<0.5*C59,MIN(1,SUMPRODUCT(--ISNUMBER(SEARCH({"fecha","date","periodo","timestamp"},G59))))>0) -> FALSE
A60: 21 | B60: =IF(INDEX(Datos!$A$1:$AN$1,1,21)="","",INDEX(Datos!$A$1:$AN$1,1,21)&"") | C60: =IF(B60="",0,COUNTA(INDEX(Datos!$A$2:$AN$1048576,0,21))) -> 0 | D60: =IF(B60="",0,COUNT(INDEX(Datos!$A$2:$AN$1048576,0,21))) -> 0 | E60: =AND(C60>0,D60>=0.9*C60,OR(LEFT(CELL("format",INDEX(Datos!$A$2:$AN$2,1,21)),1)="D",MIN(1,SUMPRODUCT(--ISNUMBER(SEARCH({"fecha","date","periodo","timestamp"},G60))))>0)) -> FALSE | F60: =AND(C60>0,D60>=0.9*C60,NOT(E60),MIN(1,SUMPRODUCT(--ISNUMBER(SEARCH({" id "," id"," cod"," nit "," cedula"," cédula"," telefono"," teléfono"," celular"," sku"," factura"," numero"," número"," nro"," año "," ano "," year"," zip"," postal"," documento"," guia"," guía"," orden"," cuenta"," pedido"," radicado"," consecutivo"," omr"," pob "," placa"," referencia"," ref "},G60))))=0,NOT(AND(K60>=20,K60>=0.95*MIN(500,C60),MIN(1,SUMPRODUCT(--ISNUMBER(SEARCH({"venta","ingreso","monto","importe","total","valor","factur","revenue","sales","amount","utilidad","ganancia","gasto"},G60))))+MIN(1,SUMPRODUCT(--ISNUMBER(SEARCH({"precio","price","unit","costo","cost","promedio","tasa","%","edad","calific","rating","puntaje","porcentaje","satisf","nps","score","nota"},G60))))+MIN(1,SUMPRODUCT(--ISNUMBER(SEARCH({"costo","cost"},G60))))+MIN(1,SUMPRODUCT(--ISNUMBER(SEARCH({" dias"," días","tiempo","demora","duraci","lead"," horas"},G60))))+MIN(1,SUMPRODUCT(--ISNUMBER(SEARCH({"cantidad","unidades","qty","peso","kilos"," kg","volumen","stock","existencia","inventario"},G60))))=0))) -> FALSE | G60: =" "&LOWER(SUBSTITUTE(SUBSTITUTE(SUBSTITUTE(B60,"_"," "),"-"," "),"."," "))&" " | H60: =AND(C60>0,D60<0.5*C60) -> FALSE | I60: =IF(F60,2+10*MIN(1,SUMPRODUCT(--ISNUMBER(SEARCH({"venta","ingreso","monto","importe","total","valor","factur","revenue","sales","amount","utilidad","ganancia","gasto"},G60))))+8*MIN(1,SUMPRODUCT(--ISNUMBER(SEARCH({"cantidad","unidades","qty","peso","kilos"," kg","volumen","stock","existencia","inventario"},G60))))*(1-MIN(1,SUMPRODUCT(--ISNUMBER(SEARCH({"venta","ingreso","monto","importe","total","valor","factur","revenue","sales","amount","utilidad","ganancia","gasto"},G60)))))-MIN(1,SUMPRODUCT(--ISNUMBER(SEARCH({"precio","price","unit","costo","cost","promedio","tasa","%","edad","calific","rating","puntaje","porcentaje","satisf","nps","score","nota"},G60))))+0.020,0) -> 0 | J60: =IF(AND(H60,K60>=2),IF(K60<=40,2+10*MIN(1,SUMPRODUCT(--ISNUMBER(SEARCH({"categor","region","región","producto","linea","línea","segmento","canal","ciudad","tienda","sucursal","vendedor","cliente","tipo","marca","zona","sede","courier","transportadora","oficina","trayecto","motivo","clasifica","proceso"},G60))))+3*AND(K60>=4,K60<=25),0.5+MIN(1,SUMPRODUCT(--ISNUMBER(SEARCH({"categor","region","región","producto","linea","línea","segmento","canal","ciudad","tienda","sucursal","vendedor","cliente","tipo","marca","zona","sede","courier","transportadora","oficina","trayecto","motivo","clasifica","proceso"},G60)))))+0.020,0) -> 0 | K60: =IF(C60>0,SUMPRODUCT((INDEX(Datos!$A$2:$AN$501,0,21)<>"")/COUNTIF(INDEX(Datos!$A$2:$AN$501,0,21),INDEX(Datos!$A$2:$AN$501,0,21)&"")),0) -> 0 | L60: =IF(E60,1+MIN(1,SUMPRODUCT(--ISNUMBER(SEARCH({"fecha","date","periodo","timestamp"},G60))))+0.020,0) -> 0 | M60: =IF(AND(H60,K60>=2,K60<=15),MIN(1,SUMPRODUCT(--ISNUMBER(SEARCH({"etapa","fase","estado","stage","embudo","funnel","paso","status"},G60))))*(1+0.020),0) -> 0 | N60: =IF(H60,MIN(1,SUMPRODUCT(--ISNUMBER(SEARCH({"departamento","depto","dpto","depart"},G60))))*(1+0.020),0) -> 0 | O60: =IF(F60,MIN(1,SUMPRODUCT(--ISNUMBER(SEARCH({"costo","cost"},G60))))*(1+0.020),0) -> 0 | P60: =IF(B60=$E$6,0,I60+5*MIN(1,SUMPRODUCT(--ISNUMBER(SEARCH({" dias"," días","tiempo","demora","duraci","lead"," horas"},G60))))*(I60>0)) -> 0 | Q60: =IF(B60=$E$9,0,J60) -> 0 | R60: =IF(OR(B60=$E$6,INDEX($I$40:$I$79,MAX(1,$F$6))<12),0,O60) -> 0 | S60: =AND(C60>0,D60<0.5*C60,MIN(1,SUMPRODUCT(--ISNUMBER(SEARCH({"fecha","date","periodo","timestamp"},G60))))>0) -> FALSE
A61: 22 | B61: =IF(INDEX(Datos!$A$1:$AN$1,1,22)="","",INDEX(Datos!$A$1:$AN$1,1,22)&"") | C61: =IF(B61="",0,COUNTA(INDEX(Datos!$A$2:$AN$1048576,0,22))) -> 0 | D61: =IF(B61="",0,COUNT(INDEX(Datos!$A$2:$AN$1048576,0,22))) -> 0 | E61: =AND(C61>0,D61>=0.9*C61,OR(LEFT(CELL("format",INDEX(Datos!$A$2:$AN$2,1,22)),1)="D",MIN(1,SUMPRODUCT(--ISNUMBER(SEARCH({"fecha","date","periodo","timestamp"},G61))))>0)) -> FALSE | F61: =AND(C61>0,D61>=0.9*C61,NOT(E61),MIN(1,SUMPRODUCT(--ISNUMBER(SEARCH({" id "," id"," cod"," nit "," cedula"," cédula"," telefono"," teléfono"," celular"," sku"," factura"," numero"," número"," nro"," año "," ano "," year"," zip"," postal"," documento"," guia"," guía"," orden"," cuenta"," pedido"," radicado"," consecutivo"," omr"," pob "," placa"," referencia"," ref "},G61))))=0,NOT(AND(K61>=20,K61>=0.95*MIN(500,C61),MIN(1,SUMPRODUCT(--ISNUMBER(SEARCH({"venta","ingreso","monto","importe","total","valor","factur","revenue","sales","amount","utilidad","ganancia","gasto"},G61))))+MIN(1,SUMPRODUCT(--ISNUMBER(SEARCH({"precio","price","unit","costo","cost","promedio","tasa","%","edad","calific","rating","puntaje","porcentaje","satisf","nps","score","nota"},G61))))+MIN(1,SUMPRODUCT(--ISNUMBER(SEARCH({"costo","cost"},G61))))+MIN(1,SUMPRODUCT(--ISNUMBER(SEARCH({" dias"," días","tiempo","demora","duraci","lead"," horas"},G61))))+MIN(1,SUMPRODUCT(--ISNUMBER(SEARCH({"cantidad","unidades","qty","peso","kilos"," kg","volumen","stock","existencia","inventario"},G61))))=0))) -> FALSE | G61: =" "&LOWER(SUBSTITUTE(SUBSTITUTE(SUBSTITUTE(B61,"_"," "),"-"," "),"."," "))&" " | H61: =AND(C61>0,D61<0.5*C61) -> FALSE | I61: =IF(F61,2+10*MIN(1,SUMPRODUCT(--ISNUMBER(SEARCH({"venta","ingreso","monto","importe","total","valor","factur","revenue","sales","amount","utilidad","ganancia","gasto"},G61))))+8*MIN(1,SUMPRODUCT(--ISNUMBER(SEARCH({"cantidad","unidades","qty","peso","kilos"," kg","volumen","stock","existencia","inventario"},G61))))*(1-MIN(1,SUMPRODUCT(--ISNUMBER(SEARCH({"venta","ingreso","monto","importe","total","valor","factur","revenue","sales","amount","utilidad","ganancia","gasto"},G61)))))-MIN(1,SUMPRODUCT(--ISNUMBER(SEARCH({"precio","price","unit","costo","cost","promedio","tasa","%","edad","calific","rating","puntaje","porcentaje","satisf","nps","score","nota"},G61))))+0.019,0) -> 0 | J61: =IF(AND(H61,K61>=2),IF(K61<=40,2+10*MIN(1,SUMPRODUCT(--ISNUMBER(SEARCH({"categor","region","región","producto","linea","línea","segmento","canal","ciudad","tienda","sucursal","vendedor","cliente","tipo","marca","zona","sede","courier","transportadora","oficina","trayecto","motivo","clasifica","proceso"},G61))))+3*AND(K61>=4,K61<=25),0.5+MIN(1,SUMPRODUCT(--ISNUMBER(SEARCH({"categor","region","región","producto","linea","línea","segmento","canal","ciudad","tienda","sucursal","vendedor","cliente","tipo","marca","zona","sede","courier","transportadora","oficina","trayecto","motivo","clasifica","proceso"},G61)))))+0.019,0) -> 0 | K61: =IF(C61>0,SUMPRODUCT((INDEX(Datos!$A$2:$AN$501,0,22)<>"")/COUNTIF(INDEX(Datos!$A$2:$AN$501,0,22),INDEX(Datos!$A$2:$AN$501,0,22)&"")),0) -> 0 | L61: =IF(E61,1+MIN(1,SUMPRODUCT(--ISNUMBER(SEARCH({"fecha","date","periodo","timestamp"},G61))))+0.019,0) -> 0 | M61: =IF(AND(H61,K61>=2,K61<=15),MIN(1,SUMPRODUCT(--ISNUMBER(SEARCH({"etapa","fase","estado","stage","embudo","funnel","paso","status"},G61))))*(1+0.019),0) -> 0 | N61: =IF(H61,MIN(1,SUMPRODUCT(--ISNUMBER(SEARCH({"departamento","depto","dpto","depart"},G61))))*(1+0.019),0) -> 0 | O61: =IF(F61,MIN(1,SUMPRODUCT(--ISNUMBER(SEARCH({"costo","cost"},G61))))*(1+0.019),0) -> 0 | P61: =IF(B61=$E$6,0,I61+5*MIN(1,SUMPRODUCT(--ISNUMBER(SEARCH({" dias"," días","tiempo","demora","duraci","lead"," horas"},G61))))*(I61>0)) -> 0 | Q61: =IF(B61=$E$9,0,J61) -> 0 | R61: =IF(OR(B61=$E$6,INDEX($I$40:$I$79,MAX(1,$F$6))<12),0,O61) -> 0 | S61: =AND(C61>0,D61<0.5*C61,MIN(1,SUMPRODUCT(--ISNUMBER(SEARCH({"fecha","date","periodo","timestamp"},G61))))>0) -> FALSE
A62: 23 | B62: =IF(INDEX(Datos!$A$1:$AN$1,1,23)="","",INDEX(Datos!$A$1:$AN$1,1,23)&"") | C62: =IF(B62="",0,COUNTA(INDEX(Datos!$A$2:$AN$1048576,0,23))) -> 0 | D62: =IF(B62="",0,COUNT(INDEX(Datos!$A$2:$AN$1048576,0,23))) -> 0 | E62: =AND(C62>0,D62>=0.9*C62,OR(LEFT(CELL("format",INDEX(Datos!$A$2:$AN$2,1,23)),1)="D",MIN(1,SUMPRODUCT(--ISNUMBER(SEARCH({"fecha","date","periodo","timestamp"},G62))))>0)) -> FALSE | F62: =AND(C62>0,D62>=0.9*C62,NOT(E62),MIN(1,SUMPRODUCT(--ISNUMBER(SEARCH({" id "," id"," cod"," nit "," cedula"," cédula"," telefono"," teléfono"," celular"," sku"," factura"," numero"," número"," nro"," año "," ano "," year"," zip"," postal"," documento"," guia"," guía"," orden"," cuenta"," pedido"," radicado"," consecutivo"," omr"," pob "," placa"," referencia"," ref "},G62))))=0,NOT(AND(K62>=20,K62>=0.95*MIN(500,C62),MIN(1,SUMPRODUCT(--ISNUMBER(SEARCH({"venta","ingreso","monto","importe","total","valor","factur","revenue","sales","amount","utilidad","ganancia","gasto"},G62))))+MIN(1,SUMPRODUCT(--ISNUMBER(SEARCH({"precio","price","unit","costo","cost","promedio","tasa","%","edad","calific","rating","puntaje","porcentaje","satisf","nps","score","nota"},G62))))+MIN(1,SUMPRODUCT(--ISNUMBER(SEARCH({"costo","cost"},G62))))+MIN(1,SUMPRODUCT(--ISNUMBER(SEARCH({" dias"," días","tiempo","demora","duraci","lead"," horas"},G62))))+MIN(1,SUMPRODUCT(--ISNUMBER(SEARCH({"cantidad","unidades","qty","peso","kilos"," kg","volumen","stock","existencia","inventario"},G62))))=0))) -> FALSE | G62: =" "&LOWER(SUBSTITUTE(SUBSTITUTE(SUBSTITUTE(B62,"_"," "),"-"," "),"."," "))&" " | H62: =AND(C62>0,D62<0.5*C62) -> FALSE | I62: =IF(F62,2+10*MIN(1,SUMPRODUCT(--ISNUMBER(SEARCH({"venta","ingreso","monto","importe","total","valor","factur","revenue","sales","amount","utilidad","ganancia","gasto"},G62))))+8*MIN(1,SUMPRODUCT(--ISNUMBER(SEARCH({"cantidad","unidades","qty","peso","kilos"," kg","volumen","stock","existencia","inventario"},G62))))*(1-MIN(1,SUMPRODUCT(--ISNUMBER(SEARCH({"venta","ingreso","monto","importe","total","valor","factur","revenue","sales","amount","utilidad","ganancia","gasto"},G62)))))-MIN(1,SUMPRODUCT(--ISNUMBER(SEARCH({"precio","price","unit","costo","cost","promedio","tasa","%","edad","calific","rating","puntaje","porcentaje","satisf","nps","score","nota"},G62))))+0.018,0) -> 0 | J62: =IF(AND(H62,K62>=2),IF(K62<=40,2+10*MIN(1,SUMPRODUCT(--ISNUMBER(SEARCH({"categor","region","región","producto","linea","línea","segmento","canal","ciudad","tienda","sucursal","vendedor","cliente","tipo","marca","zona","sede","courier","transportadora","oficina","trayecto","motivo","clasifica","proceso"},G62))))+3*AND(K62>=4,K62<=25),0.5+MIN(1,SUMPRODUCT(--ISNUMBER(SEARCH({"categor","region","región","producto","linea","línea","segmento","canal","ciudad","tienda","sucursal","vendedor","cliente","tipo","marca","zona","sede","courier","transportadora","oficina","trayecto","motivo","clasifica","proceso"},G62)))))+0.018,0) -> 0 | K62: =IF(C62>0,SUMPRODUCT((INDEX(Datos!$A$2:$AN$501,0,23)<>"")/COUNTIF(INDEX(Datos!$A$2:$AN$501,0,23),INDEX(Datos!$A$2:$AN$501,0,23)&"")),0) -> 0 | L62: =IF(E62,1+MIN(1,SUMPRODUCT(--ISNUMBER(SEARCH({"fecha","date","periodo","timestamp"},G62))))+0.018,0) -> 0 | M62: =IF(AND(H62,K62>=2,K62<=15),MIN(1,SUMPRODUCT(--ISNUMBER(SEARCH({"etapa","fase","estado","stage","embudo","funnel","paso","status"},G62))))*(1+0.018),0) -> 0 | N62: =IF(H62,MIN(1,SUMPRODUCT(--ISNUMBER(SEARCH({"departamento","depto","dpto","depart"},G62))))*(1+0.018),0) -> 0 | O62: =IF(F62,MIN(1,SUMPRODUCT(--ISNUMBER(SEARCH({"costo","cost"},G62))))*(1+0.018),0) -> 0 | P62: =IF(B62=$E$6,0,I62+5*MIN(1,SUMPRODUCT(--ISNUMBER(SEARCH({" dias"," días","tiempo","demora","duraci","lead"," horas"},G62))))*(I62>0)) -> 0 | Q62: =IF(B62=$E$9,0,J62) -> 0 | R62: =IF(OR(B62=$E$6,INDEX($I$40:$I$79,MAX(1,$F$6))<12),0,O62) -> 0 | S62: =AND(C62>0,D62<0.5*C62,MIN(1,SUMPRODUCT(--ISNUMBER(SEARCH({"fecha","date","periodo","timestamp"},G62))))>0) -> FALSE
A63: 24 | B63: =IF(INDEX(Datos!$A$1:$AN$1,1,24)="","",INDEX(Datos!$A$1:$AN$1,1,24)&"") | C63: =IF(B63="",0,COUNTA(INDEX(Datos!$A$2:$AN$1048576,0,24))) -> 0 | D63: =IF(B63="",0,COUNT(INDEX(Datos!$A$2:$AN$1048576,0,24))) -> 0 | E63: =AND(C63>0,D63>=0.9*C63,OR(LEFT(CELL("format",INDEX(Datos!$A$2:$AN$2,1,24)),1)="D",MIN(1,SUMPRODUCT(--ISNUMBER(SEARCH({"fecha","date","periodo","timestamp"},G63))))>0)) -> FALSE | F63: =AND(C63>0,D63>=0.9*C63,NOT(E63),MIN(1,SUMPRODUCT(--ISNUMBER(SEARCH({" id "," id"," cod"," nit "," cedula"," cédula"," telefono"," teléfono"," celular"," sku"," factura"," numero"," número"," nro"," año "," ano "," year"," zip"," postal"," documento"," guia"," guía"," orden"," cuenta"," pedido"," radicado"," consecutivo"," omr"," pob "," placa"," referencia"," ref "},G63))))=0,NOT(AND(K63>=20,K63>=0.95*MIN(500,C63),MIN(1,SUMPRODUCT(--ISNUMBER(SEARCH({"venta","ingreso","monto","importe","total","valor","factur","revenue","sales","amount","utilidad","ganancia","gasto"},G63))))+MIN(1,SUMPRODUCT(--ISNUMBER(SEARCH({"precio","price","unit","costo","cost","promedio","tasa","%","edad","calific","rating","puntaje","porcentaje","satisf","nps","score","nota"},G63))))+MIN(1,SUMPRODUCT(--ISNUMBER(SEARCH({"costo","cost"},G63))))+MIN(1,SUMPRODUCT(--ISNUMBER(SEARCH({" dias"," días","tiempo","demora","duraci","lead"," horas"},G63))))+MIN(1,SUMPRODUCT(--ISNUMBER(SEARCH({"cantidad","unidades","qty","peso","kilos"," kg","volumen","stock","existencia","inventario"},G63))))=0))) -> FALSE | G63: =" "&LOWER(SUBSTITUTE(SUBSTITUTE(SUBSTITUTE(B63,"_"," "),"-"," "),"."," "))&" " | H63: =AND(C63>0,D63<0.5*C63) -> FALSE | I63: =IF(F63,2+10*MIN(1,SUMPRODUCT(--ISNUMBER(SEARCH({"venta","ingreso","monto","importe","total","valor","factur","revenue","sales","amount","utilidad","ganancia","gasto"},G63))))+8*MIN(1,SUMPRODUCT(--ISNUMBER(SEARCH({"cantidad","unidades","qty","peso","kilos"," kg","volumen","stock","existencia","inventario"},G63))))*(1-MIN(1,SUMPRODUCT(--ISNUMBER(SEARCH({"venta","ingreso","monto","importe","total","valor","factur","revenue","sales","amount","utilidad","ganancia","gasto"},G63)))))-MIN(1,SUMPRODUCT(--ISNUMBER(SEARCH({"precio","price","unit","costo","cost","promedio","tasa","%","edad","calific","rating","puntaje","porcentaje","satisf","nps","score","nota"},G63))))+0.017,0) -> 0 | J63: =IF(AND(H63,K63>=2),IF(K63<=40,2+10*MIN(1,SUMPRODUCT(--ISNUMBER(SEARCH({"categor","region","región","producto","linea","línea","segmento","canal","ciudad","tienda","sucursal","vendedor","cliente","tipo","marca","zona","sede","courier","transportadora","oficina","trayecto","motivo","clasifica","proceso"},G63))))+3*AND(K63>=4,K63<=25),0.5+MIN(1,SUMPRODUCT(--ISNUMBER(SEARCH({"categor","region","región","producto","linea","línea","segmento","canal","ciudad","tienda","sucursal","vendedor","cliente","tipo","marca","zona","sede","courier","transportadora","oficina","trayecto","motivo","clasifica","proceso"},G63)))))+0.017,0) -> 0 | K63: =IF(C63>0,SUMPRODUCT((INDEX(Datos!$A$2:$AN$501,0,24)<>"")/COUNTIF(INDEX(Datos!$A$2:$AN$501,0,24),INDEX(Datos!$A$2:$AN$501,0,24)&"")),0) -> 0 | L63: =IF(E63,1+MIN(1,SUMPRODUCT(--ISNUMBER(SEARCH({"fecha","date","periodo","timestamp"},G63))))+0.017,0) -> 0 | M63: =IF(AND(H63,K63>=2,K63<=15),MIN(1,SUMPRODUCT(--ISNUMBER(SEARCH({"etapa","fase","estado","stage","embudo","funnel","paso","status"},G63))))*(1+0.017),0) -> 0 | N63: =IF(H63,MIN(1,SUMPRODUCT(--ISNUMBER(SEARCH({"departamento","depto","dpto","depart"},G63))))*(1+0.017),0) -> 0 | O63: =IF(F63,MIN(1,SUMPRODUCT(--ISNUMBER(SEARCH({"costo","cost"},G63))))*(1+0.017),0) -> 0 | P63: =IF(B63=$E$6,0,I63+5*MIN(1,SUMPRODUCT(--ISNUMBER(SEARCH({" dias"," días","tiempo","demora","duraci","lead"," horas"},G63))))*(I63>0)) -> 0 | Q63: =IF(B63=$E$9,0,J63) -> 0 | R63: =IF(OR(B63=$E$6,INDEX($I$40:$I$79,MAX(1,$F$6))<12),0,O63) -> 0 | S63: =AND(C63>0,D63<0.5*C63,MIN(1,SUMPRODUCT(--ISNUMBER(SEARCH({"fecha","date","periodo","timestamp"},G63))))>0) -> FALSE
A64: 25 | B64: =IF(INDEX(Datos!$A$1:$AN$1,1,25)="","",INDEX(Datos!$A$1:$AN$1,1,25)&"") | C64: =IF(B64="",0,COUNTA(INDEX(Datos!$A$2:$AN$1048576,0,25))) -> 0 | D64: =IF(B64="",0,COUNT(INDEX(Datos!$A$2:$AN$1048576,0,25))) -> 0 | E64: =AND(C64>0,D64>=0.9*C64,OR(LEFT(CELL("format",INDEX(Datos!$A$2:$AN$2,1,25)),1)="D",MIN(1,SUMPRODUCT(--ISNUMBER(SEARCH({"fecha","date","periodo","timestamp"},G64))))>0)) -> FALSE | F64: =AND(C64>0,D64>=0.9*C64,NOT(E64),MIN(1,SUMPRODUCT(--ISNUMBER(SEARCH({" id "," id"," cod"," nit "," cedula"," cédula"," telefono"," teléfono"," celular"," sku"," factura"," numero"," número"," nro"," año "," ano "," year"," zip"," postal"," documento"," guia"," guía"," orden"," cuenta"," pedido"," radicado"," consecutivo"," omr"," pob "," placa"," referencia"," ref "},G64))))=0,NOT(AND(K64>=20,K64>=0.95*MIN(500,C64),MIN(1,SUMPRODUCT(--ISNUMBER(SEARCH({"venta","ingreso","monto","importe","total","valor","factur","revenue","sales","amount","utilidad","ganancia","gasto"},G64))))+MIN(1,SUMPRODUCT(--ISNUMBER(SEARCH({"precio","price","unit","costo","cost","promedio","tasa","%","edad","calific","rating","puntaje","porcentaje","satisf","nps","score","nota"},G64))))+MIN(1,SUMPRODUCT(--ISNUMBER(SEARCH({"costo","cost"},G64))))+MIN(1,SUMPRODUCT(--ISNUMBER(SEARCH({" dias"," días","tiempo","demora","duraci","lead"," horas"},G64))))+MIN(1,SUMPRODUCT(--ISNUMBER(SEARCH({"cantidad","unidades","qty","peso","kilos"," kg","volumen","stock","existencia","inventario"},G64))))=0))) -> FALSE | G64: =" "&LOWER(SUBSTITUTE(SUBSTITUTE(SUBSTITUTE(B64,"_"," "),"-"," "),"."," "))&" " | H64: =AND(C64>0,D64<0.5*C64) -> FALSE | I64: =IF(F64,2+10*MIN(1,SUMPRODUCT(--ISNUMBER(SEARCH({"venta","ingreso","monto","importe","total","valor","factur","revenue","sales","amount","utilidad","ganancia","gasto"},G64))))+8*MIN(1,SUMPRODUCT(--ISNUMBER(SEARCH({"cantidad","unidades","qty","peso","kilos"," kg","volumen","stock","existencia","inventario"},G64))))*(1-MIN(1,SUMPRODUCT(--ISNUMBER(SEARCH({"venta","ingreso","monto","importe","total","valor","factur","revenue","sales","amount","utilidad","ganancia","gasto"},G64)))))-MIN(1,SUMPRODUCT(--ISNUMBER(SEARCH({"precio","price","unit","costo","cost","promedio","tasa","%","edad","calific","rating","puntaje","porcentaje","satisf","nps","score","nota"},G64))))+0.016,0) -> 0 | J64: =IF(AND(H64,K64>=2),IF(K64<=40,2+10*MIN(1,SUMPRODUCT(--ISNUMBER(SEARCH({"categor","region","región","producto","linea","línea","segmento","canal","ciudad","tienda","sucursal","vendedor","cliente","tipo","marca","zona","sede","courier","transportadora","oficina","trayecto","motivo","clasifica","proceso"},G64))))+3*AND(K64>=4,K64<=25),0.5+MIN(1,SUMPRODUCT(--ISNUMBER(SEARCH({"categor","region","región","producto","linea","línea","segmento","canal","ciudad","tienda","sucursal","vendedor","cliente","tipo","marca","zona","sede","courier","transportadora","oficina","trayecto","motivo","clasifica","proceso"},G64)))))+0.016,0) -> 0 | K64: =IF(C64>0,SUMPRODUCT((INDEX(Datos!$A$2:$AN$501,0,25)<>"")/COUNTIF(INDEX(Datos!$A$2:$AN$501,0,25),INDEX(Datos!$A$2:$AN$501,0,25)&"")),0) -> 0 | L64: =IF(E64,1+MIN(1,SUMPRODUCT(--ISNUMBER(SEARCH({"fecha","date","periodo","timestamp"},G64))))+0.016,0) -> 0 | M64: =IF(AND(H64,K64>=2,K64<=15),MIN(1,SUMPRODUCT(--ISNUMBER(SEARCH({"etapa","fase","estado","stage","embudo","funnel","paso","status"},G64))))*(1+0.016),0) -> 0 | N64: =IF(H64,MIN(1,SUMPRODUCT(--ISNUMBER(SEARCH({"departamento","depto","dpto","depart"},G64))))*(1+0.016),0) -> 0 | O64: =IF(F64,MIN(1,SUMPRODUCT(--ISNUMBER(SEARCH({"costo","cost"},G64))))*(1+0.016),0) -> 0 | P64: =IF(B64=$E$6,0,I64+5*MIN(1,SUMPRODUCT(--ISNUMBER(SEARCH({" dias"," días","tiempo","demora","duraci","lead"," horas"},G64))))*(I64>0)) -> 0 | Q64: =IF(B64=$E$9,0,J64) -> 0 | R64: =IF(OR(B64=$E$6,INDEX($I$40:$I$79,MAX(1,$F$6))<12),0,O64) -> 0 | S64: =AND(C64>0,D64<0.5*C64,MIN(1,SUMPRODUCT(--ISNUMBER(SEARCH({"fecha","date","periodo","timestamp"},G64))))>0) -> FALSE
A65: 26 | B65: =IF(INDEX(Datos!$A$1:$AN$1,1,26)="","",INDEX(Datos!$A$1:$AN$1,1,26)&"") | C65: =IF(B65="",0,COUNTA(INDEX(Datos!$A$2:$AN$1048576,0,26))) -> 0 | D65: =IF(B65="",0,COUNT(INDEX(Datos!$A$2:$AN$1048576,0,26))) -> 0 | E65: =AND(C65>0,D65>=0.9*C65,OR(LEFT(CELL("format",INDEX(Datos!$A$2:$AN$2,1,26)),1)="D",MIN(1,SUMPRODUCT(--ISNUMBER(SEARCH({"fecha","date","periodo","timestamp"},G65))))>0)) -> FALSE | F65: =AND(C65>0,D65>=0.9*C65,NOT(E65),MIN(1,SUMPRODUCT(--ISNUMBER(SEARCH({" id "," id"," cod"," nit "," cedula"," cédula"," telefono"," teléfono"," celular"," sku"," factura"," numero"," número"," nro"," año "," ano "," year"," zip"," postal"," documento"," guia"," guía"," orden"," cuenta"," pedido"," radicado"," consecutivo"," omr"," pob "," placa"," referencia"," ref "},G65))))=0,NOT(AND(K65>=20,K65>=0.95*MIN(500,C65),MIN(1,SUMPRODUCT(--ISNUMBER(SEARCH({"venta","ingreso","monto","importe","total","valor","factur","revenue","sales","amount","utilidad","ganancia","gasto"},G65))))+MIN(1,SUMPRODUCT(--ISNUMBER(SEARCH({"precio","price","unit","costo","cost","promedio","tasa","%","edad","calific","rating","puntaje","porcentaje","satisf","nps","score","nota"},G65))))+MIN(1,SUMPRODUCT(--ISNUMBER(SEARCH({"costo","cost"},G65))))+MIN(1,SUMPRODUCT(--ISNUMBER(SEARCH({" dias"," días","tiempo","demora","duraci","lead"," horas"},G65))))+MIN(1,SUMPRODUCT(--ISNUMBER(SEARCH({"cantidad","unidades","qty","peso","kilos"," kg","volumen","stock","existencia","inventario"},G65))))=0))) -> FALSE | G65: =" "&LOWER(SUBSTITUTE(SUBSTITUTE(SUBSTITUTE(B65,"_"," "),"-"," "),"."," "))&" " | H65: =AND(C65>0,D65<0.5*C65) -> FALSE | I65: =IF(F65,2+10*MIN(1,SUMPRODUCT(--ISNUMBER(SEARCH({"venta","ingreso","monto","importe","total","valor","factur","revenue","sales","amount","utilidad","ganancia","gasto"},G65))))+8*MIN(1,SUMPRODUCT(--ISNUMBER(SEARCH({"cantidad","unidades","qty","peso","kilos"," kg","volumen","stock","existencia","inventario"},G65))))*(1-MIN(1,SUMPRODUCT(--ISNUMBER(SEARCH({"venta","ingreso","monto","importe","total","valor","factur","revenue","sales","amount","utilidad","ganancia","gasto"},G65)))))-MIN(1,SUMPRODUCT(--ISNUMBER(SEARCH({"precio","price","unit","costo","cost","promedio","tasa","%","edad","calific","rating","puntaje","porcentaje","satisf","nps","score","nota"},G65))))+0.015,0) -> 0 | J65: =IF(AND(H65,K65>=2),IF(K65<=40,2+10*MIN(1,SUMPRODUCT(--ISNUMBER(SEARCH({"categor","region","región","producto","linea","línea","segmento","canal","ciudad","tienda","sucursal","vendedor","cliente","tipo","marca","zona","sede","courier","transportadora","oficina","trayecto","motivo","clasifica","proceso"},G65))))+3*AND(K65>=4,K65<=25),0.5+MIN(1,SUMPRODUCT(--ISNUMBER(SEARCH({"categor","region","región","producto","linea","línea","segmento","canal","ciudad","tienda","sucursal","vendedor","cliente","tipo","marca","zona","sede","courier","transportadora","oficina","trayecto","motivo","clasifica","proceso"},G65)))))+0.015,0) -> 0 | K65: =IF(C65>0,SUMPRODUCT((INDEX(Datos!$A$2:$AN$501,0,26)<>"")/COUNTIF(INDEX(Datos!$A$2:$AN$501,0,26),INDEX(Datos!$A$2:$AN$501,0,26)&"")),0) -> 0 | L65: =IF(E65,1+MIN(1,SUMPRODUCT(--ISNUMBER(SEARCH({"fecha","date","periodo","timestamp"},G65))))+0.015,0) -> 0 | M65: =IF(AND(H65,K65>=2,K65<=15),MIN(1,SUMPRODUCT(--ISNUMBER(SEARCH({"etapa","fase","estado","stage","embudo","funnel","paso","status"},G65))))*(1+0.015),0) -> 0 | N65: =IF(H65,MIN(1,SUMPRODUCT(--ISNUMBER(SEARCH({"departamento","depto","dpto","depart"},G65))))*(1+0.015),0) -> 0 | O65: =IF(F65,MIN(1,SUMPRODUCT(--ISNUMBER(SEARCH({"costo","cost"},G65))))*(1+0.015),0) -> 0 | P65: =IF(B65=$E$6,0,I65+5*MIN(1,SUMPRODUCT(--ISNUMBER(SEARCH({" dias"," días","tiempo","demora","duraci","lead"," horas"},G65))))*(I65>0)) -> 0 | Q65: =IF(B65=$E$9,0,J65) -> 0 | R65: =IF(OR(B65=$E$6,INDEX($I$40:$I$79,MAX(1,$F$6))<12),0,O65) -> 0 | S65: =AND(C65>0,D65<0.5*C65,MIN(1,SUMPRODUCT(--ISNUMBER(SEARCH({"fecha","date","periodo","timestamp"},G65))))>0) -> FALSE
A66: 27 | B66: =IF(INDEX(Datos!$A$1:$AN$1,1,27)="","",INDEX(Datos!$A$1:$AN$1,1,27)&"") | C66: =IF(B66="",0,COUNTA(INDEX(Datos!$A$2:$AN$1048576,0,27))) -> 0 | D66: =IF(B66="",0,COUNT(INDEX(Datos!$A$2:$AN$1048576,0,27))) -> 0 | E66: =AND(C66>0,D66>=0.9*C66,OR(LEFT(CELL("format",INDEX(Datos!$A$2:$AN$2,1,27)),1)="D",MIN(1,SUMPRODUCT(--ISNUMBER(SEARCH({"fecha","date","periodo","timestamp"},G66))))>0)) -> FALSE | F66: =AND(C66>0,D66>=0.9*C66,NOT(E66),MIN(1,SUMPRODUCT(--ISNUMBER(SEARCH({" id "," id"," cod"," nit "," cedula"," cédula"," telefono"," teléfono"," celular"," sku"," factura"," numero"," número"," nro"," año "," ano "," year"," zip"," postal"," documento"," guia"," guía"," orden"," cuenta"," pedido"," radicado"," consecutivo"," omr"," pob "," placa"," referencia"," ref "},G66))))=0,NOT(AND(K66>=20,K66>=0.95*MIN(500,C66),MIN(1,SUMPRODUCT(--ISNUMBER(SEARCH({"venta","ingreso","monto","importe","total","valor","factur","revenue","sales","amount","utilidad","ganancia","gasto"},G66))))+MIN(1,SUMPRODUCT(--ISNUMBER(SEARCH({"precio","price","unit","costo","cost","promedio","tasa","%","edad","calific","rating","puntaje","porcentaje","satisf","nps","score","nota"},G66))))+MIN(1,SUMPRODUCT(--ISNUMBER(SEARCH({"costo","cost"},G66))))+MIN(1,SUMPRODUCT(--ISNUMBER(SEARCH({" dias"," días","tiempo","demora","duraci","lead"," horas"},G66))))+MIN(1,SUMPRODUCT(--ISNUMBER(SEARCH({"cantidad","unidades","qty","peso","kilos"," kg","volumen","stock","existencia","inventario"},G66))))=0))) -> FALSE | G66: =" "&LOWER(SUBSTITUTE(SUBSTITUTE(SUBSTITUTE(B66,"_"," "),"-"," "),"."," "))&" " | H66: =AND(C66>0,D66<0.5*C66) -> FALSE | I66: =IF(F66,2+10*MIN(1,SUMPRODUCT(--ISNUMBER(SEARCH({"venta","ingreso","monto","importe","total","valor","factur","revenue","sales","amount","utilidad","ganancia","gasto"},G66))))+8*MIN(1,SUMPRODUCT(--ISNUMBER(SEARCH({"cantidad","unidades","qty","peso","kilos"," kg","volumen","stock","existencia","inventario"},G66))))*(1-MIN(1,SUMPRODUCT(--ISNUMBER(SEARCH({"venta","ingreso","monto","importe","total","valor","factur","revenue","sales","amount","utilidad","ganancia","gasto"},G66)))))-MIN(1,SUMPRODUCT(--ISNUMBER(SEARCH({"precio","price","unit","costo","cost","promedio","tasa","%","edad","calific","rating","puntaje","porcentaje","satisf","nps","score","nota"},G66))))+0.014,0) -> 0 | J66: =IF(AND(H66,K66>=2),IF(K66<=40,2+10*MIN(1,SUMPRODUCT(--ISNUMBER(SEARCH({"categor","region","región","producto","linea","línea","segmento","canal","ciudad","tienda","sucursal","vendedor","cliente","tipo","marca","zona","sede","courier","transportadora","oficina","trayecto","motivo","clasifica","proceso"},G66))))+3*AND(K66>=4,K66<=25),0.5+MIN(1,SUMPRODUCT(--ISNUMBER(SEARCH({"categor","region","región","producto","linea","línea","segmento","canal","ciudad","tienda","sucursal","vendedor","cliente","tipo","marca","zona","sede","courier","transportadora","oficina","trayecto","motivo","clasifica","proceso"},G66)))))+0.014,0) -> 0 | K66: =IF(C66>0,SUMPRODUCT((INDEX(Datos!$A$2:$AN$501,0,27)<>"")/COUNTIF(INDEX(Datos!$A$2:$AN$501,0,27),INDEX(Datos!$A$2:$AN$501,0,27)&"")),0) -> 0 | L66: =IF(E66,1+MIN(1,SUMPRODUCT(--ISNUMBER(SEARCH({"fecha","date","periodo","timestamp"},G66))))+0.014,0) -> 0 | M66: =IF(AND(H66,K66>=2,K66<=15),MIN(1,SUMPRODUCT(--ISNUMBER(SEARCH({"etapa","fase","estado","stage","embudo","funnel","paso","status"},G66))))*(1+0.014),0) -> 0 | N66: =IF(H66,MIN(1,SUMPRODUCT(--ISNUMBER(SEARCH({"departamento","depto","dpto","depart"},G66))))*(1+0.014),0) -> 0 | O66: =IF(F66,MIN(1,SUMPRODUCT(--ISNUMBER(SEARCH({"costo","cost"},G66))))*(1+0.014),0) -> 0 | P66: =IF(B66=$E$6,0,I66+5*MIN(1,SUMPRODUCT(--ISNUMBER(SEARCH({" dias"," días","tiempo","demora","duraci","lead"," horas"},G66))))*(I66>0)) -> 0 | Q66: =IF(B66=$E$9,0,J66) -> 0 | R66: =IF(OR(B66=$E$6,INDEX($I$40:$I$79,MAX(1,$F$6))<12),0,O66) -> 0 | S66: =AND(C66>0,D66<0.5*C66,MIN(1,SUMPRODUCT(--ISNUMBER(SEARCH({"fecha","date","periodo","timestamp"},G66))))>0) -> FALSE
A67: 28 | B67: =IF(INDEX(Datos!$A$1:$AN$1,1,28)="","",INDEX(Datos!$A$1:$AN$1,1,28)&"") | C67: =IF(B67="",0,COUNTA(INDEX(Datos!$A$2:$AN$1048576,0,28))) -> 0 | D67: =IF(B67="",0,COUNT(INDEX(Datos!$A$2:$AN$1048576,0,28))) -> 0 | E67: =AND(C67>0,D67>=0.9*C67,OR(LEFT(CELL("format",INDEX(Datos!$A$2:$AN$2,1,28)),1)="D",MIN(1,SUMPRODUCT(--ISNUMBER(SEARCH({"fecha","date","periodo","timestamp"},G67))))>0)) -> FALSE | F67: =AND(C67>0,D67>=0.9*C67,NOT(E67),MIN(1,SUMPRODUCT(--ISNUMBER(SEARCH({" id "," id"," cod"," nit "," cedula"," cédula"," telefono"," teléfono"," celular"," sku"," factura"," numero"," número"," nro"," año "," ano "," year"," zip"," postal"," documento"," guia"," guía"," orden"," cuenta"," pedido"," radicado"," consecutivo"," omr"," pob "," placa"," referencia"," ref "},G67))))=0,NOT(AND(K67>=20,K67>=0.95*MIN(500,C67),MIN(1,SUMPRODUCT(--ISNUMBER(SEARCH({"venta","ingreso","monto","importe","total","valor","factur","revenue","sales","amount","utilidad","ganancia","gasto"},G67))))+MIN(1,SUMPRODUCT(--ISNUMBER(SEARCH({"precio","price","unit","costo","cost","promedio","tasa","%","edad","calific","rating","puntaje","porcentaje","satisf","nps","score","nota"},G67))))+MIN(1,SUMPRODUCT(--ISNUMBER(SEARCH({"costo","cost"},G67))))+MIN(1,SUMPRODUCT(--ISNUMBER(SEARCH({" dias"," días","tiempo","demora","duraci","lead"," horas"},G67))))+MIN(1,SUMPRODUCT(--ISNUMBER(SEARCH({"cantidad","unidades","qty","peso","kilos"," kg","volumen","stock","existencia","inventario"},G67))))=0))) -> FALSE | G67: =" "&LOWER(SUBSTITUTE(SUBSTITUTE(SUBSTITUTE(B67,"_"," "),"-"," "),"."," "))&" " | H67: =AND(C67>0,D67<0.5*C67) -> FALSE | I67: =IF(F67,2+10*MIN(1,SUMPRODUCT(--ISNUMBER(SEARCH({"venta","ingreso","monto","importe","total","valor","factur","revenue","sales","amount","utilidad","ganancia","gasto"},G67))))+8*MIN(1,SUMPRODUCT(--ISNUMBER(SEARCH({"cantidad","unidades","qty","peso","kilos"," kg","volumen","stock","existencia","inventario"},G67))))*(1-MIN(1,SUMPRODUCT(--ISNUMBER(SEARCH({"venta","ingreso","monto","importe","total","valor","factur","revenue","sales","amount","utilidad","ganancia","gasto"},G67)))))-MIN(1,SUMPRODUCT(--ISNUMBER(SEARCH({"precio","price","unit","costo","cost","promedio","tasa","%","edad","calific","rating","puntaje","porcentaje","satisf","nps","score","nota"},G67))))+0.013,0) -> 0 | J67: =IF(AND(H67,K67>=2),IF(K67<=40,2+10*MIN(1,SUMPRODUCT(--ISNUMBER(SEARCH({"categor","region","región","producto","linea","línea","segmento","canal","ciudad","tienda","sucursal","vendedor","cliente","tipo","marca","zona","sede","courier","transportadora","oficina","trayecto","motivo","clasifica","proceso"},G67))))+3*AND(K67>=4,K67<=25),0.5+MIN(1,SUMPRODUCT(--ISNUMBER(SEARCH({"categor","region","región","producto","linea","línea","segmento","canal","ciudad","tienda","sucursal","vendedor","cliente","tipo","marca","zona","sede","courier","transportadora","oficina","trayecto","motivo","clasifica","proceso"},G67)))))+0.013,0) -> 0 | K67: =IF(C67>0,SUMPRODUCT((INDEX(Datos!$A$2:$AN$501,0,28)<>"")/COUNTIF(INDEX(Datos!$A$2:$AN$501,0,28),INDEX(Datos!$A$2:$AN$501,0,28)&"")),0) -> 0 | L67: =IF(E67,1+MIN(1,SUMPRODUCT(--ISNUMBER(SEARCH({"fecha","date","periodo","timestamp"},G67))))+0.013,0) -> 0 | M67: =IF(AND(H67,K67>=2,K67<=15),MIN(1,SUMPRODUCT(--ISNUMBER(SEARCH({"etapa","fase","estado","stage","embudo","funnel","paso","status"},G67))))*(1+0.013),0) -> 0 | N67: =IF(H67,MIN(1,SUMPRODUCT(--ISNUMBER(SEARCH({"departamento","depto","dpto","depart"},G67))))*(1+0.013),0) -> 0 | O67: =IF(F67,MIN(1,SUMPRODUCT(--ISNUMBER(SEARCH({"costo","cost"},G67))))*(1+0.013),0) -> 0 | P67: =IF(B67=$E$6,0,I67+5*MIN(1,SUMPRODUCT(--ISNUMBER(SEARCH({" dias"," días","tiempo","demora","duraci","lead"," horas"},G67))))*(I67>0)) -> 0 | Q67: =IF(B67=$E$9,0,J67) -> 0 | R67: =IF(OR(B67=$E$6,INDEX($I$40:$I$79,MAX(1,$F$6))<12),0,O67) -> 0 | S67: =AND(C67>0,D67<0.5*C67,MIN(1,SUMPRODUCT(--ISNUMBER(SEARCH({"fecha","date","periodo","timestamp"},G67))))>0) -> FALSE
A68: 29 | B68: =IF(INDEX(Datos!$A$1:$AN$1,1,29)="","",INDEX(Datos!$A$1:$AN$1,1,29)&"") | C68: =IF(B68="",0,COUNTA(INDEX(Datos!$A$2:$AN$1048576,0,29))) -> 0 | D68: =IF(B68="",0,COUNT(INDEX(Datos!$A$2:$AN$1048576,0,29))) -> 0 | E68: =AND(C68>0,D68>=0.9*C68,OR(LEFT(CELL("format",INDEX(Datos!$A$2:$AN$2,1,29)),1)="D",MIN(1,SUMPRODUCT(--ISNUMBER(SEARCH({"fecha","date","periodo","timestamp"},G68))))>0)) -> FALSE | F68: =AND(C68>0,D68>=0.9*C68,NOT(E68),MIN(1,SUMPRODUCT(--ISNUMBER(SEARCH({" id "," id"," cod"," nit "," cedula"," cédula"," telefono"," teléfono"," celular"," sku"," factura"," numero"," número"," nro"," año "," ano "," year"," zip"," postal"," documento"," guia"," guía"," orden"," cuenta"," pedido"," radicado"," consecutivo"," omr"," pob "," placa"," referencia"," ref "},G68))))=0,NOT(AND(K68>=20,K68>=0.95*MIN(500,C68),MIN(1,SUMPRODUCT(--ISNUMBER(SEARCH({"venta","ingreso","monto","importe","total","valor","factur","revenue","sales","amount","utilidad","ganancia","gasto"},G68))))+MIN(1,SUMPRODUCT(--ISNUMBER(SEARCH({"precio","price","unit","costo","cost","promedio","tasa","%","edad","calific","rating","puntaje","porcentaje","satisf","nps","score","nota"},G68))))+MIN(1,SUMPRODUCT(--ISNUMBER(SEARCH({"costo","cost"},G68))))+MIN(1,SUMPRODUCT(--ISNUMBER(SEARCH({" dias"," días","tiempo","demora","duraci","lead"," horas"},G68))))+MIN(1,SUMPRODUCT(--ISNUMBER(SEARCH({"cantidad","unidades","qty","peso","kilos"," kg","volumen","stock","existencia","inventario"},G68))))=0))) -> FALSE | G68: =" "&LOWER(SUBSTITUTE(SUBSTITUTE(SUBSTITUTE(B68,"_"," "),"-"," "),"."," "))&" " | H68: =AND(C68>0,D68<0.5*C68) -> FALSE | I68: =IF(F68,2+10*MIN(1,SUMPRODUCT(--ISNUMBER(SEARCH({"venta","ingreso","monto","importe","total","valor","factur","revenue","sales","amount","utilidad","ganancia","gasto"},G68))))+8*MIN(1,SUMPRODUCT(--ISNUMBER(SEARCH({"cantidad","unidades","qty","peso","kilos"," kg","volumen","stock","existencia","inventario"},G68))))*(1-MIN(1,SUMPRODUCT(--ISNUMBER(SEARCH({"venta","ingreso","monto","importe","total","valor","factur","revenue","sales","amount","utilidad","ganancia","gasto"},G68)))))-MIN(1,SUMPRODUCT(--ISNUMBER(SEARCH({"precio","price","unit","costo","cost","promedio","tasa","%","edad","calific","rating","puntaje","porcentaje","satisf","nps","score","nota"},G68))))+0.012,0) -> 0 | J68: =IF(AND(H68,K68>=2),IF(K68<=40,2+10*MIN(1,SUMPRODUCT(--ISNUMBER(SEARCH({"categor","region","región","producto","linea","línea","segmento","canal","ciudad","tienda","sucursal","vendedor","cliente","tipo","marca","zona","sede","courier","transportadora","oficina","trayecto","motivo","clasifica","proceso"},G68))))+3*AND(K68>=4,K68<=25),0.5+MIN(1,SUMPRODUCT(--ISNUMBER(SEARCH({"categor","region","región","producto","linea","línea","segmento","canal","ciudad","tienda","sucursal","vendedor","cliente","tipo","marca","zona","sede","courier","transportadora","oficina","trayecto","motivo","clasifica","proceso"},G68)))))+0.012,0) -> 0 | K68: =IF(C68>0,SUMPRODUCT((INDEX(Datos!$A$2:$AN$501,0,29)<>"")/COUNTIF(INDEX(Datos!$A$2:$AN$501,0,29),INDEX(Datos!$A$2:$AN$501,0,29)&"")),0) -> 0 | L68: =IF(E68,1+MIN(1,SUMPRODUCT(--ISNUMBER(SEARCH({"fecha","date","periodo","timestamp"},G68))))+0.012,0) -> 0 | M68: =IF(AND(H68,K68>=2,K68<=15),MIN(1,SUMPRODUCT(--ISNUMBER(SEARCH({"etapa","fase","estado","stage","embudo","funnel","paso","status"},G68))))*(1+0.012),0) -> 0 | N68: =IF(H68,MIN(1,SUMPRODUCT(--ISNUMBER(SEARCH({"departamento","depto","dpto","depart"},G68))))*(1+0.012),0) -> 0 | O68: =IF(F68,MIN(1,SUMPRODUCT(--ISNUMBER(SEARCH({"costo","cost"},G68))))*(1+0.012),0) -> 0 | P68: =IF(B68=$E$6,0,I68+5*MIN(1,SUMPRODUCT(--ISNUMBER(SEARCH({" dias"," días","tiempo","demora","duraci","lead"," horas"},G68))))*(I68>0)) -> 0 | Q68: =IF(B68=$E$9,0,J68) -> 0 | R68: =IF(OR(B68=$E$6,INDEX($I$40:$I$79,MAX(1,$F$6))<12),0,O68) -> 0 | S68: =AND(C68>0,D68<0.5*C68,MIN(1,SUMPRODUCT(--ISNUMBER(SEARCH({"fecha","date","periodo","timestamp"},G68))))>0) -> FALSE
A69: 30 | B69: =IF(INDEX(Datos!$A$1:$AN$1,1,30)="","",INDEX(Datos!$A$1:$AN$1,1,30)&"") | C69: =IF(B69="",0,COUNTA(INDEX(Datos!$A$2:$AN$1048576,0,30))) -> 0 | D69: =IF(B69="",0,COUNT(INDEX(Datos!$A$2:$AN$1048576,0,30))) -> 0 | E69: =AND(C69>0,D69>=0.9*C69,OR(LEFT(CELL("format",INDEX(Datos!$A$2:$AN$2,1,30)),1)="D",MIN(1,SUMPRODUCT(--ISNUMBER(SEARCH({"fecha","date","periodo","timestamp"},G69))))>0)) -> FALSE | F69: =AND(C69>0,D69>=0.9*C69,NOT(E69),MIN(1,SUMPRODUCT(--ISNUMBER(SEARCH({" id "," id"," cod"," nit "," cedula"," cédula"," telefono"," teléfono"," celular"," sku"," factura"," numero"," número"," nro"," año "," ano "," year"," zip"," postal"," documento"," guia"," guía"," orden"," cuenta"," pedido"," radicado"," consecutivo"," omr"," pob "," placa"," referencia"," ref "},G69))))=0,NOT(AND(K69>=20,K69>=0.95*MIN(500,C69),MIN(1,SUMPRODUCT(--ISNUMBER(SEARCH({"venta","ingreso","monto","importe","total","valor","factur","revenue","sales","amount","utilidad","ganancia","gasto"},G69))))+MIN(1,SUMPRODUCT(--ISNUMBER(SEARCH({"precio","price","unit","costo","cost","promedio","tasa","%","edad","calific","rating","puntaje","porcentaje","satisf","nps","score","nota"},G69))))+MIN(1,SUMPRODUCT(--ISNUMBER(SEARCH({"costo","cost"},G69))))+MIN(1,SUMPRODUCT(--ISNUMBER(SEARCH({" dias"," días","tiempo","demora","duraci","lead"," horas"},G69))))+MIN(1,SUMPRODUCT(--ISNUMBER(SEARCH({"cantidad","unidades","qty","peso","kilos"," kg","volumen","stock","existencia","inventario"},G69))))=0))) -> FALSE | G69: =" "&LOWER(SUBSTITUTE(SUBSTITUTE(SUBSTITUTE(B69,"_"," "),"-"," "),"."," "))&" " | H69: =AND(C69>0,D69<0.5*C69) -> FALSE | I69: =IF(F69,2+10*MIN(1,SUMPRODUCT(--ISNUMBER(SEARCH({"venta","ingreso","monto","importe","total","valor","factur","revenue","sales","amount","utilidad","ganancia","gasto"},G69))))+8*MIN(1,SUMPRODUCT(--ISNUMBER(SEARCH({"cantidad","unidades","qty","peso","kilos"," kg","volumen","stock","existencia","inventario"},G69))))*(1-MIN(1,SUMPRODUCT(--ISNUMBER(SEARCH({"venta","ingreso","monto","importe","total","valor","factur","revenue","sales","amount","utilidad","ganancia","gasto"},G69)))))-MIN(1,SUMPRODUCT(--ISNUMBER(SEARCH({"precio","price","unit","costo","cost","promedio","tasa","%","edad","calific","rating","puntaje","porcentaje","satisf","nps","score","nota"},G69))))+0.011,0) -> 0 | J69: =IF(AND(H69,K69>=2),IF(K69<=40,2+10*MIN(1,SUMPRODUCT(--ISNUMBER(SEARCH({"categor","region","región","producto","linea","línea","segmento","canal","ciudad","tienda","sucursal","vendedor","cliente","tipo","marca","zona","sede","courier","transportadora","oficina","trayecto","motivo","clasifica","proceso"},G69))))+3*AND(K69>=4,K69<=25),0.5+MIN(1,SUMPRODUCT(--ISNUMBER(SEARCH({"categor","region","región","producto","linea","línea","segmento","canal","ciudad","tienda","sucursal","vendedor","cliente","tipo","marca","zona","sede","courier","transportadora","oficina","trayecto","motivo","clasifica","proceso"},G69)))))+0.011,0) -> 0 | K69: =IF(C69>0,SUMPRODUCT((INDEX(Datos!$A$2:$AN$501,0,30)<>"")/COUNTIF(INDEX(Datos!$A$2:$AN$501,0,30),INDEX(Datos!$A$2:$AN$501,0,30)&"")),0) -> 0 | L69: =IF(E69,1+MIN(1,SUMPRODUCT(--ISNUMBER(SEARCH({"fecha","date","periodo","timestamp"},G69))))+0.011,0) -> 0 | M69: =IF(AND(H69,K69>=2,K69<=15),MIN(1,SUMPRODUCT(--ISNUMBER(SEARCH({"etapa","fase","estado","stage","embudo","funnel","paso","status"},G69))))*(1+0.011),0) -> 0 | N69: =IF(H69,MIN(1,SUMPRODUCT(--ISNUMBER(SEARCH({"departamento","depto","dpto","depart"},G69))))*(1+0.011),0) -> 0 | O69: =IF(F69,MIN(1,SUMPRODUCT(--ISNUMBER(SEARCH({"costo","cost"},G69))))*(1+0.011),0) -> 0 | P69: =IF(B69=$E$6,0,I69+5*MIN(1,SUMPRODUCT(--ISNUMBER(SEARCH({" dias"," días","tiempo","demora","duraci","lead"," horas"},G69))))*(I69>0)) -> 0 | Q69: =IF(B69=$E$9,0,J69) -> 0 | R69: =IF(OR(B69=$E$6,INDEX($I$40:$I$79,MAX(1,$F$6))<12),0,O69) -> 0 | S69: =AND(C69>0,D69<0.5*C69,MIN(1,SUMPRODUCT(--ISNUMBER(SEARCH({"fecha","date","periodo","timestamp"},G69))))>0) -> FALSE
A70: 31 | B70: =IF(INDEX(Datos!$A$1:$AN$1,1,31)="","",INDEX(Datos!$A$1:$AN$1,1,31)&"") | C70: =IF(B70="",0,COUNTA(INDEX(Datos!$A$2:$AN$1048576,0,31))) -> 0 | D70: =IF(B70="",0,COUNT(INDEX(Datos!$A$2:$AN$1048576,0,31))) -> 0 | E70: =AND(C70>0,D70>=0.9*C70,OR(LEFT(CELL("format",INDEX(Datos!$A$2:$AN$2,1,31)),1)="D",MIN(1,SUMPRODUCT(--ISNUMBER(SEARCH({"fecha","date","periodo","timestamp"},G70))))>0)) -> FALSE | F70: =AND(C70>0,D70>=0.9*C70,NOT(E70),MIN(1,SUMPRODUCT(--ISNUMBER(SEARCH({" id "," id"," cod"," nit "," cedula"," cédula"," telefono"," teléfono"," celular"," sku"," factura"," numero"," número"," nro"," año "," ano "," year"," zip"," postal"," documento"," guia"," guía"," orden"," cuenta"," pedido"," radicado"," consecutivo"," omr"," pob "," placa"," referencia"," ref "},G70))))=0,NOT(AND(K70>=20,K70>=0.95*MIN(500,C70),MIN(1,SUMPRODUCT(--ISNUMBER(SEARCH({"venta","ingreso","monto","importe","total","valor","factur","revenue","sales","amount","utilidad","ganancia","gasto"},G70))))+MIN(1,SUMPRODUCT(--ISNUMBER(SEARCH({"precio","price","unit","costo","cost","promedio","tasa","%","edad","calific","rating","puntaje","porcentaje","satisf","nps","score","nota"},G70))))+MIN(1,SUMPRODUCT(--ISNUMBER(SEARCH({"costo","cost"},G70))))+MIN(1,SUMPRODUCT(--ISNUMBER(SEARCH({" dias"," días","tiempo","demora","duraci","lead"," horas"},G70))))+MIN(1,SUMPRODUCT(--ISNUMBER(SEARCH({"cantidad","unidades","qty","peso","kilos"," kg","volumen","stock","existencia","inventario"},G70))))=0))) -> FALSE | G70: =" "&LOWER(SUBSTITUTE(SUBSTITUTE(SUBSTITUTE(B70,"_"," "),"-"," "),"."," "))&" " | H70: =AND(C70>0,D70<0.5*C70) -> FALSE | I70: =IF(F70,2+10*MIN(1,SUMPRODUCT(--ISNUMBER(SEARCH({"venta","ingreso","monto","importe","total","valor","factur","revenue","sales","amount","utilidad","ganancia","gasto"},G70))))+8*MIN(1,SUMPRODUCT(--ISNUMBER(SEARCH({"cantidad","unidades","qty","peso","kilos"," kg","volumen","stock","existencia","inventario"},G70))))*(1-MIN(1,SUMPRODUCT(--ISNUMBER(SEARCH({"venta","ingreso","monto","importe","total","valor","factur","revenue","sales","amount","utilidad","ganancia","gasto"},G70)))))-MIN(1,SUMPRODUCT(--ISNUMBER(SEARCH({"precio","price","unit","costo","cost","promedio","tasa","%","edad","calific","rating","puntaje","porcentaje","satisf","nps","score","nota"},G70))))+0.010,0) -> 0 | J70: =IF(AND(H70,K70>=2),IF(K70<=40,2+10*MIN(1,SUMPRODUCT(--ISNUMBER(SEARCH({"categor","region","región","producto","linea","línea","segmento","canal","ciudad","tienda","sucursal","vendedor","cliente","tipo","marca","zona","sede","courier","transportadora","oficina","trayecto","motivo","clasifica","proceso"},G70))))+3*AND(K70>=4,K70<=25),0.5+MIN(1,SUMPRODUCT(--ISNUMBER(SEARCH({"categor","region","región","producto","linea","línea","segmento","canal","ciudad","tienda","sucursal","vendedor","cliente","tipo","marca","zona","sede","courier","transportadora","oficina","trayecto","motivo","clasifica","proceso"},G70)))))+0.010,0) -> 0 | K70: =IF(C70>0,SUMPRODUCT((INDEX(Datos!$A$2:$AN$501,0,31)<>"")/COUNTIF(INDEX(Datos!$A$2:$AN$501,0,31),INDEX(Datos!$A$2:$AN$501,0,31)&"")),0) -> 0 | L70: =IF(E70,1+MIN(1,SUMPRODUCT(--ISNUMBER(SEARCH({"fecha","date","periodo","timestamp"},G70))))+0.010,0) -> 0 | M70: =IF(AND(H70,K70>=2,K70<=15),MIN(1,SUMPRODUCT(--ISNUMBER(SEARCH({"etapa","fase","estado","stage","embudo","funnel","paso","status"},G70))))*(1+0.010),0) -> 0 | N70: =IF(H70,MIN(1,SUMPRODUCT(--ISNUMBER(SEARCH({"departamento","depto","dpto","depart"},G70))))*(1+0.010),0) -> 0 | O70: =IF(F70,MIN(1,SUMPRODUCT(--ISNUMBER(SEARCH({"costo","cost"},G70))))*(1+0.010),0) -> 0 | P70: =IF(B70=$E$6,0,I70+5*MIN(1,SUMPRODUCT(--ISNUMBER(SEARCH({" dias"," días","tiempo","demora","duraci","lead"," horas"},G70))))*(I70>0)) -> 0 | Q70: =IF(B70=$E$9,0,J70) -> 0 | R70: =IF(OR(B70=$E$6,INDEX($I$40:$I$79,MAX(1,$F$6))<12),0,O70) -> 0 | S70: =AND(C70>0,D70<0.5*C70,MIN(1,SUMPRODUCT(--ISNUMBER(SEARCH({"fecha","date","periodo","timestamp"},G70))))>0) -> FALSE
A71: 32 | B71: =IF(INDEX(Datos!$A$1:$AN$1,1,32)="","",INDEX(Datos!$A$1:$AN$1,1,32)&"") | C71: =IF(B71="",0,COUNTA(INDEX(Datos!$A$2:$AN$1048576,0,32))) -> 0 | D71: =IF(B71="",0,COUNT(INDEX(Datos!$A$2:$AN$1048576,0,32))) -> 0 | E71: =AND(C71>0,D71>=0.9*C71,OR(LEFT(CELL("format",INDEX(Datos!$A$2:$AN$2,1,32)),1)="D",MIN(1,SUMPRODUCT(--ISNUMBER(SEARCH({"fecha","date","periodo","timestamp"},G71))))>0)) -> FALSE | F71: =AND(C71>0,D71>=0.9*C71,NOT(E71),MIN(1,SUMPRODUCT(--ISNUMBER(SEARCH({" id "," id"," cod"," nit "," cedula"," cédula"," telefono"," teléfono"," celular"," sku"," factura"," numero"," número"," nro"," año "," ano "," year"," zip"," postal"," documento"," guia"," guía"," orden"," cuenta"," pedido"," radicado"," consecutivo"," omr"," pob "," placa"," referencia"," ref "},G71))))=0,NOT(AND(K71>=20,K71>=0.95*MIN(500,C71),MIN(1,SUMPRODUCT(--ISNUMBER(SEARCH({"venta","ingreso","monto","importe","total","valor","factur","revenue","sales","amount","utilidad","ganancia","gasto"},G71))))+MIN(1,SUMPRODUCT(--ISNUMBER(SEARCH({"precio","price","unit","costo","cost","promedio","tasa","%","edad","calific","rating","puntaje","porcentaje","satisf","nps","score","nota"},G71))))+MIN(1,SUMPRODUCT(--ISNUMBER(SEARCH({"costo","cost"},G71))))+MIN(1,SUMPRODUCT(--ISNUMBER(SEARCH({" dias"," días","tiempo","demora","duraci","lead"," horas"},G71))))+MIN(1,SUMPRODUCT(--ISNUMBER(SEARCH({"cantidad","unidades","qty","peso","kilos"," kg","volumen","stock","existencia","inventario"},G71))))=0))) -> FALSE | G71: =" "&LOWER(SUBSTITUTE(SUBSTITUTE(SUBSTITUTE(B71,"_"," "),"-"," "),"."," "))&" " | H71: =AND(C71>0,D71<0.5*C71) -> FALSE | I71: =IF(F71,2+10*MIN(1,SUMPRODUCT(--ISNUMBER(SEARCH({"venta","ingreso","monto","importe","total","valor","factur","revenue","sales","amount","utilidad","ganancia","gasto"},G71))))+8*MIN(1,SUMPRODUCT(--ISNUMBER(SEARCH({"cantidad","unidades","qty","peso","kilos"," kg","volumen","stock","existencia","inventario"},G71))))*(1-MIN(1,SUMPRODUCT(--ISNUMBER(SEARCH({"venta","ingreso","monto","importe","total","valor","factur","revenue","sales","amount","utilidad","ganancia","gasto"},G71)))))-MIN(1,SUMPRODUCT(--ISNUMBER(SEARCH({"precio","price","unit","costo","cost","promedio","tasa","%","edad","calific","rating","puntaje","porcentaje","satisf","nps","score","nota"},G71))))+0.009,0) -> 0 | J71: =IF(AND(H71,K71>=2),IF(K71<=40,2+10*MIN(1,SUMPRODUCT(--ISNUMBER(SEARCH({"categor","region","región","producto","linea","línea","segmento","canal","ciudad","tienda","sucursal","vendedor","cliente","tipo","marca","zona","sede","courier","transportadora","oficina","trayecto","motivo","clasifica","proceso"},G71))))+3*AND(K71>=4,K71<=25),0.5+MIN(1,SUMPRODUCT(--ISNUMBER(SEARCH({"categor","region","región","producto","linea","línea","segmento","canal","ciudad","tienda","sucursal","vendedor","cliente","tipo","marca","zona","sede","courier","transportadora","oficina","trayecto","motivo","clasifica","proceso"},G71)))))+0.009,0) -> 0 | K71: =IF(C71>0,SUMPRODUCT((INDEX(Datos!$A$2:$AN$501,0,32)<>"")/COUNTIF(INDEX(Datos!$A$2:$AN$501,0,32),INDEX(Datos!$A$2:$AN$501,0,32)&"")),0) -> 0 | L71: =IF(E71,1+MIN(1,SUMPRODUCT(--ISNUMBER(SEARCH({"fecha","date","periodo","timestamp"},G71))))+0.009,0) -> 0 | M71: =IF(AND(H71,K71>=2,K71<=15),MIN(1,SUMPRODUCT(--ISNUMBER(SEARCH({"etapa","fase","estado","stage","embudo","funnel","paso","status"},G71))))*(1+0.009),0) -> 0 | N71: =IF(H71,MIN(1,SUMPRODUCT(--ISNUMBER(SEARCH({"departamento","depto","dpto","depart"},G71))))*(1+0.009),0) -> 0 | O71: =IF(F71,MIN(1,SUMPRODUCT(--ISNUMBER(SEARCH({"costo","cost"},G71))))*(1+0.009),0) -> 0 | P71: =IF(B71=$E$6,0,I71+5*MIN(1,SUMPRODUCT(--ISNUMBER(SEARCH({" dias"," días","tiempo","demora","duraci","lead"," horas"},G71))))*(I71>0)) -> 0 | Q71: =IF(B71=$E$9,0,J71) -> 0 | R71: =IF(OR(B71=$E$6,INDEX($I$40:$I$79,MAX(1,$F$6))<12),0,O71) -> 0 | S71: =AND(C71>0,D71<0.5*C71,MIN(1,SUMPRODUCT(--ISNUMBER(SEARCH({"fecha","date","periodo","timestamp"},G71))))>0) -> FALSE
A72: 33 | B72: =IF(INDEX(Datos!$A$1:$AN$1,1,33)="","",INDEX(Datos!$A$1:$AN$1,1,33)&"") | C72: =IF(B72="",0,COUNTA(INDEX(Datos!$A$2:$AN$1048576,0,33))) -> 0 | D72: =IF(B72="",0,COUNT(INDEX(Datos!$A$2:$AN$1048576,0,33))) -> 0 | E72: =AND(C72>0,D72>=0.9*C72,OR(LEFT(CELL("format",INDEX(Datos!$A$2:$AN$2,1,33)),1)="D",MIN(1,SUMPRODUCT(--ISNUMBER(SEARCH({"fecha","date","periodo","timestamp"},G72))))>0)) -> FALSE | F72: =AND(C72>0,D72>=0.9*C72,NOT(E72),MIN(1,SUMPRODUCT(--ISNUMBER(SEARCH({" id "," id"," cod"," nit "," cedula"," cédula"," telefono"," teléfono"," celular"," sku"," factura"," numero"," número"," nro"," año "," ano "," year"," zip"," postal"," documento"," guia"," guía"," orden"," cuenta"," pedido"," radicado"," consecutivo"," omr"," pob "," placa"," referencia"," ref "},G72))))=0,NOT(AND(K72>=20,K72>=0.95*MIN(500,C72),MIN(1,SUMPRODUCT(--ISNUMBER(SEARCH({"venta","ingreso","monto","importe","total","valor","factur","revenue","sales","amount","utilidad","ganancia","gasto"},G72))))+MIN(1,SUMPRODUCT(--ISNUMBER(SEARCH({"precio","price","unit","costo","cost","promedio","tasa","%","edad","calific","rating","puntaje","porcentaje","satisf","nps","score","nota"},G72))))+MIN(1,SUMPRODUCT(--ISNUMBER(SEARCH({"costo","cost"},G72))))+MIN(1,SUMPRODUCT(--ISNUMBER(SEARCH({" dias"," días","tiempo","demora","duraci","lead"," horas"},G72))))+MIN(1,SUMPRODUCT(--ISNUMBER(SEARCH({"cantidad","unidades","qty","peso","kilos"," kg","volumen","stock","existencia","inventario"},G72))))=0))) -> FALSE | G72: =" "&LOWER(SUBSTITUTE(SUBSTITUTE(SUBSTITUTE(B72,"_"," "),"-"," "),"."," "))&" " | H72: =AND(C72>0,D72<0.5*C72) -> FALSE | I72: =IF(F72,2+10*MIN(1,SUMPRODUCT(--ISNUMBER(SEARCH({"venta","ingreso","monto","importe","total","valor","factur","revenue","sales","amount","utilidad","ganancia","gasto"},G72))))+8*MIN(1,SUMPRODUCT(--ISNUMBER(SEARCH({"cantidad","unidades","qty","peso","kilos"," kg","volumen","stock","existencia","inventario"},G72))))*(1-MIN(1,SUMPRODUCT(--ISNUMBER(SEARCH({"venta","ingreso","monto","importe","total","valor","factur","revenue","sales","amount","utilidad","ganancia","gasto"},G72)))))-MIN(1,SUMPRODUCT(--ISNUMBER(SEARCH({"precio","price","unit","costo","cost","promedio","tasa","%","edad","calific","rating","puntaje","porcentaje","satisf","nps","score","nota"},G72))))+0.008,0) -> 0 | J72: =IF(AND(H72,K72>=2),IF(K72<=40,2+10*MIN(1,SUMPRODUCT(--ISNUMBER(SEARCH({"categor","region","región","producto","linea","línea","segmento","canal","ciudad","tienda","sucursal","vendedor","cliente","tipo","marca","zona","sede","courier","transportadora","oficina","trayecto","motivo","clasifica","proceso"},G72))))+3*AND(K72>=4,K72<=25),0.5+MIN(1,SUMPRODUCT(--ISNUMBER(SEARCH({"categor","region","región","producto","linea","línea","segmento","canal","ciudad","tienda","sucursal","vendedor","cliente","tipo","marca","zona","sede","courier","transportadora","oficina","trayecto","motivo","clasifica","proceso"},G72)))))+0.008,0) -> 0 | K72: =IF(C72>0,SUMPRODUCT((INDEX(Datos!$A$2:$AN$501,0,33)<>"")/COUNTIF(INDEX(Datos!$A$2:$AN$501,0,33),INDEX(Datos!$A$2:$AN$501,0,33)&"")),0) -> 0 | L72: =IF(E72,1+MIN(1,SUMPRODUCT(--ISNUMBER(SEARCH({"fecha","date","periodo","timestamp"},G72))))+0.008,0) -> 0 | M72: =IF(AND(H72,K72>=2,K72<=15),MIN(1,SUMPRODUCT(--ISNUMBER(SEARCH({"etapa","fase","estado","stage","embudo","funnel","paso","status"},G72))))*(1+0.008),0) -> 0 | N72: =IF(H72,MIN(1,SUMPRODUCT(--ISNUMBER(SEARCH({"departamento","depto","dpto","depart"},G72))))*(1+0.008),0) -> 0 | O72: =IF(F72,MIN(1,SUMPRODUCT(--ISNUMBER(SEARCH({"costo","cost"},G72))))*(1+0.008),0) -> 0 | P72: =IF(B72=$E$6,0,I72+5*MIN(1,SUMPRODUCT(--ISNUMBER(SEARCH({" dias"," días","tiempo","demora","duraci","lead"," horas"},G72))))*(I72>0)) -> 0 | Q72: =IF(B72=$E$9,0,J72) -> 0 | R72: =IF(OR(B72=$E$6,INDEX($I$40:$I$79,MAX(1,$F$6))<12),0,O72) -> 0 | S72: =AND(C72>0,D72<0.5*C72,MIN(1,SUMPRODUCT(--ISNUMBER(SEARCH({"fecha","date","periodo","timestamp"},G72))))>0) -> FALSE
A73: 34 | B73: =IF(INDEX(Datos!$A$1:$AN$1,1,34)="","",INDEX(Datos!$A$1:$AN$1,1,34)&"") | C73: =IF(B73="",0,COUNTA(INDEX(Datos!$A$2:$AN$1048576,0,34))) -> 0 | D73: =IF(B73="",0,COUNT(INDEX(Datos!$A$2:$AN$1048576,0,34))) -> 0 | E73: =AND(C73>0,D73>=0.9*C73,OR(LEFT(CELL("format",INDEX(Datos!$A$2:$AN$2,1,34)),1)="D",MIN(1,SUMPRODUCT(--ISNUMBER(SEARCH({"fecha","date","periodo","timestamp"},G73))))>0)) -> FALSE | F73: =AND(C73>0,D73>=0.9*C73,NOT(E73),MIN(1,SUMPRODUCT(--ISNUMBER(SEARCH({" id "," id"," cod"," nit "," cedula"," cédula"," telefono"," teléfono"," celular"," sku"," factura"," numero"," número"," nro"," año "," ano "," year"," zip"," postal"," documento"," guia"," guía"," orden"," cuenta"," pedido"," radicado"," consecutivo"," omr"," pob "," placa"," referencia"," ref "},G73))))=0,NOT(AND(K73>=20,K73>=0.95*MIN(500,C73),MIN(1,SUMPRODUCT(--ISNUMBER(SEARCH({"venta","ingreso","monto","importe","total","valor","factur","revenue","sales","amount","utilidad","ganancia","gasto"},G73))))+MIN(1,SUMPRODUCT(--ISNUMBER(SEARCH({"precio","price","unit","costo","cost","promedio","tasa","%","edad","calific","rating","puntaje","porcentaje","satisf","nps","score","nota"},G73))))+MIN(1,SUMPRODUCT(--ISNUMBER(SEARCH({"costo","cost"},G73))))+MIN(1,SUMPRODUCT(--ISNUMBER(SEARCH({" dias"," días","tiempo","demora","duraci","lead"," horas"},G73))))+MIN(1,SUMPRODUCT(--ISNUMBER(SEARCH({"cantidad","unidades","qty","peso","kilos"," kg","volumen","stock","existencia","inventario"},G73))))=0))) -> FALSE | G73: =" "&LOWER(SUBSTITUTE(SUBSTITUTE(SUBSTITUTE(B73,"_"," "),"-"," "),"."," "))&" " | H73: =AND(C73>0,D73<0.5*C73) -> FALSE | I73: =IF(F73,2+10*MIN(1,SUMPRODUCT(--ISNUMBER(SEARCH({"venta","ingreso","monto","importe","total","valor","factur","revenue","sales","amount","utilidad","ganancia","gasto"},G73))))+8*MIN(1,SUMPRODUCT(--ISNUMBER(SEARCH({"cantidad","unidades","qty","peso","kilos"," kg","volumen","stock","existencia","inventario"},G73))))*(1-MIN(1,SUMPRODUCT(--ISNUMBER(SEARCH({"venta","ingreso","monto","importe","total","valor","factur","revenue","sales","amount","utilidad","ganancia","gasto"},G73)))))-MIN(1,SUMPRODUCT(--ISNUMBER(SEARCH({"precio","price","unit","costo","cost","promedio","tasa","%","edad","calific","rating","puntaje","porcentaje","satisf","nps","score","nota"},G73))))+0.007,0) -> 0 | J73: =IF(AND(H73,K73>=2),IF(K73<=40,2+10*MIN(1,SUMPRODUCT(--ISNUMBER(SEARCH({"categor","region","región","producto","linea","línea","segmento","canal","ciudad","tienda","sucursal","vendedor","cliente","tipo","marca","zona","sede","courier","transportadora","oficina","trayecto","motivo","clasifica","proceso"},G73))))+3*AND(K73>=4,K73<=25),0.5+MIN(1,SUMPRODUCT(--ISNUMBER(SEARCH({"categor","region","región","producto","linea","línea","segmento","canal","ciudad","tienda","sucursal","vendedor","cliente","tipo","marca","zona","sede","courier","transportadora","oficina","trayecto","motivo","clasifica","proceso"},G73)))))+0.007,0) -> 0 | K73: =IF(C73>0,SUMPRODUCT((INDEX(Datos!$A$2:$AN$501,0,34)<>"")/COUNTIF(INDEX(Datos!$A$2:$AN$501,0,34),INDEX(Datos!$A$2:$AN$501,0,34)&"")),0) -> 0 | L73: =IF(E73,1+MIN(1,SUMPRODUCT(--ISNUMBER(SEARCH({"fecha","date","periodo","timestamp"},G73))))+0.007,0) -> 0 | M73: =IF(AND(H73,K73>=2,K73<=15),MIN(1,SUMPRODUCT(--ISNUMBER(SEARCH({"etapa","fase","estado","stage","embudo","funnel","paso","status"},G73))))*(1+0.007),0) -> 0 | N73: =IF(H73,MIN(1,SUMPRODUCT(--ISNUMBER(SEARCH({"departamento","depto","dpto","depart"},G73))))*(1+0.007),0) -> 0 | O73: =IF(F73,MIN(1,SUMPRODUCT(--ISNUMBER(SEARCH({"costo","cost"},G73))))*(1+0.007),0) -> 0 | P73: =IF(B73=$E$6,0,I73+5*MIN(1,SUMPRODUCT(--ISNUMBER(SEARCH({" dias"," días","tiempo","demora","duraci","lead"," horas"},G73))))*(I73>0)) -> 0 | Q73: =IF(B73=$E$9,0,J73) -> 0 | R73: =IF(OR(B73=$E$6,INDEX($I$40:$I$79,MAX(1,$F$6))<12),0,O73) -> 0 | S73: =AND(C73>0,D73<0.5*C73,MIN(1,SUMPRODUCT(--ISNUMBER(SEARCH({"fecha","date","periodo","timestamp"},G73))))>0) -> FALSE
A74: 35 | B74: =IF(INDEX(Datos!$A$1:$AN$1,1,35)="","",INDEX(Datos!$A$1:$AN$1,1,35)&"") | C74: =IF(B74="",0,COUNTA(INDEX(Datos!$A$2:$AN$1048576,0,35))) -> 0 | D74: =IF(B74="",0,COUNT(INDEX(Datos!$A$2:$AN$1048576,0,35))) -> 0 | E74: =AND(C74>0,D74>=0.9*C74,OR(LEFT(CELL("format",INDEX(Datos!$A$2:$AN$2,1,35)),1)="D",MIN(1,SUMPRODUCT(--ISNUMBER(SEARCH({"fecha","date","periodo","timestamp"},G74))))>0)) -> FALSE | F74: =AND(C74>0,D74>=0.9*C74,NOT(E74),MIN(1,SUMPRODUCT(--ISNUMBER(SEARCH({" id "," id"," cod"," nit "," cedula"," cédula"," telefono"," teléfono"," celular"," sku"," factura"," numero"," número"," nro"," año "," ano "," year"," zip"," postal"," documento"," guia"," guía"," orden"," cuenta"," pedido"," radicado"," consecutivo"," omr"," pob "," placa"," referencia"," ref "},G74))))=0,NOT(AND(K74>=20,K74>=0.95*MIN(500,C74),MIN(1,SUMPRODUCT(--ISNUMBER(SEARCH({"venta","ingreso","monto","importe","total","valor","factur","revenue","sales","amount","utilidad","ganancia","gasto"},G74))))+MIN(1,SUMPRODUCT(--ISNUMBER(SEARCH({"precio","price","unit","costo","cost","promedio","tasa","%","edad","calific","rating","puntaje","porcentaje","satisf","nps","score","nota"},G74))))+MIN(1,SUMPRODUCT(--ISNUMBER(SEARCH({"costo","cost"},G74))))+MIN(1,SUMPRODUCT(--ISNUMBER(SEARCH({" dias"," días","tiempo","demora","duraci","lead"," horas"},G74))))+MIN(1,SUMPRODUCT(--ISNUMBER(SEARCH({"cantidad","unidades","qty","peso","kilos"," kg","volumen","stock","existencia","inventario"},G74))))=0))) -> FALSE | G74: =" "&LOWER(SUBSTITUTE(SUBSTITUTE(SUBSTITUTE(B74,"_"," "),"-"," "),"."," "))&" " | H74: =AND(C74>0,D74<0.5*C74) -> FALSE | I74: =IF(F74,2+10*MIN(1,SUMPRODUCT(--ISNUMBER(SEARCH({"venta","ingreso","monto","importe","total","valor","factur","revenue","sales","amount","utilidad","ganancia","gasto"},G74))))+8*MIN(1,SUMPRODUCT(--ISNUMBER(SEARCH({"cantidad","unidades","qty","peso","kilos"," kg","volumen","stock","existencia","inventario"},G74))))*(1-MIN(1,SUMPRODUCT(--ISNUMBER(SEARCH({"venta","ingreso","monto","importe","total","valor","factur","revenue","sales","amount","utilidad","ganancia","gasto"},G74)))))-MIN(1,SUMPRODUCT(--ISNUMBER(SEARCH({"precio","price","unit","costo","cost","promedio","tasa","%","edad","calific","rating","puntaje","porcentaje","satisf","nps","score","nota"},G74))))+0.006,0) -> 0 | J74: =IF(AND(H74,K74>=2),IF(K74<=40,2+10*MIN(1,SUMPRODUCT(--ISNUMBER(SEARCH({"categor","region","región","producto","linea","línea","segmento","canal","ciudad","tienda","sucursal","vendedor","cliente","tipo","marca","zona","sede","courier","transportadora","oficina","trayecto","motivo","clasifica","proceso"},G74))))+3*AND(K74>=4,K74<=25),0.5+MIN(1,SUMPRODUCT(--ISNUMBER(SEARCH({"categor","region","región","producto","linea","línea","segmento","canal","ciudad","tienda","sucursal","vendedor","cliente","tipo","marca","zona","sede","courier","transportadora","oficina","trayecto","motivo","clasifica","proceso"},G74)))))+0.006,0) -> 0 | K74: =IF(C74>0,SUMPRODUCT((INDEX(Datos!$A$2:$AN$501,0,35)<>"")/COUNTIF(INDEX(Datos!$A$2:$AN$501,0,35),INDEX(Datos!$A$2:$AN$501,0,35)&"")),0) -> 0 | L74: =IF(E74,1+MIN(1,SUMPRODUCT(--ISNUMBER(SEARCH({"fecha","date","periodo","timestamp"},G74))))+0.006,0) -> 0 | M74: =IF(AND(H74,K74>=2,K74<=15),MIN(1,SUMPRODUCT(--ISNUMBER(SEARCH({"etapa","fase","estado","stage","embudo","funnel","paso","status"},G74))))*(1+0.006),0) -> 0 | N74: =IF(H74,MIN(1,SUMPRODUCT(--ISNUMBER(SEARCH({"departamento","depto","dpto","depart"},G74))))*(1+0.006),0) -> 0 | O74: =IF(F74,MIN(1,SUMPRODUCT(--ISNUMBER(SEARCH({"costo","cost"},G74))))*(1+0.006),0) -> 0 | P74: =IF(B74=$E$6,0,I74+5*MIN(1,SUMPRODUCT(--ISNUMBER(SEARCH({" dias"," días","tiempo","demora","duraci","lead"," horas"},G74))))*(I74>0)) -> 0 | Q74: =IF(B74=$E$9,0,J74) -> 0 | R74: =IF(OR(B74=$E$6,INDEX($I$40:$I$79,MAX(1,$F$6))<12),0,O74) -> 0 | S74: =AND(C74>0,D74<0.5*C74,MIN(1,SUMPRODUCT(--ISNUMBER(SEARCH({"fecha","date","periodo","timestamp"},G74))))>0) -> FALSE
A75: 36 | B75: =IF(INDEX(Datos!$A$1:$AN$1,1,36)="","",INDEX(Datos!$A$1:$AN$1,1,36)&"") | C75: =IF(B75="",0,COUNTA(INDEX(Datos!$A$2:$AN$1048576,0,36))) -> 0 | D75: =IF(B75="",0,COUNT(INDEX(Datos!$A$2:$AN$1048576,0,36))) -> 0 | E75: =AND(C75>0,D75>=0.9*C75,OR(LEFT(CELL("format",INDEX(Datos!$A$2:$AN$2,1,36)),1)="D",MIN(1,SUMPRODUCT(--ISNUMBER(SEARCH({"fecha","date","periodo","timestamp"},G75))))>0)) -> FALSE | F75: =AND(C75>0,D75>=0.9*C75,NOT(E75),MIN(1,SUMPRODUCT(--ISNUMBER(SEARCH({" id "," id"," cod"," nit "," cedula"," cédula"," telefono"," teléfono"," celular"," sku"," factura"," numero"," número"," nro"," año "," ano "," year"," zip"," postal"," documento"," guia"," guía"," orden"," cuenta"," pedido"," radicado"," consecutivo"," omr"," pob "," placa"," referencia"," ref "},G75))))=0,NOT(AND(K75>=20,K75>=0.95*MIN(500,C75),MIN(1,SUMPRODUCT(--ISNUMBER(SEARCH({"venta","ingreso","monto","importe","total","valor","factur","revenue","sales","amount","utilidad","ganancia","gasto"},G75))))+MIN(1,SUMPRODUCT(--ISNUMBER(SEARCH({"precio","price","unit","costo","cost","promedio","tasa","%","edad","calific","rating","puntaje","porcentaje","satisf","nps","score","nota"},G75))))+MIN(1,SUMPRODUCT(--ISNUMBER(SEARCH({"costo","cost"},G75))))+MIN(1,SUMPRODUCT(--ISNUMBER(SEARCH({" dias"," días","tiempo","demora","duraci","lead"," horas"},G75))))+MIN(1,SUMPRODUCT(--ISNUMBER(SEARCH({"cantidad","unidades","qty","peso","kilos"," kg","volumen","stock","existencia","inventario"},G75))))=0))) -> FALSE | G75: =" "&LOWER(SUBSTITUTE(SUBSTITUTE(SUBSTITUTE(B75,"_"," "),"-"," "),"."," "))&" " | H75: =AND(C75>0,D75<0.5*C75) -> FALSE | I75: =IF(F75,2+10*MIN(1,SUMPRODUCT(--ISNUMBER(SEARCH({"venta","ingreso","monto","importe","total","valor","factur","revenue","sales","amount","utilidad","ganancia","gasto"},G75))))+8*MIN(1,SUMPRODUCT(--ISNUMBER(SEARCH({"cantidad","unidades","qty","peso","kilos"," kg","volumen","stock","existencia","inventario"},G75))))*(1-MIN(1,SUMPRODUCT(--ISNUMBER(SEARCH({"venta","ingreso","monto","importe","total","valor","factur","revenue","sales","amount","utilidad","ganancia","gasto"},G75)))))-MIN(1,SUMPRODUCT(--ISNUMBER(SEARCH({"precio","price","unit","costo","cost","promedio","tasa","%","edad","calific","rating","puntaje","porcentaje","satisf","nps","score","nota"},G75))))+0.005,0) -> 0 | J75: =IF(AND(H75,K75>=2),IF(K75<=40,2+10*MIN(1,SUMPRODUCT(--ISNUMBER(SEARCH({"categor","region","región","producto","linea","línea","segmento","canal","ciudad","tienda","sucursal","vendedor","cliente","tipo","marca","zona","sede","courier","transportadora","oficina","trayecto","motivo","clasifica","proceso"},G75))))+3*AND(K75>=4,K75<=25),0.5+MIN(1,SUMPRODUCT(--ISNUMBER(SEARCH({"categor","region","región","producto","linea","línea","segmento","canal","ciudad","tienda","sucursal","vendedor","cliente","tipo","marca","zona","sede","courier","transportadora","oficina","trayecto","motivo","clasifica","proceso"},G75)))))+0.005,0) -> 0 | K75: =IF(C75>0,SUMPRODUCT((INDEX(Datos!$A$2:$AN$501,0,36)<>"")/COUNTIF(INDEX(Datos!$A$2:$AN$501,0,36),INDEX(Datos!$A$2:$AN$501,0,36)&"")),0) -> 0 | L75: =IF(E75,1+MIN(1,SUMPRODUCT(--ISNUMBER(SEARCH({"fecha","date","periodo","timestamp"},G75))))+0.005,0) -> 0 | M75: =IF(AND(H75,K75>=2,K75<=15),MIN(1,SUMPRODUCT(--ISNUMBER(SEARCH({"etapa","fase","estado","stage","embudo","funnel","paso","status"},G75))))*(1+0.005),0) -> 0 | N75: =IF(H75,MIN(1,SUMPRODUCT(--ISNUMBER(SEARCH({"departamento","depto","dpto","depart"},G75))))*(1+0.005),0) -> 0 | O75: =IF(F75,MIN(1,SUMPRODUCT(--ISNUMBER(SEARCH({"costo","cost"},G75))))*(1+0.005),0) -> 0 | P75: =IF(B75=$E$6,0,I75+5*MIN(1,SUMPRODUCT(--ISNUMBER(SEARCH({" dias"," días","tiempo","demora","duraci","lead"," horas"},G75))))*(I75>0)) -> 0 | Q75: =IF(B75=$E$9,0,J75) -> 0 | R75: =IF(OR(B75=$E$6,INDEX($I$40:$I$79,MAX(1,$F$6))<12),0,O75) -> 0 | S75: =AND(C75>0,D75<0.5*C75,MIN(1,SUMPRODUCT(--ISNUMBER(SEARCH({"fecha","date","periodo","timestamp"},G75))))>0) -> FALSE
A76: 37 | B76: =IF(INDEX(Datos!$A$1:$AN$1,1,37)="","",INDEX(Datos!$A$1:$AN$1,1,37)&"") | C76: =IF(B76="",0,COUNTA(INDEX(Datos!$A$2:$AN$1048576,0,37))) -> 0 | D76: =IF(B76="",0,COUNT(INDEX(Datos!$A$2:$AN$1048576,0,37))) -> 0 | E76: =AND(C76>0,D76>=0.9*C76,OR(LEFT(CELL("format",INDEX(Datos!$A$2:$AN$2,1,37)),1)="D",MIN(1,SUMPRODUCT(--ISNUMBER(SEARCH({"fecha","date","periodo","timestamp"},G76))))>0)) -> FALSE | F76: =AND(C76>0,D76>=0.9*C76,NOT(E76),MIN(1,SUMPRODUCT(--ISNUMBER(SEARCH({" id "," id"," cod"," nit "," cedula"," cédula"," telefono"," teléfono"," celular"," sku"," factura"," numero"," número"," nro"," año "," ano "," year"," zip"," postal"," documento"," guia"," guía"," orden"," cuenta"," pedido"," radicado"," consecutivo"," omr"," pob "," placa"," referencia"," ref "},G76))))=0,NOT(AND(K76>=20,K76>=0.95*MIN(500,C76),MIN(1,SUMPRODUCT(--ISNUMBER(SEARCH({"venta","ingreso","monto","importe","total","valor","factur","revenue","sales","amount","utilidad","ganancia","gasto"},G76))))+MIN(1,SUMPRODUCT(--ISNUMBER(SEARCH({"precio","price","unit","costo","cost","promedio","tasa","%","edad","calific","rating","puntaje","porcentaje","satisf","nps","score","nota"},G76))))+MIN(1,SUMPRODUCT(--ISNUMBER(SEARCH({"costo","cost"},G76))))+MIN(1,SUMPRODUCT(--ISNUMBER(SEARCH({" dias"," días","tiempo","demora","duraci","lead"," horas"},G76))))+MIN(1,SUMPRODUCT(--ISNUMBER(SEARCH({"cantidad","unidades","qty","peso","kilos"," kg","volumen","stock","existencia","inventario"},G76))))=0))) -> FALSE | G76: =" "&LOWER(SUBSTITUTE(SUBSTITUTE(SUBSTITUTE(B76,"_"," "),"-"," "),"."," "))&" " | H76: =AND(C76>0,D76<0.5*C76) -> FALSE | I76: =IF(F76,2+10*MIN(1,SUMPRODUCT(--ISNUMBER(SEARCH({"venta","ingreso","monto","importe","total","valor","factur","revenue","sales","amount","utilidad","ganancia","gasto"},G76))))+8*MIN(1,SUMPRODUCT(--ISNUMBER(SEARCH({"cantidad","unidades","qty","peso","kilos"," kg","volumen","stock","existencia","inventario"},G76))))*(1-MIN(1,SUMPRODUCT(--ISNUMBER(SEARCH({"venta","ingreso","monto","importe","total","valor","factur","revenue","sales","amount","utilidad","ganancia","gasto"},G76)))))-MIN(1,SUMPRODUCT(--ISNUMBER(SEARCH({"precio","price","unit","costo","cost","promedio","tasa","%","edad","calific","rating","puntaje","porcentaje","satisf","nps","score","nota"},G76))))+0.004,0) -> 0 | J76: =IF(AND(H76,K76>=2),IF(K76<=40,2+10*MIN(1,SUMPRODUCT(--ISNUMBER(SEARCH({"categor","region","región","producto","linea","línea","segmento","canal","ciudad","tienda","sucursal","vendedor","cliente","tipo","marca","zona","sede","courier","transportadora","oficina","trayecto","motivo","clasifica","proceso"},G76))))+3*AND(K76>=4,K76<=25),0.5+MIN(1,SUMPRODUCT(--ISNUMBER(SEARCH({"categor","region","región","producto","linea","línea","segmento","canal","ciudad","tienda","sucursal","vendedor","cliente","tipo","marca","zona","sede","courier","transportadora","oficina","trayecto","motivo","clasifica","proceso"},G76)))))+0.004,0) -> 0 | K76: =IF(C76>0,SUMPRODUCT((INDEX(Datos!$A$2:$AN$501,0,37)<>"")/COUNTIF(INDEX(Datos!$A$2:$AN$501,0,37),INDEX(Datos!$A$2:$AN$501,0,37)&"")),0) -> 0 | L76: =IF(E76,1+MIN(1,SUMPRODUCT(--ISNUMBER(SEARCH({"fecha","date","periodo","timestamp"},G76))))+0.004,0) -> 0 | M76: =IF(AND(H76,K76>=2,K76<=15),MIN(1,SUMPRODUCT(--ISNUMBER(SEARCH({"etapa","fase","estado","stage","embudo","funnel","paso","status"},G76))))*(1+0.004),0) -> 0 | N76: =IF(H76,MIN(1,SUMPRODUCT(--ISNUMBER(SEARCH({"departamento","depto","dpto","depart"},G76))))*(1+0.004),0) -> 0 | O76: =IF(F76,MIN(1,SUMPRODUCT(--ISNUMBER(SEARCH({"costo","cost"},G76))))*(1+0.004),0) -> 0 | P76: =IF(B76=$E$6,0,I76+5*MIN(1,SUMPRODUCT(--ISNUMBER(SEARCH({" dias"," días","tiempo","demora","duraci","lead"," horas"},G76))))*(I76>0)) -> 0 | Q76: =IF(B76=$E$9,0,J76) -> 0 | R76: =IF(OR(B76=$E$6,INDEX($I$40:$I$79,MAX(1,$F$6))<12),0,O76) -> 0 | S76: =AND(C76>0,D76<0.5*C76,MIN(1,SUMPRODUCT(--ISNUMBER(SEARCH({"fecha","date","periodo","timestamp"},G76))))>0) -> FALSE
A77: 38 | B77: =IF(INDEX(Datos!$A$1:$AN$1,1,38)="","",INDEX(Datos!$A$1:$AN$1,1,38)&"") | C77: =IF(B77="",0,COUNTA(INDEX(Datos!$A$2:$AN$1048576,0,38))) -> 0 | D77: =IF(B77="",0,COUNT(INDEX(Datos!$A$2:$AN$1048576,0,38))) -> 0 | E77: =AND(C77>0,D77>=0.9*C77,OR(LEFT(CELL("format",INDEX(Datos!$A$2:$AN$2,1,38)),1)="D",MIN(1,SUMPRODUCT(--ISNUMBER(SEARCH({"fecha","date","periodo","timestamp"},G77))))>0)) -> FALSE | F77: =AND(C77>0,D77>=0.9*C77,NOT(E77),MIN(1,SUMPRODUCT(--ISNUMBER(SEARCH({" id "," id"," cod"," nit "," cedula"," cédula"," telefono"," teléfono"," celular"," sku"," factura"," numero"," número"," nro"," año "," ano "," year"," zip"," postal"," documento"," guia"," guía"," orden"," cuenta"," pedido"," radicado"," consecutivo"," omr"," pob "," placa"," referencia"," ref "},G77))))=0,NOT(AND(K77>=20,K77>=0.95*MIN(500,C77),MIN(1,SUMPRODUCT(--ISNUMBER(SEARCH({"venta","ingreso","monto","importe","total","valor","factur","revenue","sales","amount","utilidad","ganancia","gasto"},G77))))+MIN(1,SUMPRODUCT(--ISNUMBER(SEARCH({"precio","price","unit","costo","cost","promedio","tasa","%","edad","calific","rating","puntaje","porcentaje","satisf","nps","score","nota"},G77))))+MIN(1,SUMPRODUCT(--ISNUMBER(SEARCH({"costo","cost"},G77))))+MIN(1,SUMPRODUCT(--ISNUMBER(SEARCH({" dias"," días","tiempo","demora","duraci","lead"," horas"},G77))))+MIN(1,SUMPRODUCT(--ISNUMBER(SEARCH({"cantidad","unidades","qty","peso","kilos"," kg","volumen","stock","existencia","inventario"},G77))))=0))) -> FALSE | G77: =" "&LOWER(SUBSTITUTE(SUBSTITUTE(SUBSTITUTE(B77,"_"," "),"-"," "),"."," "))&" " | H77: =AND(C77>0,D77<0.5*C77) -> FALSE | I77: =IF(F77,2+10*MIN(1,SUMPRODUCT(--ISNUMBER(SEARCH({"venta","ingreso","monto","importe","total","valor","factur","revenue","sales","amount","utilidad","ganancia","gasto"},G77))))+8*MIN(1,SUMPRODUCT(--ISNUMBER(SEARCH({"cantidad","unidades","qty","peso","kilos"," kg","volumen","stock","existencia","inventario"},G77))))*(1-MIN(1,SUMPRODUCT(--ISNUMBER(SEARCH({"venta","ingreso","monto","importe","total","valor","factur","revenue","sales","amount","utilidad","ganancia","gasto"},G77)))))-MIN(1,SUMPRODUCT(--ISNUMBER(SEARCH({"precio","price","unit","costo","cost","promedio","tasa","%","edad","calific","rating","puntaje","porcentaje","satisf","nps","score","nota"},G77))))+0.003,0) -> 0 | J77: =IF(AND(H77,K77>=2),IF(K77<=40,2+10*MIN(1,SUMPRODUCT(--ISNUMBER(SEARCH({"categor","region","región","producto","linea","línea","segmento","canal","ciudad","tienda","sucursal","vendedor","cliente","tipo","marca","zona","sede","courier","transportadora","oficina","trayecto","motivo","clasifica","proceso"},G77))))+3*AND(K77>=4,K77<=25),0.5+MIN(1,SUMPRODUCT(--ISNUMBER(SEARCH({"categor","region","región","producto","linea","línea","segmento","canal","ciudad","tienda","sucursal","vendedor","cliente","tipo","marca","zona","sede","courier","transportadora","oficina","trayecto","motivo","clasifica","proceso"},G77)))))+0.003,0) -> 0 | K77: =IF(C77>0,SUMPRODUCT((INDEX(Datos!$A$2:$AN$501,0,38)<>"")/COUNTIF(INDEX(Datos!$A$2:$AN$501,0,38),INDEX(Datos!$A$2:$AN$501,0,38)&"")),0) -> 0 | L77: =IF(E77,1+MIN(1,SUMPRODUCT(--ISNUMBER(SEARCH({"fecha","date","periodo","timestamp"},G77))))+0.003,0) -> 0 | M77: =IF(AND(H77,K77>=2,K77<=15),MIN(1,SUMPRODUCT(--ISNUMBER(SEARCH({"etapa","fase","estado","stage","embudo","funnel","paso","status"},G77))))*(1+0.003),0) -> 0 | N77: =IF(H77,MIN(1,SUMPRODUCT(--ISNUMBER(SEARCH({"departamento","depto","dpto","depart"},G77))))*(1+0.003),0) -> 0 | O77: =IF(F77,MIN(1,SUMPRODUCT(--ISNUMBER(SEARCH({"costo","cost"},G77))))*(1+0.003),0) -> 0 | P77: =IF(B77=$E$6,0,I77+5*MIN(1,SUMPRODUCT(--ISNUMBER(SEARCH({" dias"," días","tiempo","demora","duraci","lead"," horas"},G77))))*(I77>0)) -> 0 | Q77: =IF(B77=$E$9,0,J77) -> 0 | R77: =IF(OR(B77=$E$6,INDEX($I$40:$I$79,MAX(1,$F$6))<12),0,O77) -> 0 | S77: =AND(C77>0,D77<0.5*C77,MIN(1,SUMPRODUCT(--ISNUMBER(SEARCH({"fecha","date","periodo","timestamp"},G77))))>0) -> FALSE
A78: 39 | B78: =IF(INDEX(Datos!$A$1:$AN$1,1,39)="","",INDEX(Datos!$A$1:$AN$1,1,39)&"") | C78: =IF(B78="",0,COUNTA(INDEX(Datos!$A$2:$AN$1048576,0,39))) -> 0 | D78: =IF(B78="",0,COUNT(INDEX(Datos!$A$2:$AN$1048576,0,39))) -> 0 | E78: =AND(C78>0,D78>=0.9*C78,OR(LEFT(CELL("format",INDEX(Datos!$A$2:$AN$2,1,39)),1)="D",MIN(1,SUMPRODUCT(--ISNUMBER(SEARCH({"fecha","date","periodo","timestamp"},G78))))>0)) -> FALSE | F78: =AND(C78>0,D78>=0.9*C78,NOT(E78),MIN(1,SUMPRODUCT(--ISNUMBER(SEARCH({" id "," id"," cod"," nit "," cedula"," cédula"," telefono"," teléfono"," celular"," sku"," factura"," numero"," número"," nro"," año "," ano "," year"," zip"," postal"," documento"," guia"," guía"," orden"," cuenta"," pedido"," radicado"," consecutivo"," omr"," pob "," placa"," referencia"," ref "},G78))))=0,NOT(AND(K78>=20,K78>=0.95*MIN(500,C78),MIN(1,SUMPRODUCT(--ISNUMBER(SEARCH({"venta","ingreso","monto","importe","total","valor","factur","revenue","sales","amount","utilidad","ganancia","gasto"},G78))))+MIN(1,SUMPRODUCT(--ISNUMBER(SEARCH({"precio","price","unit","costo","cost","promedio","tasa","%","edad","calific","rating","puntaje","porcentaje","satisf","nps","score","nota"},G78))))+MIN(1,SUMPRODUCT(--ISNUMBER(SEARCH({"costo","cost"},G78))))+MIN(1,SUMPRODUCT(--ISNUMBER(SEARCH({" dias"," días","tiempo","demora","duraci","lead"," horas"},G78))))+MIN(1,SUMPRODUCT(--ISNUMBER(SEARCH({"cantidad","unidades","qty","peso","kilos"," kg","volumen","stock","existencia","inventario"},G78))))=0))) -> FALSE | G78: =" "&LOWER(SUBSTITUTE(SUBSTITUTE(SUBSTITUTE(B78,"_"," "),"-"," "),"."," "))&" " | H78: =AND(C78>0,D78<0.5*C78) -> FALSE | I78: =IF(F78,2+10*MIN(1,SUMPRODUCT(--ISNUMBER(SEARCH({"venta","ingreso","monto","importe","total","valor","factur","revenue","sales","amount","utilidad","ganancia","gasto"},G78))))+8*MIN(1,SUMPRODUCT(--ISNUMBER(SEARCH({"cantidad","unidades","qty","peso","kilos"," kg","volumen","stock","existencia","inventario"},G78))))*(1-MIN(1,SUMPRODUCT(--ISNUMBER(SEARCH({"venta","ingreso","monto","importe","total","valor","factur","revenue","sales","amount","utilidad","ganancia","gasto"},G78)))))-MIN(1,SUMPRODUCT(--ISNUMBER(SEARCH({"precio","price","unit","costo","cost","promedio","tasa","%","edad","calific","rating","puntaje","porcentaje","satisf","nps","score","nota"},G78))))+0.002,0) -> 0 | J78: =IF(AND(H78,K78>=2),IF(K78<=40,2+10*MIN(1,SUMPRODUCT(--ISNUMBER(SEARCH({"categor","region","región","producto","linea","línea","segmento","canal","ciudad","tienda","sucursal","vendedor","cliente","tipo","marca","zona","sede","courier","transportadora","oficina","trayecto","motivo","clasifica","proceso"},G78))))+3*AND(K78>=4,K78<=25),0.5+MIN(1,SUMPRODUCT(--ISNUMBER(SEARCH({"categor","region","región","producto","linea","línea","segmento","canal","ciudad","tienda","sucursal","vendedor","cliente","tipo","marca","zona","sede","courier","transportadora","oficina","trayecto","motivo","clasifica","proceso"},G78)))))+0.002,0) -> 0 | K78: =IF(C78>0,SUMPRODUCT((INDEX(Datos!$A$2:$AN$501,0,39)<>"")/COUNTIF(INDEX(Datos!$A$2:$AN$501,0,39),INDEX(Datos!$A$2:$AN$501,0,39)&"")),0) -> 0 | L78: =IF(E78,1+MIN(1,SUMPRODUCT(--ISNUMBER(SEARCH({"fecha","date","periodo","timestamp"},G78))))+0.002,0) -> 0 | M78: =IF(AND(H78,K78>=2,K78<=15),MIN(1,SUMPRODUCT(--ISNUMBER(SEARCH({"etapa","fase","estado","stage","embudo","funnel","paso","status"},G78))))*(1+0.002),0) -> 0 | N78: =IF(H78,MIN(1,SUMPRODUCT(--ISNUMBER(SEARCH({"departamento","depto","dpto","depart"},G78))))*(1+0.002),0) -> 0 | O78: =IF(F78,MIN(1,SUMPRODUCT(--ISNUMBER(SEARCH({"costo","cost"},G78))))*(1+0.002),0) -> 0 | P78: =IF(B78=$E$6,0,I78+5*MIN(1,SUMPRODUCT(--ISNUMBER(SEARCH({" dias"," días","tiempo","demora","duraci","lead"," horas"},G78))))*(I78>0)) -> 0 | Q78: =IF(B78=$E$9,0,J78) -> 0 | R78: =IF(OR(B78=$E$6,INDEX($I$40:$I$79,MAX(1,$F$6))<12),0,O78) -> 0 | S78: =AND(C78>0,D78<0.5*C78,MIN(1,SUMPRODUCT(--ISNUMBER(SEARCH({"fecha","date","periodo","timestamp"},G78))))>0) -> FALSE
A79: 40 | B79: =IF(INDEX(Datos!$A$1:$AN$1,1,40)="","",INDEX(Datos!$A$1:$AN$1,1,40)&"") | C79: =IF(B79="",0,COUNTA(INDEX(Datos!$A$2:$AN$1048576,0,40))) -> 0 | D79: =IF(B79="",0,COUNT(INDEX(Datos!$A$2:$AN$1048576,0,40))) -> 0 | E79: =AND(C79>0,D79>=0.9*C79,OR(LEFT(CELL("format",INDEX(Datos!$A$2:$AN$2,1,40)),1)="D",MIN(1,SUMPRODUCT(--ISNUMBER(SEARCH({"fecha","date","periodo","timestamp"},G79))))>0)) -> FALSE | F79: =AND(C79>0,D79>=0.9*C79,NOT(E79),MIN(1,SUMPRODUCT(--ISNUMBER(SEARCH({" id "," id"," cod"," nit "," cedula"," cédula"," telefono"," teléfono"," celular"," sku"," factura"," numero"," número"," nro"," año "," ano "," year"," zip"," postal"," documento"," guia"," guía"," orden"," cuenta"," pedido"," radicado"," consecutivo"," omr"," pob "," placa"," referencia"," ref "},G79))))=0,NOT(AND(K79>=20,K79>=0.95*MIN(500,C79),MIN(1,SUMPRODUCT(--ISNUMBER(SEARCH({"venta","ingreso","monto","importe","total","valor","factur","revenue","sales","amount","utilidad","ganancia","gasto"},G79))))+MIN(1,SUMPRODUCT(--ISNUMBER(SEARCH({"precio","price","unit","costo","cost","promedio","tasa","%","edad","calific","rating","puntaje","porcentaje","satisf","nps","score","nota"},G79))))+MIN(1,SUMPRODUCT(--ISNUMBER(SEARCH({"costo","cost"},G79))))+MIN(1,SUMPRODUCT(--ISNUMBER(SEARCH({" dias"," días","tiempo","demora","duraci","lead"," horas"},G79))))+MIN(1,SUMPRODUCT(--ISNUMBER(SEARCH({"cantidad","unidades","qty","peso","kilos"," kg","volumen","stock","existencia","inventario"},G79))))=0))) -> FALSE | G79: =" "&LOWER(SUBSTITUTE(SUBSTITUTE(SUBSTITUTE(B79,"_"," "),"-"," "),"."," "))&" " | H79: =AND(C79>0,D79<0.5*C79) -> FALSE | I79: =IF(F79,2+10*MIN(1,SUMPRODUCT(--ISNUMBER(SEARCH({"venta","ingreso","monto","importe","total","valor","factur","revenue","sales","amount","utilidad","ganancia","gasto"},G79))))+8*MIN(1,SUMPRODUCT(--ISNUMBER(SEARCH({"cantidad","unidades","qty","peso","kilos"," kg","volumen","stock","existencia","inventario"},G79))))*(1-MIN(1,SUMPRODUCT(--ISNUMBER(SEARCH({"venta","ingreso","monto","importe","total","valor","factur","revenue","sales","amount","utilidad","ganancia","gasto"},G79)))))-MIN(1,SUMPRODUCT(--ISNUMBER(SEARCH({"precio","price","unit","costo","cost","promedio","tasa","%","edad","calific","rating","puntaje","porcentaje","satisf","nps","score","nota"},G79))))+0.001,0) -> 0 | J79: =IF(AND(H79,K79>=2),IF(K79<=40,2+10*MIN(1,SUMPRODUCT(--ISNUMBER(SEARCH({"categor","region","región","producto","linea","línea","segmento","canal","ciudad","tienda","sucursal","vendedor","cliente","tipo","marca","zona","sede","courier","transportadora","oficina","trayecto","motivo","clasifica","proceso"},G79))))+3*AND(K79>=4,K79<=25),0.5+MIN(1,SUMPRODUCT(--ISNUMBER(SEARCH({"categor","region","región","producto","linea","línea","segmento","canal","ciudad","tienda","sucursal","vendedor","cliente","tipo","marca","zona","sede","courier","transportadora","oficina","trayecto","motivo","clasifica","proceso"},G79)))))+0.001,0) -> 0 | K79: =IF(C79>0,SUMPRODUCT((INDEX(Datos!$A$2:$AN$501,0,40)<>"")/COUNTIF(INDEX(Datos!$A$2:$AN$501,0,40),INDEX(Datos!$A$2:$AN$501,0,40)&"")),0) -> 0 | L79: =IF(E79,1+MIN(1,SUMPRODUCT(--ISNUMBER(SEARCH({"fecha","date","periodo","timestamp"},G79))))+0.001,0) -> 0 | M79: =IF(AND(H79,K79>=2,K79<=15),MIN(1,SUMPRODUCT(--ISNUMBER(SEARCH({"etapa","fase","estado","stage","embudo","funnel","paso","status"},G79))))*(1+0.001),0) -> 0 | N79: =IF(H79,MIN(1,SUMPRODUCT(--ISNUMBER(SEARCH({"departamento","depto","dpto","depart"},G79))))*(1+0.001),0) -> 0 | O79: =IF(F79,MIN(1,SUMPRODUCT(--ISNUMBER(SEARCH({"costo","cost"},G79))))*(1+0.001),0) -> 0 | P79: =IF(B79=$E$6,0,I79+5*MIN(1,SUMPRODUCT(--ISNUMBER(SEARCH({" dias"," días","tiempo","demora","duraci","lead"," horas"},G79))))*(I79>0)) -> 0 | Q79: =IF(B79=$E$9,0,J79) -> 0 | R79: =IF(OR(B79=$E$6,INDEX($I$40:$I$79,MAX(1,$F$6))<12),0,O79) -> 0 | S79: =AND(C79>0,D79<0.5*C79,MIN(1,SUMPRODUCT(--ISNUMBER(SEARCH({"fecha","date","periodo","timestamp"},G79))))>0) -> FALSE

Sheet Motor
A1: Categoría principal | J1: Categoría secundaria | S1: Etapas | AB1: Tendencia | AG1: Participación | AJ1: Composición mensual | AT1: Matriz | AU1: =IF(cFecha=0,"",DATE(YEAR(fMax),MONTH(fMax)-6+1,1)) -> 45748 | AV1: =IF(cFecha=0,"",DATE(YEAR(fMax),MONTH(fMax)-6+2,1)) -> 45778 | AW1: =IF(cFecha=0,"",DATE(YEAR(fMax),MONTH(fMax)-6+3,1)) -> 45809 | AX1: =IF(cFecha=0,"",DATE(YEAR(fMax),MONTH(fMax)-6+4,1)) -> 45839 | AY1: =IF(cFecha=0,"",DATE(YEAR(fMax),MONTH(fMax)-6+5,1)) -> 45870 | AZ1: =IF(cFecha=0,"",DATE(YEAR(fMax),MONTH(fMax)-6+6,1)) -> 45901 | BC1: Mapa de calor | BL1: Mapa por departamento | BS1: Embudo | BX1: Dispersión | CA1: KPIs
AE2: =nomMed -> Ventas | AH2: =nomMed -> Ventas | AM2: =IF(cCat2>0,O3,F3) -> Tecnología | AN2: =IF(cCat2>0,O4,F4) -> Hogar | AO2: =IF(cCat2>0,O5,F5) -> Deportes | AP2: =IF(cCat2>0,O6,F6) -> Moda | AQ2: Otros | AR2: Total | AT2: =IF(cCat1>0,Config!$E$9,"") -> Ciudad | AU2: =IF(AU1="","",CHOOSE(MONTH(AU1),"Ene","Feb","Mar","Abr","May","Jun","Jul","Ago","Sep","Oct","Nov","Dic")&" "&RIGHT(YEAR(AU1),2)) -> Abr 25 | AV2: =IF(AV1="","",CHOOSE(MONTH(AV1),"Ene","Feb","Mar","Abr","May","Jun","Jul","Ago","Sep","Oct","Nov","Dic")&" "&RIGHT(YEAR(AV1),2)) -> May 25 | AW2: =IF(AW1="","",CHOOSE(MONTH(AW1),"Ene","Feb","Mar","Abr","May","Jun","Jul","Ago","Sep","Oct","Nov","Dic")&" "&RIGHT(YEAR(AW1),2)) -> Jun 25 | AX2: =IF(AX1="","",CHOOSE(MONTH(AX1),"Ene","Feb","Mar","Abr","May","Jun","Jul","Ago","Sep","Oct","Nov","Dic")&" "&RIGHT(YEAR(AX1),2)) -> Jul 25 | AY2: =IF(AY1="","",CHOOSE(MONTH(AY1),"Ene","Feb","Mar","Abr","May","Jun","Jul","Ago","Sep","Oct","Nov","Dic")&" "&RIGHT(YEAR(AY1),2)) -> Ago 25 | AZ2: =IF(AZ1="","",CHOOSE(MONTH(AZ1),"Ene","Feb","Mar","Abr","May","Jun","Jul","Ago","Sep","Oct","Nov","Dic")&" "&RIGHT(YEAR(AZ1),2)) -> Sep 25 | BA2: ="Total 6 meses" -> Total 6 meses | BC2: =IF(conHora,"Hora","Mes") -> Hora | BD2: Lun | BE2: Mar | BF2: Mié | BG2: Jue | BH2: Vie | BI2: Sáb | BJ2: Dom | BT2: Relleno | BU2: Registros
A3: 1 | B3: {=IF(cCat1=0,"",IFERROR(INDEX(rCat1,MATCH(0,COUNTIF(B$2:B2,rCat1&"")+(rCat1&""=""),0))&"",""))} -> Bogotá | C3: =IF(B3="","",IF(cMed>0,SUMIFS(rMed,rCat1,B3),COUNTIFS(rCat1,B3))) -> 554388700 | D3: =IF(B3="","",COUNTIF(C$3:C$42,">"&C3)+COUNTIF(C$3:C3,C3)) -> 1 | E3: 1 | F3: =IFERROR(INDEX(B$3:B$42,MATCH(E3,D$3:D$42,0)),"") -> Bogotá | G3: =IFERROR(INDEX(C$3:C$42,MATCH(E3,D$3:D$42,0)),"") -> 554388700 | H3: =IF(G3="","",IFERROR(G3/total,"")) -> 0.27631127 | J3: 1 | K3: {=IF(cCat2=0,"",IFERROR(INDEX(rCat2,MATCH(0,COUNTIF(K$2:K2,rCat2&"")+(rCat2&""=""),0))&"",""))} -> Hogar | L3: =IF(K3="","",IF(cMed>0,SUMIFS(rMed,rCat2,K3),COUNTIFS(rCat2,K3))) -> 257060440 | M3: =IF(K3="","",COUNTIF(L$3:L$42,">"&L3)+COUNTIF(L$3:L3,L3)) -> 2 | N3: 1 | O3: =IFERROR(INDEX(K$3:K$42,MATCH(N3,M$3:M$42,0)),"") -> Tecnología | P3: =IFERROR(INDEX(L$3:L$42,MATCH(N3,M$3:M$42,0)),"") -> 1154656965 | Q3: =IF(P3="","",IFERROR(P3/total,"")) -> 0.57548924 | S3: 1 | T3: {=IF(cEtapa=0,"",IFERROR(INDEX(rEtapa,MATCH(0,COUNTIF(T$2:T2,rEtapa&"")+(rEtapa&""=""),0))&"",""))} -> 3. Pago | U3: =IF(T3="","",COUNTIFS(rEtapa,T3)) -> 372 | V3: =IF(T3="","",COUNTIF(U$3:U$17,">"&U3)+COUNTIF(U$3:U3,U3)) -> 3 | W3: 1 | X3: =IFERROR(INDEX(T$3:T$17,MATCH(W3,V$3:V$17,0)),"") -> 1. Visita | Y3: =IFERROR(INDEX(U$3:U$17,MATCH(W3,V$3:V$17,0)),"") -> 1122 | Z3: =IF(Y3="","",IFERROR(Y3/SUM(U$3:U$17),"")) -> 0.4675 | AB3: =IF(cFecha=0,"",IF(CHOOSE(gIdx,tBase+0,tBase+0,DATE(YEAR(tBase),MONTH(tBase)+0,1),DATE(YEAR(tBase),MONTH(tBase)+0,1),DATE(YEAR(tBase)+0,1,1))>fMax,"",CHOOSE(gIdx,tBase+0,tBase+0,DATE(YEAR(tBase),MONTH(tBase)+0,1),DATE(YEAR(tBase),MONTH(tBase)+0,1),DATE(YEAR(tBase)+0,1,1)))) -> 45383 | AC3: =IF(AB3="","",CHOOSE(gIdx,AB3+1,AB3+7,DATE(YEAR(AB3),MONTH(AB3)+1,1),DATE(YEAR(AB3),MONTH(AB3)+3,1),DATE(YEAR(AB3)+1,1,1))) -> 45413 | AD3: =IF(AB3="","",CHOOSE(MONTH(AB3),"Ene","Feb","Mar","Abr","May","Jun","Jul","Ago","Sep","Oct","Nov","Dic")&" "&RIGHT(YEAR(AB3),2)) -> Abr 24 | AE3: =IF(AB3="",NA(),IF(cMed>0,SUMIFS(rMed,rFecha,">="&AB3,rFecha,"<"&AC3),COUNTIFS(rFecha,">="&AB3,rFecha,"<"&AC3))) -> 118254975 | AF3: =IF(AB3="",NA(),AB3) -> 45383 | AG3: =IF(dona2,O3,F3) -> Tecnología | AH3: =IF(AG3="","",IF(dona2,P3,G3)) -> 1154656965 | AJ3: =IF(cFecha=0,"",DATE(YEAR(fMax),MONTH(fMax)-12+1,1)) -> 45566 | AK3: =IF(AJ3="","",DATE(YEAR(AJ3),MONTH(AJ3)+1,1)) -> 45597 | AL3: =IF(AJ3="","",CHOOSE(MONTH(AJ3),"Ene","Feb","Mar","Abr","May","Jun","Jul","Ago","Sep","Oct","Nov","Dic")&" "&RIGHT(YEAR(AJ3),2)) -> Oct 24 | AM3: =IF(OR($AJ3="",AM$2=""),0,IF(cCat2>0,IF(cMed>0,SUMIFS(rMed,rFecha,">="&$AJ3,rFecha,"<"&$AK3,rCat2,AM$2),COUNTIFS(rFecha,">="&$AJ3,rFecha,"<"&$AK3,rCat2,AM$2)),IF(cMed>0,SUMIFS(rMed,rFecha,">="&$AJ3,rFecha,"<"&$AK3,rCat1,AM$2),COUNTIFS(rFecha,">="&$AJ3,rFecha,"<"&$AK3,rCat1,AM$2)))) -> 74990670 | AN3: =IF(OR($AJ3="",AN$2=""),0,IF(cCat2>0,IF(cMed>0,SUMIFS(rMed,rFecha,">="&$AJ3,rFecha,"<"&$AK3,rCat2,AN$2),COUNTIFS(rFecha,">="&$AJ3,rFecha,"<"&$AK3,rCat2,AN$2)),IF(cMed>0,SUMIFS(rMed,rFecha,">="&$AJ3,rFecha,"<"&$AK3,rCat1,AN$2),COUNTIFS(rFecha,">="&$AJ3,rFecha,"<"&$AK3,rCat1,AN$2)))) -> 9415765 | AO3: =IF(OR($AJ3="",AO$2=""),0,IF(cCat2>0,IF(cMed>0,SUMIFS(rMed,rFecha,">="&$AJ3,rFecha,"<"&$AK3,rCat2,AO$2),COUNTIFS(rFecha,">="&$AJ3,rFecha,"<"&$AK3,rCat2,AO$2)),IF(cMed>0,SUMIFS(rMed,rFecha,">="&$AJ3,rFecha,"<"&$AK3,rCat1,AO$2),COUNTIFS(rFecha,">="&$AJ3,rFecha,"<"&$AK3,rCat1,AO$2)))) -> 9141060 | AP3: =IF(OR($AJ3="",AP$2=""),0,IF(cCat2>0,IF(cMed>0,SUMIFS(rMed,rFecha,">="&$AJ3,rFecha,"<"&$AK3,rCat2,AP$2),COUNTIFS(rFecha,">="&$AJ3,rFecha,"<"&$AK3,rCat2,AP$2)),IF(cMed>0,SUMIFS(rMed,rFecha,">="&$AJ3,rFecha,"<"&$AK3,rCat1,AP$2),COUNTIFS(rFecha,">="&$AJ3,rFecha,"<"&$AK3,rCat1,AP$2)))) -> 13823915 | AQ3: =MAX(0,AR3-SUM(AM3:AP3)) -> 11739880 | AR3: =IF(AJ3="",0,IF(cMed>0,SUMIFS(rMed,rFecha,">="&$AJ3,rFecha,"<"&$AK3),COUNTIFS(rFecha,">="&$AJ3,rFecha,"<"&$AK3))) -> 119111290 | AT3: =F3 -> Bogotá | AU3: =IF(OR($AT3="",AU$1=""),"",IF(cMed>0,SUMIFS(rMed,rCat1,$AT3,rFecha,">="&AU$1,rFecha,"<"&DATE(YEAR(AU$1),MONTH(AU$1)+1,1)),COUNTIFS(rCat1,$AT3,rFecha,">="&AU$1,rFecha,"<"&DATE(YEAR(AU$1),MONTH(AU$1)+1,1)))) -> 30128910 | AV3: =IF(OR($AT3="",AV$1=""),"",IF(cMed>0,SUMIFS(rMed,rCat1,$AT3,rFecha,">="&AV$1,rFecha,"<"&DATE(YEAR(AV$1),MONTH(AV$1)+1,1)),COUNTIFS(rCat1,$AT3,rFecha,">="&AV$1,rFecha,"<"&DATE(YEAR(AV$1),MONTH(AV$1)+1,1)))) -> 32358815 | AW3: =IF(OR($AT3="",AW$1=""),"",IF(cMed>0,SUMIFS(rMed,rCat1,$AT3,rFecha,">="&AW$1,rFecha,"<"&DATE(YEAR(AW$1),MONTH(AW$1)+1,1)),COUNTIFS(rCat1,$AT3,rFecha,">="&AW$1,rFecha,"<"&DATE(YEAR(AW$1),MONTH(AW$1)+1,1)))) -> 30920975 | AX3: =IF(OR($AT3="",AX$1=""),"",IF(cMed>0,SUMIFS(rMed,rCat1,$AT3,rFecha,">="&AX$1,rFecha,"<"&DATE(YEAR(AX$1),MONTH(AX$1)+1,1)),COUNTIFS(rCat1,$AT3,rFecha,">="&AX$1,rFecha,"<"&DATE(YEAR(AX$1),MONTH(AX$1)+1,1)))) -> 19240210 | AY3: =IF(OR($AT3="",AY$1=""),"",IF(cMed>0,SUMIFS(rMed,rCat1,$AT3,rFecha,">="&AY$1,rFecha,"<"&DATE(YEAR(AY$1),MONTH(AY$1)+1,1)),COUNTIFS(rCat1,$AT3,rFecha,">="&AY$1,rFecha,"<"&DATE(YEAR(AY$1),MONTH(AY$1)+1,1)))) -> 31876865 | AZ3: =IF(OR($AT3="",AZ$1=""),"",IF(cMed>0,SUMIFS(rMed,rCat1,$AT3,rFecha,">="&AZ$1,rFecha,"<"&DATE(YEAR(AZ$1),MONTH(AZ$1)+1,1)),COUNTIFS(rCat1,$AT3,rFecha,">="&AZ$1,rFecha,"<"&DATE(YEAR(AZ$1),MONTH(AZ$1)+1,1)))) -> 35966285 | BA3: =IF(AT3="","",SUM(AU3:AZ3)) -> 180492060 | BC3: =IF(conHora,RIGHT("0"&0,2)&":00",IF(1<=12,CHOOSE(1,"Ene","Feb","Mar","Abr","May","Jun","Jul","Ago","Sep","Oct","Nov","Dic"),"")) -> 00:00 | BD3: {=IF(OR(cFecha=0,AND(NOT(conHora),1>12)),"",SUMPRODUCT(IFERROR(ISNUMBER(rFecha)*(WEEKDAY(rFecha,2)=1)*IF(conHora,HOUR(rFecha)=0,MONTH(rFecha)=1)*IF(cMed>0,IF(ISNUMBER(rMed),rMed,0),1),0)))} -> 803400 | BE3: {=IF(OR(cFecha=0,AND(NOT(conHora),1>12)),"",SUMPRODUCT(IFERROR(ISNUMBER(rFecha)*(WEEKDAY(rFecha,2)=2)*IF(conHora,HOUR(rFecha)=0,MONTH(rFecha)=1)*IF(cMed>0,IF(ISNUMBER(rMed),rMed,0),1),0)))} -> 0 | BF3: {=IF(OR(cFecha=0,AND(NOT(conHora),1>12)),"",SUMPRODUCT(IFERROR(ISNUMBER(rFecha)*(WEEKDAY(rFecha,2)=3)*IF(conHora,HOUR(rFecha)=0,MONTH(rFecha)=1)*IF(cMed>0,IF(ISNUMBER(rMed),rMed,0),1),0)))} -> 10614400 | BG3: {=IF(OR(cFecha=0,AND(NOT(conHora),1>12)),"",SUMPRODUCT(IFERROR(ISNUMBER(rFecha)*(WEEKDAY(rFecha,2)=4)*IF(conHora,HOUR(rFecha)=0,MONTH(rFecha)=1)*IF(cMed>0,IF(ISNUMBER(rMed),rMed,0),1),0)))} -> 1100500 | BH3: {=IF(OR(cFecha=0,AND(NOT(conHora),1>12)),"",SUMPRODUCT(IFERROR(ISNUMBER(rFecha)*(WEEKDAY(rFecha,2)=5)*IF(conHora,HOUR(rFecha)=0,MONTH(rFecha)=1)*IF(cMed>0,IF(ISNUMBER(rMed),rMed,0),1),0)))} -> 8034065 | BI3: {=IF(OR(cFecha=0,AND(NOT(conHora),1>12)),"",SUMPRODUCT(IFERROR(ISNUMBER(rFecha)*(WEEKDAY(rFecha,2)=6)*IF(conHora,HOUR(rFecha)=0,MONTH(rFecha)=1)*IF(cMed>0,IF(ISNUMBER(rMed),rMed,0),1),0)))} -> 2306205 | BJ3: {=IF(OR(cFecha=0,AND(NOT(conHora),1>12)),"",SUMPRODUCT(IFERROR(ISNUMBER(rFecha)*(WEEKDAY(rFecha,2)=7)*IF(conHora,HOUR(rFecha)=0,MONTH(rFecha)=1)*IF(cMed>0,IF(ISNUMBER(rMed),rMed,0),1),0)))} -> 3878490 | BL3: San Andrés | BM3: *San Andr?s* | BN3: =IF(cDepto=0,"",IF(cMed>0,SUMIFS(rMed,rDepto,BM3),COUNTIFS(rDepto,BM3))) -> 0 | BO3: =IF(BN3="","",COUNTIF(BN$3:BN$35,">"&BN3)+COUNTIF(BN$3:BN3,BN3)) -> 11 | BP3: =IFERROR(INDEX(BL$3:BL$35,MATCH(1,BO$3:BO$35,0)),"") -> Bogotá D.C. | BQ3: =IFERROR(INDEX(BN$3:BN$35,MATCH(1,BO$3:BO$35,0)),"") -> 554388700 | BS3: =IF(cEtapa=0,"",X3) -> 1. Visita | BT3: =IF(BU3="","",(MAX(BU$3:BU$8)-BU3)/2) -> 0 | BU3: =IF(BS3="","",Y3) -> 1122 | BV3: =IF(BU3="","",BU3/BU$3) -> 1 | BX3: =IF(OR(cMed=0,cMed2=0,1>nFilas),NA(),IF(AND(ISNUMBER(INDEX(rMed2,1)),ISNUMBER(INDEX(rMed,1))),INDEX(rMed2,1),NA())) -> 3 | BY3: =IF(OR(cMed=0,cMed2=0,1>nFilas),NA(),IF(AND(ISNUMBER(INDEX(rMed2,1)),ISNUMBER(INDEX(rMed,1))),INDEX(rMed,1),NA())) -> 776700 | CA3: Actual | CB3: =IF(cFecha=0,0,IF(cMed>0,SUMIFS(rMed,rFecha,">="&mIni,rFecha,"<"&DATE(YEAR(mIni),MONTH(mIni)+1,1)),COUNTIFS(rFecha,">="&mIni,rFecha,"<"&DATE(YEAR(mIni),MONTH(mIni)+1,1)))) -> 95743645
A4: 2 | B4: {=IF(cCat1=0,"",IFERROR(INDEX(rCat1,MATCH(0,COUNTIF(B$2:B3,rCat1&"")+(rCat1&""=""),0))&"",""))} -> Barranquilla | C4: =IF(B4="","",IF(cMed>0,SUMIFS(rMed,rCat1,B4),COUNTIFS(rCat1,B4))) -> 174627110 | D4: =IF(B4="","",COUNTIF(C$3:C$42,">"&C4)+COUNTIF(C$3:C4,C4)) -> 4 | E4: 2 | F4: =IFERROR(INDEX(B$3:B$42,MATCH(E4,D$3:D$42,0)),"") -> Medellín | G4: =IFERROR(INDEX(C$3:C$42,MATCH(E4,D$3:D$42,0)),"") -> 410638375 | H4: =IF(G4="","",IFERROR(G4/total,"")) -> 0.20466509 | J4: 2 | K4: {=IF(cCat2=0,"",IFERROR(INDEX(rCat2,MATCH(0,COUNTIF(K$2:K3,rCat2&"")+(rCat2&""=""),0))&"",""))} -> Juguetes | L4: =IF(K4="","",IF(cMed>0,SUMIFS(rMed,rCat2,K4),COUNTIFS(rCat2,K4))) -> 122933825 | M4: =IF(K4="","",COUNTIF(L$3:L$42,">"&L4)+COUNTIF(L$3:L4,L4)) -> 5 | N4: 2 | O4: =IFERROR(INDEX(K$3:K$42,MATCH(N4,M$3:M$42,0)),"") -> Hogar | P4: =IFERROR(INDEX(L$3:L$42,MATCH(N4,M$3:M$42,0)),"") -> 257060440 | Q4: =IF(P4="","",IFERROR(P4/total,"")) -> 0.12812075 | S4: 2 | T4: {=IF(cEtapa=0,"",IFERROR(INDEX(rEtapa,MATCH(0,COUNTIF(T$2:T3,rEtapa&"")+(rEtapa&""=""),0))&"",""))} -> 1. Visita | U4: =IF(T4="","",COUNTIFS(rEtapa,T4)) -> 1122 | V4: =IF(T4="","",COUNTIF(U$3:U$17,">"&U4)+COUNTIF(U$3:U4,U4)) -> 1 | W4: 2 | X4: =IFERROR(INDEX(T$3:T$17,MATCH(W4,V$3:V$17,0)),"") -> 2. Carrito | Y4: =IFERROR(INDEX(U$3:U$17,MATCH(W4,V$3:V$17,0)),"") -> 641 | Z4: =IF(Y4="","",IFERROR(Y4/SUM(U$3:U$17),"")) -> 0.26708333 | AB4: =IF(cFecha=0,"",IF(CHOOSE(gIdx,tBase+1,tBase+7,DATE(YEAR(tBase),MONTH(tBase)+1,1),DATE(YEAR(tBase),MONTH(tBase)+3,1),DATE(YEAR(tBase)+1,1,1))>fMax,"",CHOOSE(gIdx,tBase+1,tBase+7,DATE(YEAR(tBase),MONTH(tBase)+1,1),DATE(YEAR(tBase),MONTH(tBase)+3,1),DATE(YEAR(tBase)+1,1,1)))) -> 45413 | AC4: =IF(AB4="","",CHOOSE(gIdx,AB4+1,AB4+7,DATE(YEAR(AB4),MONTH(AB4)+1,1),DATE(YEAR(AB4),MONTH(AB4)+3,1),DATE(YEAR(AB4)+1,1,1))) -> 45444 | AD4: =IF(AB4="","",CHOOSE(MONTH(AB4),"Ene","Feb","Mar","Abr","May","Jun","Jul","Ago","Sep","Oct","Nov","Dic")&" "&RIGHT(YEAR(AB4),2)) -> May 24 | AE4: =IF(AB4="",NA(),IF(cMed>0,SUMIFS(rMed,rFecha,">="&AB4,rFecha,"<"&AC4),COUNTIFS(rFecha,">="&AB4,rFecha,"<"&AC4))) -> 146055220 | AF4: =IF(AB4="",NA(),AB4) -> 45413 | AG4: =IF(dona2,O4,F4) -> Hogar | AH4: =IF(AG4="","",IF(dona2,P4,G4)) -> 257060440 | AJ4: =IF(cFecha=0,"",DATE(YEAR(fMax),MONTH(fMax)-12+2,1)) -> 45597 | AK4: =IF(AJ4="","",DATE(YEAR(AJ4),MONTH(AJ4)+1,1)) -> 45627 | AL4: =IF(AJ4="","",CHOOSE(MONTH(AJ4),"Ene","Feb","Mar","Abr","May","Jun","Jul","Ago","Sep","Oct","Nov","Dic")&" "&RIGHT(YEAR(AJ4),2)) -> Nov 24 | AM4: =IF(OR($AJ4="",AM$2=""),0,IF(cCat2>0,IF(cMed>0,SUMIFS(rMed,rFecha,">="&$AJ4,rFecha,"<"&$AK4,rCat2,AM$2),COUNTIFS(rFecha,">="&$AJ4,rFecha,"<"&$AK4,rCat2,AM$2)),IF(cMed>0,SUMIFS(rMed,rFecha,">="&$AJ4,rFecha,"<"&$AK4,rCat1,AM$2),COUNTIFS(rFecha,">="&$AJ4,rFecha,"<"&$AK4,rCat1,AM$2)))) -> 64913430 | AN4: =IF(OR($AJ4="",AN$2=""),0,IF(cCat2>0,IF(cMed>0,SUMIFS(rMed,rFecha,">="&$AJ4,rFecha,"<"&$AK4,rCat2,AN$2),COUNTIFS(rFecha,">="&$AJ4,rFecha,"<"&$AK4,rCat2,AN$2)),IF(cMed>0,SUMIFS(rMed,rFecha,">="&$AJ4,rFecha,"<"&$AK4,rCat1,AN$2),COUNTIFS(rFecha,">="&$AJ4,rFecha,"<"&$AK4,rCat1,AN$2)))) -> 18949995 | AO4: =IF(OR($AJ4="",AO$2=""),0,IF(cCat2>0,IF(cMed>0,SUMIFS(rMed,rFecha,">="&$AJ4,rFecha,"<"&$AK4,rCat2,AO$2),COUNTIFS(rFecha,">="&$AJ4,rFecha,"<"&$AK4,rCat2,AO$2)),IF(cMed>0,SUMIFS(rMed,rFecha,">="&$AJ4,rFecha,"<"&$AK4,rCat1,AO$2),COUNTIFS(rFecha,">="&$AJ4,rFecha,"<"&$AK4,rCat1,AO$2)))) -> 15496805 | AP4: =IF(OR($AJ4="",AP$2=""),0,IF(cCat2>0,IF(cMed>0,SUMIFS(rMed,rFecha,">="&$AJ4,rFecha,"<"&$AK4,rCat2,AP$2),COUNTIFS(rFecha,">="&$AJ4,rFecha,"<"&$AK4,rCat2,AP$2)),IF(cMed>0,SUMIFS(rMed,rFecha,">="&$AJ4,rFecha,"<"&$AK4,rCat1,AP$2),COUNTIFS(rFecha,">="&$AJ4,rFecha,"<"&$AK4,rCat1,AP$2)))) -> 11897690 | AQ4: =MAX(0,AR4-SUM(AM4:AP4)) -> 19648620 | AR4: =IF(AJ4="",0,IF(cMed>0,SUMIFS(rMed,rFecha,">="&$AJ4,rFecha,"<"&$AK4),COUNTIFS(rFecha,">="&$AJ4,rFecha,"<"&$AK4))) -> 130906540 | AT4: =F4 -> Medellín | AU4: =IF(OR($AT4="",AU$1=""),"",IF(cMed>0,SUMIFS(rMed,rCat1,$AT4,rFecha,">="&AU$1,rFecha,"<"&DATE(YEAR(AU$1),MONTH(AU$1)+1,1)),COUNTIFS(rCat1,$AT4,rFecha,">="&AU$1,rFecha,"<"&DATE(YEAR(AU$1),MONTH(AU$1)+1,1)))) -> 30561990 | AV4: =IF(OR($AT4="",AV$1=""),"",IF(cMed>0,SUMIFS(rMed,rCat1,$AT4,rFecha,">="&AV$1,rFecha,"<"&DATE(YEAR(AV$1),MONTH(AV$1)+1,1)),COUNTIFS(rCat1,$AT4,rFecha,">="&AV$1,rFecha,"<"&DATE(YEAR(AV$1),MONTH(AV$1)+1,1)))) -> 13583845 | AW4: =IF(OR($AT4="",AW$1=""),"",IF(cMed>0,SUMIFS(rMed,rCat1,$AT4,rFecha,">="&AW$1,rFecha,"<"&DATE(YEAR(AW$1),MONTH(AW$1)+1,1)),COUNTIFS(rCat1,$AT4,rFecha,">="&AW$1,rFecha,"<"&DATE(YEAR(AW$1),MONTH(AW$1)+1,1)))) -> 16902070 | AX4: =IF(OR($AT4="",AX$1=""),"",IF(cMed>0,SUMIFS(rMed,rCat1,$AT4,rFecha,">="&AX$1,rFecha,"<"&DATE(YEAR(AX$1),MONTH(AX$1)+1,1)),COUNTIFS(rCat1,$AT4,rFecha,">="&AX$1,rFecha,"<"&DATE(YEAR(AX$1),MONTH(AX$1)+1,1)))) -> 24227440 | AY4: =IF(OR($AT4="",AY$1=""),"",IF(cMed>0,SUMIFS(rMed,rCat1,$AT4,rFecha,">="&AY$1,rFecha,"<"&DATE(YEAR(AY$1),MONTH(AY$1)+1,1)),COUNTIFS(rCat1,$AT4,rFecha,">="&AY$1,rFecha,"<"&DATE(YEAR(AY$1),MONTH(AY$1)+1,1)))) -> 15921045 | AZ4: =IF(OR($AT4="",AZ$1=""),"",IF(cMed>0,SUMIFS(rMed,rCat1,$AT4,rFecha,">="&AZ$1,rFecha,"<"&DATE(YEAR(AZ$1),MONTH(AZ$1)+1,1)),COUNTIFS(rCat1,$AT4,rFecha,">="&AZ$1,rFecha,"<"&DATE(YEAR(AZ$1),MONTH(AZ$1)+1,1)))) -> 12965950 | BA4: =IF(AT4="","",SUM(AU4:AZ4)) -> 114162340 | BC4: =IF(conHora,RIGHT("0"&1,2)&":00",IF(2<=12,CHOOSE(2,"Ene","Feb","Mar","Abr","May","Jun","Jul","Ago","Sep","Oct","Nov","Dic"),"")) -> 01:00 | BD4: {=IF(OR(cFecha=0,AND(NOT(conHora),2>12)),"",SUMPRODUCT(IFERROR(ISNUMBER(rFecha)*(WEEKDAY(rFecha,2)=1)*IF(conHora,HOUR(rFecha)=1,MONTH(rFecha)=2)*IF(cMed>0,IF(ISNUMBER(rMed),rMed,0),1),0)))} -> 347200 | BE4: {=IF(OR(cFecha=0,AND(NOT(conHora),2>12)),"",SUMPRODUCT(IFERROR(ISNUMBER(rFecha)*(WEEKDAY(rFecha,2)=2)*IF(conHora,HOUR(rFecha)=1,MONTH(rFecha)=2)*IF(cMed>0,IF(ISNUMBER(rMed),rMed,0),1),0)))} -> 328440 | BF4: {=IF(OR(cFecha=0,AND(NOT(conHora),2>12)),"",SUMPRODUCT(IFERROR(ISNUMBER(rFecha)*(WEEKDAY(rFecha,2)=3)*IF(conHora,HOUR(rFecha)=1,MONTH(rFecha)=2)*IF(cMed>0,IF(ISNUMBER(rMed),rMed,0),1),0)))} -> 919540 | BG4: {=IF(OR(cFecha=0,AND(NOT(conHora),2>12)),"",SUMPRODUCT(IFERROR(ISNUMBER(rFecha)*(WEEKDAY(rFecha,2)=4)*IF(conHora,HOUR(rFecha)=1,MONTH(rFecha)=2)*IF(cMed>0,IF(ISNUMBER(rMed),rMed,0),1),0)))} -> 0 | BH4: {=IF(OR(cFecha=0,AND(NOT(conHora),2>12)),"",SUMPRODUCT(IFERROR(ISNUMBER(rFecha)*(WEEKDAY(rFecha,2)=5)*IF(conHora,HOUR(rFecha)=1,MONTH(rFecha)=2)*IF(cMed>0,IF(ISNUMBER(rMed),rMed,0),1),0)))} -> 0 | BI4: {=IF(OR(cFecha=0,AND(NOT(conHora),2>12)),"",SUMPRODUCT(IFERROR(ISNUMBER(rFecha)*(WEEKDAY(rFecha,2)=6)*IF(conHora,HOUR(rFecha)=1,MONTH(rFecha)=2)*IF(cMed>0,IF(ISNUMBER(rMed),rMed,0),1),0)))} -> 530380 | BJ4: {=IF(OR(cFecha=0,AND(NOT(conHora),2>12)),"",SUMPRODUCT(IFERROR(ISNUMBER(rFecha)*(WEEKDAY(rFecha,2)=7)*IF(conHora,HOUR(rFecha)=1,MONTH(rFecha)=2)*IF(cMed>0,IF(ISNUMBER(rMed),rMed,0),1),0)))} -> 1190320 | BL4: La Guajira | BM4: *Guajira | BN4: =IF(cDepto=0,"",IF(cMed>0,SUMIFS(rMed,rDepto,BM4),COUNTIFS(rDepto,BM4))) -> 0 | BO4: =IF(BN4="","",COUNTIF(BN$3:BN$35,">"&BN4)+COUNTIF(BN$3:BN4,BN4)) -> 12 | BP4: =IFERROR(INDEX(BL$3:BL$35,MATCH(2,BO$3:BO$35,0)),"") -> Antioquia | BQ4: =IFERROR(INDEX(BN$3:BN$35,MATCH(2,BO$3:BO$35,0)),"") -> 410638375 | BS4: =IF(cEtapa=0,"",X4) -> 2. Carrito | BT4: =IF(BU4="","",(MAX(BU$3:BU$8)-BU4)/2) -> 240.5 | BU4: =IF(BS4="","",Y4) -> 641 | BV4: =IF(BU4="","",BU4/BU$3) -> 0.57130125 | BX4: =IF(OR(cMed=0,cMed2=0,2>nFilas),NA(),IF(AND(ISNUMBER(INDEX(rMed2,2)),ISNUMBER(INDEX(rMed,2))),INDEX(rMed2,2),NA())) -> 2 | BY4: =IF(OR(cMed=0,cMed2=0,2>nFilas),NA(),IF(AND(ISNUMBER(INDEX(rMed2,2)),ISNUMBER(INDEX(rMed,2))),INDEX(rMed,2),NA())) -> 150800 | CA4: Anterior | CB4: =IF(cFecha=0,0,IF(cMed>0,SUMIFS(rMed,rFecha,">="&DATE(YEAR(mIni),MONTH(mIni)-1,1),rFecha,"<"&mIni),COUNTIFS(rFecha,">="&DATE(YEAR(mIni),MONTH(mIni)-1,1),rFecha,"<"&mIni))) -> 88947425
